Workbook

Sheet BALANCE_MAYO_2026
D1: INGRESOS | AI1: PROYECTO CORPORACION
C2: INGRESO BAÑOS | G2: INGRESO SAYAUSI | I2: SR. NORMA | N2: Gastos OPSATEL | S2: ANALISIS | T2: DE CUENTAS | U2: OPSATEL | V2: Lab dBLog | Z2: GASTOS PLATAFORMA | AH2: OPSATEL dBLog
A3: COD-CLI | B3: FECHA DE PAGO | C3: Tipo Efectivo/Transferencia | D3: VALOR | E3: COD-CLI | F3: FECHA DE PAGO | G3: Tipo Efectivo/Transferencia | H3: Fecha Colaborador | I3: N° Comp Depósito | J3: VALOR | M3: item | N3: Descripción | O3: fecha | P3: Tipo Efectivo/Transferencia | Q3: valor | T3: SOBRANTE ANTERIOR MES | U3: OPSATEL | V3: Lab dBLog | W3: Pichincha | Z3: item | AA3: Descripcion | AC3: Fecha | AD3: Tipo Efectivo/Transferencia | AE3: valor | AH3: item | AI3: Descripcion | AK3: Fecha | AL3: Tipo Efectivo/Transferencia | AM3: valor
L4: VARIOS | M4: 1 | T4: CAJA CHICA | Y4: GASTOS VARIOS | Z4: 1 | AA4: CLARO PLAN CELU TEC ADMIN | AB4: COTITULARES | AC4: 45389 | AH4: 1 | AI4: WILIAM SANANGO | AK4: 45743
M5: 2 | T5: PICHINCHA | W5: PLUS | Z5: 2 | AH5: 2 | AI5: INTERESES CUENTA | AK5: 45743
M6: 3 | T6: JEP | W6: Proyectos | Z6: 3 | AA6: PLATAFORMA EXT | AB6: PERSONAL | AC6: 45769 | AH6: 1 | AI6: WILIAM SANANGO | AK6: 45791
M7: 4 | T7: SUBTOTAL | Z7: 4 | AA7: DiGITAL OCEAN OPSATEL | AB7: PERSONAL | AC7: 45748 | AH7: 2 | AI7: ELECAUSTRO CAMISAS | AK7: 45792
M8: 5 | T8: RESERVA | Z8: 5 | AA8: GOOGLE ONE DRIVE | AB8: PERSONAL | AC8: 45758 | AH8: 3 | AI8: PROYECTO AG CONSTRUCCIONES | AK8: 45874
M9: 6 | T9: TOTAL | Z9: 6 | AA9: ZAPING SPORTS | AB9: PERSONAL | AC9: 45749 | AH9: 4 | AI9: PROYECTO CLASES SUDAMERICANO | AK9: 45888
M10: 3 | T10: OPSATEL | V10: Lab dBLog | Z10: 7 | AA10: SMARTONE SR. AYALA | AB10: PERSONAL | AC10: 45706 | AH10: 5 | AI10: AYUDA OPSATEL | AK10: 45930
M11: 4 | S11: Caja CHICA | T11: =D19+D22+J19+J22+H38+U4-Q128 -> 254.85 | Z11: 8 | AA11: VPS | AB11: PERSONAL | AC11: 45997 | AH11: 6
M12: 5 | S12: PICHINCHA | T12: =D20+D23+J20+J23+H39+U5-Q129 -> 304.47 | V12: =AB46 -> 27.16 | AH12: 7 | AI12: WILIAM SANANGO | AK12: 45915
M13: 6 | S13: JEP | T13: =D21+D24+J21+J24+H40+U6+AE48-Q130 -> 165.14 | AH13: 8
M14: 7 | AL14: Pichincha | AM14: =SUMIF(AL4:AL13,"Pichincha",AM4:AM13) -> 0
M15: 8 | AG15: GASTOS GENERAL
M16: 9
M17: 10 | S17: TOTAL | T17: =SUM(T11:T13)+V12+V11 -> 751.62 | U17: =SUM(U11:U13)+W12+W11 -> 0 | Z17: 14 | AH17: item | AI17: Descripcion | AK17: Fecha | AL17: Tipo Efectivo/Transferencia | AM17: valor
M18: 11 | S18: CUENTA AUXILIAR | Z18: 15 | AG18: TECNICO | AH18: 1
C19: Efectivo | D19: =SUMIF(BAÑOS!BP2:BP270,C19,BAÑOS!BO2:BO270)+SUMIF(C4:C18,C19,D4:D18) -> 254.85 | F19: MOVIMIENTOS INTERNOS INGRESOS | I19: Efectivo | J19: =SUMIF(SAYAUSI!BP2:BP175,I19,SAYAUSI!BO2:BO175)+SUMIF(G4:G18,I19,J4:J18) -> 0 | M19: 12 | S19: SALDO DISPONIBLE | T19: =T17+V17 -> 751.62 | AD19: Efectivo | AE19: =SUMIF($AD$4:$AD$18,"Efectivo",$AE$4:AE18) -> 0 | AH19: 2
C20: Pichincha | D20: =SUMIF(BAÑOS!BP2:BP270,C20,BAÑOS!BO2:BO270)+SUMIF(C4:C18,C20,D4:D18) -> 248.43 | E20: DE | F20: FECHA DE PAGO | G20: Tipo Efectivo/Transferencia | H20: VALOR | I20: Pichincha | J20: =SUMIF(SAYAUSI!BP2:BP175,I20,SAYAUSI!BO2:BO175)+SUMIF(G4:G18,I20,J4:J18) -> 56.04 | M20: 13 | T20: RESERVA PICHINCHA CLIENTES | AD20: Pichincha | AE20: =SUMIF($AD$4:$AD$18,"Pichincha",$AE$4:AE19) -> 0 | AH20: 3
C21: JEP | D21: =SUMIF(BAÑOS!BP2:BP270,C21,BAÑOS!BO2:BO270)+SUMIF(C4:C18,C21,D4:D18) -> 68.54 | I21: JEP | J21: =SUMIF(SAYAUSI!BP2:BP175,I21,SAYAUSI!BO2:BO175)+SUMIF(G4:G18,I21,J4:J18) -> 84.6 | M21: 14 | T21: RESERVA EFECTIVO CLIENTES | AD21: JEP | AE21: =SUMIF($AD$4:$AD$18,"JEP",$AE$4:AE20) -> 0 | AH21: 4
C22: Extra Efectivo | D22: =SUMIF(BAÑOS!BP2:BP270,C22,BAÑOS!BO2:BO270)+SUMIF(C4:C18,C22,D4:D18) -> 0 | I22: Extra Efectivo | J22: =SUMIF(SAYAUSI!BP2:BP175,I22,SAYAUSI!BO2:BO175)+SUMIF(G4:G18,I22,J4:J18) -> 0 | M22: 1 | AH22: 5
C23: Extra Pichincha | D23: =SUMIF(BAÑOS!BP2:BP270,C23,BAÑOS!BO2:BO270)+SUMIF(C4:C18,C23,D4:D18) -> 0 | I23: Extra Pichincha | J23: =SUMIF(SAYAUSI!BP2:BP175,I23,SAYAUSI!BO2:BO175)+SUMIF(G4:G18,I23,J4:J18) -> 0 | M23: 2 | T23: RECAUDAR | U23: CLIENTES | V23: RECAUDADO | W23: CARTERA X VENCER | AA23: MOVIMIENTOS INTERNOS | AH23: 6
C24: Extra JEP | D24: =SUMIF(BAÑOS!BP2:BP270,C24,BAÑOS!BO2:BO270)+SUMIF(C4:C18,C24,D4:D18) -> 0 | I24: Extra JEP | J24: =SUMIF(SAYAUSI!BP2:BP175,I24,SAYAUSI!BO2:BO175)+SUMIF(G4:G18,I24,J4:J18) -> 0 | M24: 3 | S24: BAÑOS TOTAL | T24: =SUM(BAÑOS!IY2:IY207)+SUM(BAÑOS!JA2:JA207)+SUM(BAÑOS!JB2:JB207) -> 0 | U24: =COUNTIF(BAÑOS!JA2:JA207,"<>") -> 0 | V24: =SUM(BAÑOS!HQ2:HQ185)+SUM(BAÑOS!HS2:HS185) -> 0 | W24: =SUMIF(BAÑOS!HR2:HR185,"",BAÑOS!HU6:HU185) -> 0 | Z24: item | AA24: BANK | AC24: Fecha | AD24: BANK | AE24: valor | AH24: 7
C25: Reserva Pichincha | D25: =SUMIF(BAÑOS!BP2:BP270,C25,BAÑOS!BO2:BO270)+SUMIF(C4:C18,C25,D4:D18) -> 0 | I25: Reserva Pichincha | J25: =SUMIF(SAYAUSI!BP2:BP175,I25,SAYAUSI!BO2:BO175)+SUMIF(G4:G18,I25,J4:J18) -> 0 | L25: SUDA | M25: 1 | S25: SAYAUSI TOTAL | T25: =SUM(SAYAUSI!JR2:JR115)+SUM(SAYAUSI!JT2:JT115)+SUM(SAYAUSI!JU2:JU115) -> 0 | U25: =COUNTIF(SAYAUSI!JT2:JT115,"<>") -> 0 | V25: =SUM(SAYAUSI!ID2:ID109)+SUM(SAYAUSI!IG2:IG109) -> 0 | W25: =SUMIF(SAYAUSI!ID2:ID109,"",SAYAUSI!II2:II109) -> 0 | Y25: TRANSF EGRESOS | Z25: 1 | AH25: 8
C26: Reserva Efectivo | D26: =SUMIF(BAÑOS!BP2:BP270,C26,BAÑOS!BO2:BO270)+SUMIF(C4:C18,C26,D4:D18) -> 0 | I26: Reserva Efectivo | J26: =SUMIF(SAYAUSI!BP2:BP175,I26,SAYAUSI!BO2:BO175)+SUMIF(G4:G18,I26,J4:J18) -> 0 | M26: 2 | S26: PREPAGO | T26: =SUM(D4:D18)+SUM(J4:J18) -> 0 | Z26: 2 | AH26: 9
C27: TOTAL | D27: =SUM(D19:D26) -> 571.82 | I27: TOTAL | J27: =SUM(J19:J26) -> 140.64 | M27: 3 | S27: dBLog PLUS | T27: =SUM(PLATAFORMA!BK2:BK38) -> 0 | Z27: 3 | AH27: 10
L28: HELP PROYECTO | M28: 1 | Z28: 4 | AH28: 11
M29: 2 | Z29: 5 | AH29: 12
M30: 3 | S30: TOTAL | T30: =SUM(T24:T29) -> 0 | U30: =SUM(U24:U25) -> 0 | Z30: 6 | AH30: 13
L31: INVERSION CLIENTES NUEVOS | M31: 1 | S31: GASTOS | T31: =SUM(Q4:Q100)+SUM(AE4:AE18) -> 4674.45 | Z31: 7 | AH31: 14
M32: 2 | Z32: 8 | AH32: 15
M33: 1 | S33: A FAVOR OPSATEL | T33: =T30-T31 -> -4674.45 | Z33: 9 | AH33: 16
M34: 2 | Y34: TRANSF INGRESOS | Z34: 1 | AH34: 1
M35: 3 | Z35: 2 | AH35: 2
M36: 4 | T36: LIMA | U36: LLERENA | V36: SOLANO | W36: PAUL | Z36: 3 | AH36: 3
M37: 5 | S37: ADELANTO1 | W37: 2.75 | Z37: 4 | AH37: 4
G38: Efectivo | H38: =SUMIF(G21:G37,"Efectivo",H21:H37) -> 0 | M38: 6 | S38: OPSATEL | Z38: 5 | AH38: 5
G39: Trans Pichincha | H39: =SUMIF(G21:G37,"Pichincha",H21:H37) -> 0 | M39: 7 | S39: ENTREGADO | Z39: 6 | AH39: 6
G40: Trans JEP | H40: =SUMIF(G21:G37,"JEP",H21:H37) -> 0 | L40: PRESTAMOS | M40: 1 | S40: ADELANTO 1 | AD40: Efectivo EGRESOS | AE40: =SUMIF($AD$25:$AD$33,"Efectivo",$AE$25:$AE$33) -> 0 | AH40: 1
G41: Total Efectivo | H41: =D19+H38+J19 -> 254.85 | M41: 2 | S41: ADELANTO 2 | AD41: Pichincha EGRESOS | AE41: =SUMIF($AD$25:$AD$33,"Pichincha",$AE$25:$AE$33) -> 0 | AH41: 2
G42: Total Trans Pichincha | H42: =D20+H39+J20 -> 304.47 | M42: 3 | S42: ADELANTO | AD42: JEP EGRESOS | AE42: =SUMIF($AD$25:$AD$33,"JEP",$AE$25:$AE$33) -> 0 | AH42: 3
G43: Total Trans JEP | H43: =D21+H40+J21 -> 153.14 | M43: 4 | S43: ADELANTO 2 | AD43: Efetivo INGRESOS | AE43: =SUMIF($AD$34:$AD$39,"Efectivo",$AE$34:$AE$39) -> 0 | AH43: 4
M44: 5 | S44: ADELANTO 3 | AD44: Pichincha INGRESOS | AE44: =SUMIF($AD$34:$AD$39,"Pichincha",$AE$34:$AE$39) -> 0 | AH44: 1
M45: 6 | S45: ADELANTO 4 | AD45: JEP INGRESOS | AE45: =SUMIF($AD$34:$AD$39,"JEP",$AE$34:$AE$39) -> 0 | AH45: 2
M46: 7 | S46: OPSATEL | AA46: TOTAL | AB46: =SUM(AE46:AE47) -> 27.16 | AD46: Efectivo | AE46: =SUMIF(PLATAFORMA!AX2:AX60,AD46,PLATAFORMA!AW2:AW60)+SUMIF(BAÑOS!BS2:BS270,AD46,BAÑOS!BR2:BR270)+SUMIF(SAYAUSI!BS2:BS175,AD46,SAYAUSI!BR2:BR175)-AE19-AE40+AE43 -> 6 | AH46: 3
M47: 8 | T47: =SUM(T37:T46) -> 0 | U47: =SUM(U37:U46) -> 0 | V47: =SUM(V37:V46) -> 0 | AD47: Pichincha | AE47: =SUMIF(PLATAFORMA!AX2:AX60,AD47,PLATAFORMA!AW2:AW60)+SUMIF(BAÑOS!BS2:BS270,AD47,BAÑOS!BR2:BR270)+SUMIF(SAYAUSI!BS2:BS175,AD47,SAYAUSI!BR2:BR175)-AE20-AE41+AE44 -> 21.16 | AH47: 1
M48: 9 | AD48: JEP | AE48: =SUMIF(PLATAFORMA!AX2:AX60,AD48,PLATAFORMA!AW2:AW60)+SUMIF(BAÑOS!BS2:BS270,AD48,BAÑOS!BR2:BR270)+SUMIF(SAYAUSI!BS2:BS175,AD48,SAYAUSI!BR2:BR175)-AE21-AE42+AE45 -> 12 | AH48: 2
M49: 10 | AH49: 3
M50: 11 | AH50: 4
AH51: 5
L52: OPSATEL SERVIDOR OLT | M52: 1 | AH52: 2
M53: 2 | AH53: 6
M54: 3 | AH54: 7
M55: 4 | AH55: 3
M56: 5 | AH56: 4
M57: 6 | AG57: IMPORTACION | AH57: 1
M58: 7 | AH58: 2
M59: 8 | AH59: 3
M60: 9 | AH60: 4
M61: 10 | AH61: 5
M62: 11 | AH62: 6
L63: FIJOS | M63: 1C | N63: PAGO CREDITO NODO SAYAUSI RIOBAMBA SOLANO | O63: 45999 | Q63: 267.41 | AH63: 7
M64: 2 C | N64: LIKENET | O64: 46003 | Q64: =24.64+0.41 -> 25.05 | AH64: 8
M65: 3 C | N65: ARRIENDO LUZ | O65: 46004 | Q65: 76.08 | AH65: 9
M66: 4 C | N66: ARRIENDO LOCAL | O66: 46001 | Q66: 150.41 | AH66: 10
M67: 5 C | N67: DEPARTAMENTO JURIDICO | O67: 46008 | Q67: 200 | AH67: 11
M68: 6 C | AH68: 5
M69: 7 C | AH69: 6
M70: 8 C | N70: CREDITO JEP J | O70: 46006 | Q70: 283.66 | AH70: 7
M71: 9 C | N71: CREDITO RIOBAMBA | O71: 46010 | Q71: 476.38 | AH71: 8
M72: 10 C | N72: LLERENA | O72: 46003 | Q72: 360 | AH72: 1
M73: 11 C | N73: SOLANO | O73: 46008 | Q73: 360 | AH73: 2
M74: 12 C | N74: LIMA | O74: 46006 | Q74: 360 | AH74: 3
M75: 13 C | AG75: MARKETING | AH75: 1
M76: 14 C | AH76: 2
M77: 15 C | N77: MARKETING OPSATEL | O77: 46010 | Q77: 70 | AH77: 3
M78: 16 C | AH78: 4
M79: 17 C | N79: NEDETEL | O79: 46012 | Q79: 906.75 | AH79: 5
M80: 18 C | N80: CONTADORA | O80: 46017 | Q80: 42.58 | AH80: 6
M81: 19 C | N81: LUZ SAYAUSI | O81: 46018 | Q81: 53.88 | AH81: 7
M82: 20 C | N82: SOLANO | O82: 46021 | Q82: 17.25 | AH82: 8
M83: 21 C | N83: LLERENA | O83: 46021 | Q83: 360 | AH83: 9
M84: 22 C | N84: JOHN | O84: 46021 | Q84: 25 | AH84: 10
M85: 23 C | N85: HELP PAUL TEC | O85: 46022 | Q85: 600 | AH85: 11
M86: 24 C | AH86: 13
M87: 25 C | AH87: 14
L88: IMPREVISTOS | M88: 1D | N88: GASOLINA | O88: 45992 | Q88: 20 | AH88: 15
M89: 2D | N89: GASOLINA | O89: 45995 | Q89: 20 | AH89: 16
M90: 3D | AH90: 17
M91: 4D | AH91: 18
M92: 5D | AH92: 19
M93: 6D | AH93: 20
M94: 7D | AH94: 21
M95: 8D | AH95: 22
M96: 9D | AH96: 23
M97: 10D | AH97: 24
M98: 11D | AH98: 25
M99: 12D | AH99: 26
M100: 13D | AG100: VARIOS | AH100: 27
...

Sheet BAÑOS
B1: NAME | C1: IP | D1: ESTADO | E1: CED | F1: TIEMPO (MESES) | G1: DOCUMENTS | H1: PARISH | I1: RENT | J1: DIRECTION | K1: MAIL | L1: CEL | M1: CUENTA | N1: INSTALATION DATE | O1: PLAN | P1: INS_PAYMENT | Q1: SALDO | R1: FACT DIC | S1: INTERNET PAYMENT | T1: APP | U1: PAYMENT DATE | V1: CLIENT PAYMENT DATE | W1: INTERNET PAYMENT | X1: BANK | Y1: COD | Z1: PLUS | AA1: BANK_PLUS | AB1: SALDO | AC1: FACT JANUARY | AD1: INTERNET PAYMENT | AE1: APP | AF1: PAYMENT DATE | AG1: CLIENT PAYMENT DATE | AH1: INTERNET PAYMENT | AI1: BANK | AJ1: COD | AK1: PLUS | AL1: BANK_PLUS | AM1: SALDO | AN1: FACTURAS | AO1: INTERNET PAYMENT | AP1: APP | AQ1: PAYMENT DATE | AR1: CLIENT PAYMENT DATE | AS1: INTERNET PAYMENT | AT1: BANK | AU1: COD | AV1: PLUS | AW1: BANK_PLUS | AX1: SALDO | AY1: FACTURAS | AZ1: INTERNET PAYMENT | BA1: APP | BB1: PAYMENT DATE | BC1: CLIENT PAYMENT DATE | BD1: INTERNET PAYMENT | BE1: BANK | BF1: COD | BG1: PLUS | BH1: BANK_PLUS | BI1: SALDO | BJ1: FACTURAS | BK1: INTERNET PAYMENT | BL1: APP | BM1: PAYMENT DATE | BN1: CLIENT PAYMENT DATE | BO1: INTERNET PAYMENT | BP1: BANK | BQ1: COD | BR1: PLUS | BS1: BANK_PLUS | BT1: SALDO | BU1: FACTURAS
A2: =IFERROR(__xludf.DUMMYFUNCTION("IMPORTRANGE(""https://https://docs.google.com/spreadsheets/d/1GLbJTdVpWS8XRg8Za_otK8cqLfTYxobGAYdYQwJylW8/edit?gid=0#gid=0"", ""MAIN!B2"")"),"C01") -> C01 | B2: SAMANIEGO FEIJO ANDREA BELEN | C2: 172.17.2.2 | D2: ACTIVO | E2: F | F2: 18 | G2: 0105504971 | H2: EL SAGRARIO | I2: NO | J2: RAFAEL MARI ARIZAGA Y VARGAS MACHUCA | K2: beley18@hotmail.com | L2: 0986944564 | N2: 45086 | O2: 650M/650M | Q2: 0 | R2: C02245 | S2: 23 | T2: 0 | U2: 46036 | AB2: =Q2+S2+T2-W2-Z2 -> 23 | AC2: C02352 | AD2: 23 | AE2: 0 | AF2: 46067 | AG2: 46078 | AH2: 46 | AI2: Pichincha | AM2: =(AB2+AD2+AE2)-(AH2+AK2) -> 0 | AN2: SIN FACTURA | AO2: 23 | AP2: 0 | AQ2: 46095 | AR2: 26/3/2026 | AS2: 23 | AT2: Pichincha | AX2: =(AM2+AO2+AP2)-(AS2+AV2) -> 0 | AY2: SIN FACTURA | AZ2: 23 | BA2: 0 | BB2: 46126 | BC2: 16/4/2026 | BD2: 23 | BE2: Pichincha | BI2: =(AX2+AZ2+BA2)-(BD2+BG2) -> 0 | BK2: 23 | BL2: 0 | BM2: 46156 | BT2: =(BI2+BK2+BL2)-(BO2+BR2) -> 23
A3: =IFERROR(__xludf.DUMMYFUNCTION("IMPORTRANGE(""https://https://docs.google.com/spreadsheets/d/1GLbJTdVpWS8XRg8Za_otK8cqLfTYxobGAYdYQwJylW8/edit?gid=0#gid=0"", ""MAIN!B3"")"),"C02") -> C02 | B3: HERNANDEZ SALAS NORA GABRIELA | C3: 10.65.4.4:5151 | D3: ACTIVO | E3: F | F3: 20 | G3: 1715444947 | H3: EL SAGRARIO | I3: SI | J3: RAFAEL MARI ARIZAGA Y VARGAS MACHUCA | K3: norahs1980@hotmail.com | L3: 0994089449 0963182639 | O3: 650M/650M | Q3: 0 | S3: 23 | T3: 0 | U3: 46036 | V3: 46044 | W3: 23 | X3: Pichincha | AB3: =Q3+S3+T3-W3-Z3 -> 0 | AC3: SIN FACTURA | AD3: 23 | AE3: 0 | AF3: 46067 | AG3: 46073 | AH3: 23 | AI3: Pichincha | AM3: =(AB3+AD3+AE3)-(AH3+AK3) -> 0 | AN3: SIN FACTURA | AO3: 23 | AP3: 0 | AQ3: 46095 | AR3: 46100 | AS3: 23 | AT3: Pichincha | AX3: =(AM3+AO3+AP3)-(AS3+AV3) -> 0 | AY3: SIN FACTURA | AZ3: 23 | BA3: 0 | BB3: 46126 | BC3: 28/4/2026 | BD3: 23 | BE3: Pichincha | BI3: =(AX3+AZ3+BA3)-(BD3+BG3) -> 0 | BK3: 23 | BL3: 0 | BM3: 46156 | BT3: =(BI3+BK3+BL3)-(BO3+BR3) -> 23
A4: =IFERROR(__xludf.DUMMYFUNCTION("IMPORTRANGE(""https://https://docs.google.com/spreadsheets/d/1GLbJTdVpWS8XRg8Za_otK8cqLfTYxobGAYdYQwJylW8/edit?gid=0#gid=0"", ""MAIN!B4"")"),"C03") -> C03 | B4: GUTIERREZ ARIAS JOSE ROLANDO | C4: 172.17.1.3 | D4: ACTIVO | E4: M | F4: 24 | G4: 0100758994 | H4: EL SAGRARIO | I4: SI | J4: RAFAEL MARI ARIZAGA Y MARIANO CUEVA | L4: 0992257063 | M4: 199cejoseg | N4: 45743 | O4: 100M/100M | Q4: -0.5 | S4: 17.25 | T4: 0 | U4: 46032 | V4: 46049 | W4: 17 | X4: Pichincha | AB4: =Q4+S4+T4-W4-Z4 -> -0.25 | AC4: SIN FACTURA | AD4: 17.25 | AE4: 0 | AF4: 46063 | AG4: 46080 | AH4: 17.25 | AI4: Pichincha | AM4: =(AB4+AD4+AE4)-(AH4+AK4) -> -0.25 | AN4: SIN FACTURA | AO4: 17.25 | AP4: 0 | AQ4: 46091 | AR4: 9/3/2026 | AS4: 17.25 | AT4: Pichincha | AX4: =(AM4+AO4+AP4)-(AS4+AV4) -> -0.25 | AY4: SIN FACTURA | AZ4: 17.25 | BA4: 0 | BB4: 46122 | BC4: 11/4/2026 | BD4: 17.25 | BE4: Pichincha | BI4: =(AX4+AZ4+BA4)-(BD4+BG4) -> -0.25 | BK4: 17.25 | BL4: 0 | BM4: 46152 | BT4: =(BI4+BK4+BL4)-(BO4+BR4) -> 17
A5: =IFERROR(__xludf.DUMMYFUNCTION("IMPORTRANGE(""https://https://docs.google.com/spreadsheets/d/1GLbJTdVpWS8XRg8Za_otK8cqLfTYxobGAYdYQwJylW8/edit?gid=0#gid=0"", ""MAIN!B5"")"),"C04") -> C04 | B5: MARQUEZ MARQUEZ ROSA CARMELA | C5: 172.17.1.2 | D5: ACTIVO | E5: F | G5: 0703952135 | H5: BAÑOS | I5: SI | J5: VIA MINAS | K5: rosacarmelamarquezmarquez@gmail.com | L5: 0995398106 | N5: 45209 | O5: 650M/650M | P5: GRATIS | Q5: 0 | R5: C02246 | S5: 23 | T5: 0 | U5: 46032 | V5: 46032 | W5: 23 | X5: JEP | AB5: =Q5+S5+T5-W5-Z5 -> 0 | AC5: C02353 | AD5: 23 | AE5: 0 | AF5: 46063 | AG5: 46060.415 | AH5: 23 | AI5: JEP | AM5: =(AB5+AD5+AE5)-(AH5+AK5) -> 0 | AN5: C02456 | AO5: 23 | AP5: 0 | AQ5: 46091 | AR5: 9/3/2026 | AS5: 23 | AT5: JEP | AX5: =(AM5+AO5+AP5)-(AS5+AV5) -> 0 | AY5: C02574 | AZ5: =23+15 -> 38 | BA5: 0 | BB5: 46122 | BC5: 7/4/2026 | BD5: =23+15 -> 38 | BE5: JEP | BI5: =(AX5+AZ5+BA5)-(BD5+BG5) -> 0 | BK5: =23+15 -> 38 | BL5: 0 | BM5: 46152 | BT5: =(BI5+BK5+BL5)-(BO5+BR5) -> 38
A6: 002 | B6: MACAS NAMCELA MARIA MERCEDES | C6: 172.16.0.3 | D6: INACTIVO | G6: 1103427447 | H6: BAÑOS | I6: SI | J6: SECTOR EL CHORRO CALLE GUADALUPANA | K6: rosamarianamacasnamcela@gmail.com | L6: 0986347428 0967759439 0985702275 | N6: 44347 | O6: 100M/100M | P6: 37 | Q6: 0 | T6: 0 | AB6: =Q6+S6+T6-W6-Z6 -> 0 | AC6: SIN FACTURA | AE6: 0 | AM6: =(AB6+AD6+AE6)-(AH6+AK6) -> 0 | AN6: SIN FACTURA | AP6: 0 | AX6: =(AM6+AO6+AP6)-(AS6+AV6) -> 0 | AY6: SIN FACTURA | BA6: 0 | BI6: =(AX6+AZ6+BA6)-(BD6+BG6) -> 0 | BL6: 0 | BT6: =(BI6+BK6+BL6)-(BO6+BR6) -> 0
A7: 003 | B7: CASTILLO GUAMAN MIRIAM PATRICIA | C7: 172.16.1.2 | D7: ACTIVO | E7: F | G7: 0103832432 | H7: BAÑOS | I7: NO | J7: AV. RICARDO DURAN Y CALLE LA CALIZA (ESQUINA) | K7: miacastillo27@hotmail.com | L7: 0992296564 0929902571 | M7: 03bamiriamc | N7: 44348 | O7: 100M/100M | P7: 37 | Q7: 0 | R7: C02247 | S7: 23 | T7: 0 | U7: 46036 | V7: 46037 | W7: 23 | X7: Efectivo | AB7: =Q7+S7+T7-W7-Z7 -> 0 | AC7: C02354 | AD7: 23 | AE7: 0 | AF7: 46067 | AG7: 46073.687 | AH7: 23 | AI7: Efectivo | AM7: =(AB7+AD7+AE7)-(AH7+AK7) -> 0 | AN7: C02457 | AO7: 23 | AP7: 0 | AQ7: 46095 | AR7: 19/3/2026 | AS7: 23 | AT7: Efectivo | AX7: =(AM7+AO7+AP7)-(AS7+AV7) -> 0 | AY7: C02575 | AZ7: 23 | BA7: 0 | BB7: 46126 | BC7: 16/4/2026 | BD7: 23 | BE7: Efectivo | BI7: =(AX7+AZ7+BA7)-(BD7+BG7) -> 0 | BJ7: C02687 | BK7: 23 | BL7: 0 | BM7: 46156 | BT7: =(BI7+BK7+BL7)-(BO7+BR7) -> 23
A8: 004 | B8: CURIPOMA MEJICANO LORGIA | C8: 172.16.0.4 | D8: INACTIVO | E8: F | G8: 1715117121 | H8: YANUNCAY | I8: NO | J8: YANUNCAY | K8: curipomalorgia77@gmail.com | L8: 0999463238 0994616304 | M8: 4bacuripomal | N8: 44349 | O8: 650M/650M | P8: 37 | Q8: 0 | T8: 0 | AB8: =Q8+S8+T8-W8-Z8 -> 0 | AC8: SIN FACTURA | AE8: 0 | AM8: =(AB8+AD8+AE8)-(AH8+AK8) -> 0 | AN8: SIN FACTURA | AP8: 0 | AX8: =(AM8+AO8+AP8)-(AS8+AV8) -> 0 | AY8: SIN FACTURA | BA8: 0 | BI8: =(AX8+AZ8+BA8)-(BD8+BG8) -> 0 | BL8: 0 | BT8: =(BI8+BK8+BL8)-(BO8+BR8) -> 0
A9: 006 | B9: AUCAPIÑA NARVAEZ GLADYS VIRGINIA | C9: 172.16.3.2 | D9: ACTIVO | E9: F | G9: 1722452420 | H9: YANUNCAY | I9: NO | J9: JUEGO DE DAMAS Y TRES EN RAYA | K9: elizabethaucapina4@gmail.com | L9: 0969018149 096293803 | M9: 06bagladysa | N9: 44356 | O9: 650M/650M | P9: 37 | Q9: 0 | R9: C02248 | S9: 23 | T9: 0 | U9: 46031 | V9: 46028 | W9: 23 | X9: JEP | AB9: =Q9+S9+T9-W9-Z9 -> 0 | AC9: C02356 | AD9: 23 | AE9: 0 | AF9: 46062 | AG9: 46061 | AH9: 23 | AI9: JEP | AM9: =(AB9+AD9+AE9)-(AH9+AK9) -> 0 | AN9: C02458 | AO9: 23 | AP9: 0 | AQ9: 46090 | AR9: 8/3/2026 | AS9: 23 | AT9: JEP | AX9: =(AM9+AO9+AP9)-(AS9+AV9) -> 0 | AY9: C02576 | AZ9: 23 | BA9: 0 | BB9: 46121 | BC9: 7/4/2026 | BD9: 23 | BE9: JEP | BI9: =(AX9+AZ9+BA9)-(BD9+BG9) -> 0 | BJ9: C02688 | BK9: 23 | BL9: 0 | BM9: 46151 | BT9: =(BI9+BK9+BL9)-(BO9+BR9) -> 23
A10: 008 | B10: URGILES OTORONGO JUAN CARLOS | C10: 172.16.2.10 | D10: ACTIVO | E10: M | G10: 0105921860 | H10: BAÑOS | I10: NO | J10: PASEO DE LA GUADALUPANA Y CAMINO A NARANCAY ALTO (INTERSECCION) | K10: juanurgiles4@gmail.com | L10: 0992347655 | M10: 08bacarlos | N10: 44363 | O10: 650M/650M | P10: 37 | Q10: 0 | S10: 25 | T10: 2 | U10: 46041 | V10: 46048.731 | W10: 20 | X10: Efectivo | AB10: =Q10+S10+T10-W10-Z10 -> 7 | AC10: SIN FACTURA | AD10: 25 | AE10: 2 | AF10: 46072 | AG10: 46077 | AH10: =20+14 -> 34 | AI10: Efectivo | AM10: =(AB10+AD10+AE10)-(AH10+AK10) -> 0 | AN10: SIN FACTURA | AO10: 25 | AP10: 2 | AQ10: 46100 | AR10: 46107.74 | AS10: 27 | AT10: Efectivo | AX10: =(AM10+AO10+AP10)-(AS10+AV10) -> 0 | AY10: SIN FACTURA | AZ10: 25 | BA10: 2 | BB10: 46131 | BC10: 28/4/2026 | BD10: 23 | BE10: Efectivo | BI10: =(AX10+AZ10+BA10)-(BD10+BG10) -> 4 | BK10: 25 | BL10: 2 | BM10: 46161 | BT10: =(BI10+BK10+BL10)-(BO10+BR10) -> 31
A11: 010 | B11: YUMBLA CHILLOGALLI DIEGO FERNANDO | C11: 172.16.6.6 | D11: ACTIVO | E11: M | G11: 0105541320 | H11: BAÑOS | I11: SI | J11: RICARDO DURAN | K11: diferyumbla@gmail.com | L11: 0995461082 | M11: 010badiegoy | N11: 45548 | O11: 100M/100M | P11: GRATIS | Q11: 0 | R11: C02185 | S11: 17.25 | T11: 2 | U11: 46037 | V11: 46031 | W11: 17.25 | X11: Pichincha | Z11: 2 | AA11: Pichincha | AB11: =Q11+S11+T11-W11-Z11 -> 0 | AC11: SIN FACTURA | AD11: 17.25 | AE11: 2 | AF11: 46068 | AG11: 46076 | AH11: 19.25 | AI11: Pichincha | AM11: =(AB11+AD11+AE11)-(AH11+AK11) -> 0 | AN11: SIN FACTURA | AO11: 17.25 | AP11: 2 | AQ11: 46096 | AR11: 10/3/2026 | AS11: 17.25 | AT11: Pichincha | AV11: 2 | AW11: Pichincha | AX11: =(AM11+AO11+AP11)-(AS11+AV11) -> 0 | AY11: SIN FACTURA | AZ11: 17.25 | BA11: 2 | BB11: 46127 | BC11: 46119.568 | BD11: 17.25 | BE11: Efectivo | BI11: =(AX11+AZ11+BA11)-(BD11+BG11) -> 2 | BK11: 17.25 | BL11: 2 | BM11: 46157 | BT11: =(BI11+BK11+BL11)-(BO11+BR11) -> 21.25
A12: 011 | B12: ORDOÑEZ SIGUA CARMEN LETICIA | C12: 172.16.2.2 | D12: ACTIVO | E12: F | F12: 24 | G12: 0106447535 | H12: BAÑOS | I12: SI | J12: GUADALUPANO ALTO CALLE EL CALVARIO | K12: wpalvarezn@gmail.com | L12: 0995516478 0995183363 | N12: 45666 | O12: 650M/650M | P12: GRATIS | Q12: 0 | R12: C02186 | S12: 17.25 | T12: 0 | U12: 46041 | V12: 46045 | W12: 17.25 | X12: Pichincha | AB12: =Q12+S12+T12-W12-Z12 -> 0 | AC12: C02297 | AD12: 17.25 | AE12: 0 | AF12: 46072 | AG12: 46076 | AH12: 17.25 | AI12: Efectivo | AM12: =(AB12+AD12+AE12)-(AH12+AK12) -> 0 | AN12: C02407 | AO12: 17.25 | AP12: 0 | AQ12: 46100 | AR12: 46107.359 | AS12: 17.25 | AT12: Efectivo | AX12: =(AM12+AO12+AP12)-(AS12+AV12) -> 0 | AY12: C02520 | AZ12: 17.25 | BA12: 0 | BB12: 46131 | BC12: 23/4/2026 | BD12: 17.25 | BE12: Pichincha | BI12: =(AX12+AZ12+BA12)-(BD12+BG12) -> 0 | BJ12: C02634 | BK12: 17.25 | BL12: 0 | BM12: 46161 | BT12: =(BI12+BK12+BL12)-(BO12+BR12) -> 17.25
A13: 012 | B13: ALVAREZ VELECELA KEVIN ALEXANDER | C13: 172.16.2.3 | D13: ACTIVO | E13: F | F13: 24 | G13: 0150675601 | H13: BAÑOS | I13: NO | J13: GUADALUPANO ALTO CALLE EL CALVARIO | K13: ke266@aicloud.com | L13: 0981087927 | N13: 46059 | O13: 100M/100M | P13: GRATIS | Q13: 0 | S13: 20.54 | T13: 0 | U13: 46032 | AB13: =Q13+S13+T13-W13-Z13 -> 20.54 | AC13: C02319 | AD13: 17.25 | AE13: 0 | AF13: 46063 | AG13: 46059 | AH13: =20.54+17.25 -> 37.79 | AI13: Efectivo | AM13: =(AB13+AD13+AE13)-(AH13+AK13) -> 0 | AN13: SIN FACTURA | AO13: 17.25 | AP13: 0 | AQ13: 46091 | AR13: 46105.473 | AS13: 20.54 | AT13: Efectivo | AX13: 0 | AY13: SIN FACTURA | AZ13: 17.25 | BA13: 0 | BB13: 46122 | BC13: 20/04/2026 | BD13: 17.25 | BE13: JEP | BI13: =(AX13+AZ13+BA13)-(BD13+BG13) -> 0 | BK13: 17.25 | BL13: 0 | BM13: 46152 | BT13: =(BI13+BK13+BL13)-(BO13+BR13) -> 17.25
A14: 013 | B14: LOJANO SANCHEZ MARIA ANGELITA | C14: 172.16.2.4 | D14: ACTIVO | E14: F | G14: 0102986619 | H14: BAÑOS | I14: NO | J14: GUADALUPANO ALTO CALLE EL CALVARIO | K14: facturas.labsll@gmail.com | L14: 0968375793 0991434170 0993528296 | N14: 44383 | O14: 100M/100M | P14: GRATIS | Q14: 0 | S14: 17.25 | T14: 0 | U14: 46031 | V14: 46266 | W14: 17.25 | X14: Efectivo | AB14: =Q14+S14+T14-W14-Z14 -> 0 | AC14: SIN FACTURA | AD14: 17.25 | AE14: 0 | AF14: 46062 | AG14: 46064 | AH14: 17.25 | AI14: Efectivo | AM14: =(AB14+AD14+AE14)-(AH14+AK14) -> 0 | AN14: SIN FACTURA | AO14: 17.25 | AP14: 0 | AQ14: 46090 | AR14: 10/3/2026 | AS14: 17.25 | AT14: Efectivo | AX14: =(AM14+AO14+AP14)-(AS14+AV14) -> 0 | AY14: SIN FACTURA | AZ14: 17.25 | BA14: 0 | BB14: 46121 | BC14: 46122.393 | BD14: 17.25 | BE14: Efectivo | BI14: =(AX14+AZ14+BA14)-(BD14+BG14) -> 0 | BK14: 17.25 | BL14: 0 | BM14: 46151 | BT14: =(BI14+BK14+BL14)-(BO14+BR14) -> 17.25
A15: 016 | B15: ORDOÑEZ SIGUA LUIS HIPOLITO | C15: 172.16.2.5 | D15: ACTIVO | E15: M | G15: 0103855920 | H15: BAÑOS | I15: NO | J15: GUADALUPANO ALTO | K15: dianys1895@gmail.com | L15: 0988149915 | N15: 44403 | O15: 650M/650M | P15: GRATIS | Q15: 0 | R15: C02187 | S15: 17.25 | T15: 0 | U15: 46031 | V15: 46035 | W15: 17.25 | X15: Pichincha | AB15: =Q15+S15+T15-W15-Z15 -> 0 | AC15: C02298 | AD15: 17.25 | AE15: 0 | AF15: 46062 | AG15: 46072 | AH15: 17.25 | AI15: Pichincha | AM15: =(AB15+AD15+AE15)-(AH15+AK15) -> 0 | AN15: C02408 | AO15: 17.25 | AP15: 0 | AQ15: 46090 | AR15: 17/03/2026 | AS15: 17.25 | AT15: Pichincha | AX15: =(AM15+AO15+AP15)-(AS15+AV15) -> 0 | AY15: C02521 | AZ15: 17.25 | BA15: 0 | BB15: 46121 | BC15: 7/4/2026 | BD15: 17.25 | BE15: Pichincha | BI15: =(AX15+AZ15+BA15)-(BD15+BG15) -> 0 | BJ15: C02635 | BK15: 17.25 | BL15: 0 | BM15: 46151 | BT15: =(BI15+BK15+BL15)-(BO15+BR15) -> 17.25
A16: 019 | B16: CASTILLO MONTALEZA MANUEL SANTOS | C16: 172.16.1.6 | D16: ACTIVO | E16: M | G16: 0101565398 | H16: BAÑOS | I16: NO | J16: CALLE LA CALIZA Y RICARDO DURAN | K16: manuelscastillom@gmail.com | L16: 0997876310 0992909166 | N16: 44424 | O16: 100M/100M | P16: GRATIS | Q16: 0 | R16: C02188 | S16: 17.25 | T16: 0 | U16: 46031 | V16: 46037 | W16: 17.25 | X16: Efectivo | AB16: =Q16+S16+T16-W16-Z16 -> 0 | AC16: C02299 | AD16: 17.25 | AE16: 0 | AF16: 46062 | AH16: 17.25 | AI16: Efectivo | AM16: =(AB16+AD16+AE16)-(AH16+AK16) -> 0 | AN16: C02409 | AO16: 17.25 | AP16: 0 | AQ16: 46090 | AR16: 16/3/2026 | AS16: 17.25 | AT16: Efectivo | AX16: =(AM16+AO16+AP16)-(AS16+AV16) -> 0 | AY16: C02522 | AZ16: 17.25 | BA16: 0 | BB16: 46121 | BC16: 16/4/2026 | BD16: 17.25 | BE16: Efectivo | BI16: =(AX16+AZ16+BA16)-(BD16+BG16) -> 0 | BJ16: C02636 | BK16: 17.25 | BL16: 0 | BM16: 46151 | BT16: =(BI16+BK16+BL16)-(BO16+BR16) -> 17.25
A17: 020 | B17: VASQUEZ BUENO LUIS ALEJANDRO | C17: 172.16.1.7 | D17: ACTIVO | E17: M | G17: 0107835571 | H17: BAÑOS | I17: SI | J17: CALLE LLAVERO Y EL CALVARIO | K17: buenolastenia@gmail.com | L17: 0968397062 0992237922 | M17: 20baluisv | N17: 44438 | O17: 650M/650M | P17: GRATIS | Q17: 0 | R17: C02249 | S17: 23 | T17: 0 | U17: 46041 | V17: 46036 | W17: 23 | X17: Efectivo | AB17: =Q17+S17+T17-W17-Z17 -> 0 | AC17: C02357 | AD17: 23 | AE17: 0 | AF17: 46072 | AG17: 46064 | AH17: 23 | AI17: Efectivo | AM17: =(AB17+AD17+AE17)-(AH17+AK17) -> 0 | AN17: C02459 | AO17: 23 | AP17: 0 | AQ17: 46100 | AR17: 10/3/2026 | AS17: 23 | AT17: JEP | AX17: =(AM17+AO17+AP17)-(AS17+AV17) -> 0 | AY17: C02577 | AZ17: 23 | BA17: 0 | BB17: 46131 | BC17: 10/4/2026 | BD17: 23 | BE17: Efectivo | BI17: =(AX17+AZ17+BA17)-(BD17+BG17) -> 0 | BJ17: C02689 | BK17: 23 | BL17: 0 | BM17: 46161 | BT17: =(BI17+BK17+BL17)-(BO17+BR17) -> 23
A18: 021 | B18: GUAMAN YUNGA NARCISA PIEDAD | C18: 172.16.5.44 | D18: ACTIVO | E18: F | G18: 0106385578 | H18: BAÑOS | I18: SI | J18: SECTOR HUIZHIL | K18: facturas.labsll@gmail.com | L18: 0939645686 | M18: 21baguamann | N18: 45992 | O18: 600M/600M | P18: GRATIS | Q18: 0 | S18: 20.54 | T18: 0 | U18: 46041 | V18: 26/1/2026 | W18: 20.54 | X18: Efectivo | AB18: =Q18+S18+T18-W18-Z18 -> 0 | AC18: SIN FACTURA | AD18: 20.54 | AE18: 2 | AF18: 46072 | AG18: 46078.514 | AH18: 22.54 | AI18: Efectivo | AM18: =(AB18+AD18+AE18)-(AH18+AK18) -> 0 | AN18: SIN FACTURA | AO18: 20.54 | AP18: 2 | AQ18: 46100 | AR18: 25/3/2026 | AS18: 20.54 | AT18: Efectivo | AV18: 2 | AW18: Efectivo | AX18: =(AM18+AO18+AP18)-(AS18+AV18) -> 0 | AY18: SIN FACTURA | AZ18: 20.54 | BA18: 2 | BB18: 46131 | BC18: 46487 | BD18: 20.54 | BE18: Efectivo | BG18: 2 | BH18: Efectivo | BI18: =(AX18+AZ18+BA18)-(BD18+BG18) -> 0 | BK18: 20.54 | BL18: 2 | BM18: 46161 | BT18: =(BI18+BK18+BL18)-(BO18+BR18) -> 22.54
A19: 023 | B19: BALAREZO DURAN MARIA ELENA | C19: 172.16.1.9 | D19: ACTIVO | E19: F | G19: 0102434560 | H19: BAÑOS | I19: SI | J19: PASEO DE LA GUADALUPANA | K19: mariaelenab2011@hotmail.com | L19: 0959852484 0992424963 4097678 | N19: 44440 | O19: 100M/100M | P19: GRATIS | Q19: 0 | R19: C02189 | S19: 17.25 | T19: 0 | U19: 46041 | V19: 46045 | W19: 34.5 | X19: JEP | AB19: =Q19+S19+T19-W19-Z19 -> -17.25 | AC19: C02300 | AD19: 17.25 | AE19: 0 | AF19: 46072 | AG19: 46073 | AH19: 17.25 | AI19: JEP | AM19: =(AB19+AD19+AE19)-(AH19+AK19) -> -17.25 | AN19: C02410 | AO19: 17.25 | AP19: 0 | AQ19: 46100 | AX19: =(AM19+AO19+AP19)-(AS19+AV19) -> 0 | AY19: C02523 | AZ19: 17.25 | BA19: 0 | BB19: 46131 | BC19: 27/4/2026 | BD19: 20 | BE19: JEP | BI19: =(AX19+AZ19+BA19)-(BD19+BG19) -> -2.75 | BJ19: C02637 | BK19: 17.25 | BL19: 0 | BM19: 46161 | BT19: =(BI19+BK19+BL19)-(BO19+BR19) -> 14.5
A20: 024 | B20: SANCHEZ GUARANGO DIGNA ISABEL | C20: 172.16.4.14 | D20: ACTIVO | E20: F | G20: 0105975387 | H20: BAÑOS | I20: SI | J20: ALFONSO CARRION Y AV. RICARDO DURAN | K20: sanchezdigna284@gmail.com | L20: 0967656705 0990886597 | N20: 44446 | O20: 650M/650M | P20: GRATIS | Q20: 0 | R20: C02250 | S20: 23 | T20: 0 | U20: 46037 | V20: 26/1/2026 | W20: 23 | X20: Efectivo | AB20: =Q20+S20+T20-W20-Z20 -> 0 | AC20: C02358 | AD20: 23 | AE20: 0 | AF20: 46068 | AG20: 46076.807 | AH20: 23 | AI20: Efectivo | AM20: =(AB20+AD20+AE20)-(AH20+AK20) -> 0 | AN20: C02460 | AO20: 23 | AP20: 0 | AQ20: 46096 | AR20: 25/3/2026 | AS20: 23 | AT20: Efectivo | AX20: =(AM20+AO20+AP20)-(AS20+AV20) -> 0 | AY20: C02578 | AZ20: 23 | BA20: 0 | BB20: 46127 | BC20: 24/4/2026 | BD20: 23 | BE20: Efectivo | BI20: =(AX20+AZ20+BA20)-(BD20+BG20) -> 0 | BJ20: C02690 | BK20: 23 | BL20: 0 | BM20: 46157 | BT20: =(BI20+BK20+BL20)-(BO20+BR20) -> 23
A21: 025 | B21: SIGUA LOJANO OLGA CRISTINA | C21: 172.16.1.11 | D21: ACTIVO | E21: F | G21: 0105084875 | H21: BAÑOS | I21: NO | J21: VIA LAS MINAS BAÑOS | K21: olgasigua1985@gmail.com | L21: 0987141328 | N21: 44459 | O21: 100M/100M | P21: GRATIS | Q21: -0.75 | R21: C02190 | S21: 18 | T21: 0 | U21: 46032 | V21: 46143 | W21: 17.25 | X21: Efectivo | AB21: =Q21+S21+T21-W21-Z21 -> 0 | AC21: SIN FACTURA | AD21: 18 | AE21: 0 | AF21: 46063 | AG21: 46059.787 | AH21: 18 | AI21: Efectivo | AM21: =(AB21+AD21+AE21)-(AH21+AK21) -> 0 | AN21: SIN FACTURA | AO21: 18 | AP21: 0 | AQ21: 46091 | AR21: 46087.515 | AS21: 18 | AT21: Efectivo | AX21: =(AM21+AO21+AP21)-(AS21+AV21) -> 0 | AY21: SIN FACTURA | AZ21: 18 | BA21: 0 | BB21: 46122 | BC21: 46119.345 | BD21: 18 | BE21: Efectivo | BI21: =(AX21+AZ21+BA21)-(BD21+BG21) -> 0 | BK21: 18 | BL21: 0 | BM21: 46152 | BN21: 46148.345 | BO21: 18 | BP21: Efectivo | BT21: =(BI21+BK21+BL21)-(BO21+BR21) -> 0
A22: 029 | B22: BARBECHO ZHIÑIN MARIA BELEN | C22: 172.16.1.15 | D22: ACTIVO | E22: M | G22: 0150669596 | H22: BAÑOS | I22: NO | J22: CALLE EL CALVARIO | K22: mariabarbechocris@gmail.com | L22: 0997383316 0980921524 | N22: 45481 | O22: 100M/100M | P22: GRATIS | Q22: 0 | R22: C02191 | S22: 17.25 | T22: 0 | U22: 46036 | V22: 22/1/2026 | W22: 17.25 | X22: Efectivo | AB22: =Q22+S22+T22-W22-Z22 -> 0 | AC22: C02301 | AD22: 17.25 | AE22: 0 | AF22: 46067 | AG22: 46073.756 | AH22: 17.25 | AI22: Efectivo | AM22: =(AB22+AD22+AE22)-(AH22+AK22) -> 0 | AN22: C02411 | AO22: 17.25 | AP22: 0 | AQ22: 46095 | AR22: 46097.497 | AS22: 17.25 | AT22: Efectivo | AX22: =(AM22+AO22+AP22)-(AS22+AV22) -> 0 | AY22: C02524 | AZ22: 17.25 | BA22: 0 | BB22: 46126 | BC22: 16/4/2026 | BD22: 17.25 | BE22: Efectivo | BI22: =(AX22+AZ22+BA22)-(BD22+BG22) -> 0 | BJ22: C02638 | BK22: 17.25 | BL22: 0 | BM22: 46156 | BT22: =(BI22+BK22+BL22)-(BO22+BR22) -> 17.25
A23: 030 | B23: PINTADO GUAMAN MANUEL VICENTE | C23: 172.16.1.16 | D23: ACTIVO | E23: M | G23: 0102319902001 | H23: BAÑOS | I23: NO | J23: CALLE LA CALIZA Y RICARDO DURAN | K23: ecuadistribuidorvp@gmail.com | L23: 0997443605 | M23: 30bamanuelp | N23: 44488 | O23: 650M/650M | P23: GRATIS | Q23: 0 | R23: C02192 | S23: 17.25 | T23: 0 | U23: 46041 | V23: 46030 | W23: 17.25 | X23: JEP | AB23: =Q23+S23+T23-W23-Z23 -> 0 | AC23: C02302 | AD23: 17.25 | AE23: 0 | AF23: 46072 | AG23: 46072 | AH23: 17.25 | AI23: JEP | AM23: =(AB23+AD23+AE23)-(AH23+AK23) -> 0 | AN23: C02412 | AO23: 17.25 | AP23: 0 | AQ23: 46100 | AR23: 16/3/2026 | AS23: 17.25 | AT23: Pichincha | AX23: =(AM23+AO23+AP23)-(AS23+AV23) -> 0 | AY23: C02525 | AZ23: 17.25 | BA23: 0 | BB23: 46131 | BC23: 14/04/2026 | BD23: 17.25 | BE23: JEP | BI23: =(AX23+AZ23+BA23)-(BD23+BG23) -> 0 | BJ23: C02639 | BK23: 17.25 | BL23: 0 | BM23: 46161 | BT23: =(BI23+BK23+BL23)-(BO23+BR23) -> 17.25
A24: 031 | B24: PEÑALOZA BALAREZO DIANA MARCELA | C24: 172.16.2.15 | D24: ACTIVO | E24: F | G24: 0104386917 | H24: BAÑOS | I24: NO | J24: PASEO DE LA GUADALUPANA | K24: flakitaconK23@gmail.com | L24: 0979162869 | N24: 44488 | O24: 100M/100M | P24: GRATIS | Q24: 0 | S24: 17.25 | T24: 0 | U24: 46041 | V24: 46049 | W24: 17.25 | X24: JEP | AB24: =Q24+S24+T24-W24-Z24 -> 0 | AC24: C02303 | AD24: 17.25 | AE24: 0 | AF24: 46072 | AG24: 46076 | AH24: 17.25 | AI24: Efectivo | AM24: =(AB24+AD24+AE24)-(AH24+AK24) -> 0 | AN24: C02413 | AO24: 17.25 | AP24: 0 | AQ24: 46100 | AR24: 25/3/2026 | AS24: 17.25 | AT24: Pichincha | AX24: =(AM24+AO24+AP24)-(AS24+AV24) -> 0 | AY24: C02526 | AZ24: 17.25 | BA24: 0 | BB24: 46131 | BI24: =(AX24+AZ24+BA24)-(BD24+BG24) -> 17.25 | BJ24: C02640 | BK24: 17.25 | BL24: 0 | BM24: 46161 | BT24: =(BI24+BK24+BL24)-(BO24+BR24) -> 34.5
A25: 032 | B25: CARRILLO DOMINGUEZ JHOANA ELIZABETH | C25: 172.16.3.3 | D25: ACTIVO | F25: 12 | G25: 0105877864 | H25: YANUNCAY | I25: SI | J25: CONTROL SUR - SALTO DE LA SOGA Y DE LA PAJARA PINTA | K25: carrillo.jhoana@yahoo.com | L25: 0980444195 0995635986 | N25: 44489 | O25: 800M/800M | P25: GRATIS | Q25: 0 | R25: C02291 | S25: 32.2 | T25: 0 | U25: 46031 | V25: 46036 | W25: 32.2 | X25: JEP | AB25: =Q25+S25+T25-W25-Z25 -> 0 | AC25: C02395 | AD25: 32.2 | AE25: 0 | AF25: 46062 | AG25: 46073 | AH25: 35 | AI25: JEP | AM25: =(AB25+AD25+AE25)-(AH25+AK25) -> -2.8 | AN25: SIN FACTURA | AO25: 32.2 | AP25: 0 | AQ25: 46090 | AR25: 13/3/2026 | AS25: 32.2 | AT25: JEP | AX25: =(AM25+AO25+AP25)-(AS25+AV25) -> -2.8 | AY25: SIN FACTURA | AZ25: 32.2 | BA25: 0 | BB25: 46121 | BC25: 14/4/2026 | BD25: 32.2 | BE25: JEP | BI25: =(AX25+AZ25+BA25)-(BD25+BG25) -> -2.8 | BK25: 32.2 | BL25: 0 | BM25: 46151 | BT25: =(BI25+BK25+BL25)-(BO25+BR25) -> 29.4
A26: 033 | B26: TOBAY ALVAREZ MONICA ISABEL | C26: 172.16.0.2 | D26: EN PROCESO | E26: F | G26: 0106133002 | H26: BAÑOS | I26: SI | J26: NARANCAY ALTO - CUCHILOMA | K26: tobaymiki@gmail.com | L26: 0967964254 | N26: 44492 | O26: 100M/100M | P26: GRATIS | Q26: 164.5 | T26: 0 | U26: 46036 | AB26: =Q26+S26+T26-W26-Z26 -> 164.5 | AC26: SIN FACTURA | AE26: 0 | AF26: 46067 | AM26: =(AB26+AD26+AE26)-(AH26+AK26) -> 164.5 | AN26: SIN FACTURA | AP26: 0 | AQ26: 46095 | AX26: =(AM26+AO26+AP26)-(AS26+AV26) -> 164.5 | AY26: SIN FACTURA | BA26: 0 | BB26: 46126 | BI26: =(AX26+AZ26+BA26)-(BD26+BG26) -> 164.5 | BL26: 0 | BM26: 46156 | BT26: =(BI26+BK26+BL26)-(BO26+BR26) -> 164.5
A27: 035 | B27: MOROCHO QUITUIZACA MIRIAN PATRICIA | C27: 172.16.0.10 | D27: ACTIVO | E27: F | G27: 0107236390 | H27: BAÑOS | I27: NO | J27: VIA AL CHORRO CARROLOMA | K27: mirianmorocho017@gmail.com | L27: 0969892598 0969955271 | N27: 44501 | O27: 650M/650M | P27: GRATIS | Q27: 0 | R27: C02251 | S27: 23 | T27: 0 | U27: 46031 | V27: 46034 | W27: 23 | X27: Efectivo | AB27: =Q27+S27+T27-W27-Z27 -> 0 | AC27: C02359 | AD27: 23 | AE27: 0 | AF27: 46062 | AG27: 46064.76 | AH27: 23 | AI27: Efectivo | AM27: =(AB27+AD27+AE27)-(AH27+AK27) -> 0 | AN27: C02461 | AO27: 23 | AP27: 0 | AQ27: 46090 | AR27: 9/3/2026 | AS27: 23 | AT27: Pichincha | AX27: =(AM27+AO27+AP27)-(AS27+AV27) -> 0 | AY27: C02579 | AZ27: 23 | BA27: 0 | BB27: 46121 | BC27: 4/10/2026 | BD27: 23 | BE27: Efectivo | BI27: =(AX27+AZ27+BA27)-(BD27+BG27) -> 0 | BJ27: C02691 | BK27: 23 | BL27: 0 | BM27: 46151 | BT27: =(BI27+BK27+BL27)-(BO27+BR27) -> 23
A28: 036 | B28: SANCHEZ BURBANO ALICIA LUCIA | C28: 172.16.3.7 | D28: ACTIVO | E28: F | G28: 0602095416 | H28: YANUNCAY | I28: SI | J28: VIA NARANCAY | K28: pamelagranizo1992@gmail.com | L28: 0962855527 0984503895 | M28: 36baaliciab | N28: 44536 | O28: 650M/650M | P28: GRATIS | Q28: 0 | S28: 25 | T28: 0 | U28: 46041 | V28: 46036 | W28: 25 | X28: Pichincha | AB28: =Q28+S28+T28-W28-Z28 -> 0 | AC28: SIN FACTURA | AD28: 25 | AE28: 0 | AF28: 46072 | AG28: 46061 | AH28: 25 | AI28: JEP | AM28: =(AB28+AD28+AE28)-(AH28+AK28) -> 0 | AN28: SIN FACTURA | AO28: 25 | AP28: 0 | AQ28: 46100 | AR28: 11/3/2026 | AS28: 50 | AT28: Pichincha | AX28: =(AM28+AO28+AP28)-(AS28+AV28) -> -25 | AY28: SIN FACTURA | AZ28: 25 | BA28: 0 | BB28: 46131 | BI28: =(AX28+AZ28+BA28)-(BD28+BG28) -> 0 | BK28: 25 | BL28: 0 | BM28: 46161 | BT28: =(BI28+BK28+BL28)-(BO28+BR28) -> 25
A29: 037 | B29: SIGUA LOJANO FREDY BOLIVAR | C29: 172.16.1.18 | D29: ACTIVO | E29: M | G29: 0106101801 | H29: BAÑOS | I29: NO | J29: VIA LAS MINAS BAÑOS | K29: fredybolivar321@gmail.com | L29: 0987141328 0997253643 | N29: 44545 | O29: 100M/100M | P29: GRATIS | Q29: 0 | R29: C02193 | S29: 17.25 | T29: 0 | U29: 46031 | V29: 46025 | W29: 17.5 | X29: Pichincha | AB29: =Q29+S29+T29-W29-Z29 -> -0.25 | AC29: C02304 | AD29: 17.25 | AE29: 0 | AF29: 46062 | AG29: 46055.808 | AH29: 17.25 | AI29: Efectivo | AM29: =(AB29+AD29+AE29)-(AH29+AK29) -> -0.25 | AN29: C02414 | AO29: 17.25 | AP29: 0 | AQ29: 46090 | AR29: 1/3/2026 | AS29: 17.25 | AT29: Pichincha | AX29: =(AM29+AO29+AP29)-(AS29+AV29) -> -0.25 | AY29: C02527 | AZ29: 17.25 | BA29: 0 | BB29: 46121 | BC29: 1/4/2026 | BD29: 17.5 | BE29: Pichincha | BI29: =(AX29+AZ29+BA29)-(BD29+BG29) -> -0.5 | BJ29: C02641 | BK29: 17.25 | BL29: 0 | BM29: 46151 | BN29: 3/5/2026 | BO29: 17.5 | BP29: Pichincha | BT29: =(BI29+BK29+BL29)-(BO29+BR29) -> -0.75
A30: 038 | B30: SIGUA LOJANO NORMA PATRICIA | C30: 172.16.1.19 | D30: ACTIVO | E30: F | G30: 0104130505 | H30: BAÑOS | I30: NO | J30: VIA LAS MINAS BAÑOS | K30: nathalyv728@gmail.com | L30: 0959530127 0990345417 | N30: 44545 | O30: 100M/100M | P30: GRATIS | Q30: 0 | R30: C02194 | S30: 17.25 | T30: 0 | U30: 46031 | V30: 46024 | W30: 17.25 | X30: JEP | AB30: =Q30+S30+T30-W30-Z30 -> 0 | AC30: C02305 | AD30: 17.25 | AE30: 0 | AF30: 46062 | AG30: 46057 | AH30: 17.25 | AI30: JEP | AM30: =(AB30+AD30+AE30)-(AH30+AK30) -> 0 | AN30: C02415 | AO30: 17.25 | AP30: 0 | AQ30: 46090 | AR30: 6/3/2026 | AS30: 17.25 | AT30: Efectivo | AX30: =(AM30+AO30+AP30)-(AS30+AV30) -> 0 | AY30: C02528 | AZ30: 17.25 | BA30: 0 | BB30: 46121 | BC30: 4/4/2026 | BD30: 17.25 | BE30: JEP | BI30: =(AX30+AZ30+BA30)-(BD30+BG30) -> 0 | BJ30: C02642 | BK30: 17.25 | BL30: 0 | BM30: 46151 | BT30: =(BI30+BK30+BL30)-(BO30+BR30) -> 17.25
A31: 039 | B31: SIGUA CRIOLLO CARMEN DE JESUS | C31: 172.16.1.20 | D31: ACTIVO | E31: F | G31: 0103456018 | H31: BAÑOS | I31: NO | J31: VIA LAS MINAS BAÑOS | K31: carmensigua75@gmail.com | L31: 0983571157 4092792 2893644 | N31: 46017 | O31: 800M/800M | P31: GRATIS | Q31: 0 | R31: C02292 | S31: =32.2+35 -> 67.2 | T31: 0 | U31: 46041 | V31: 26/1/2026 | W31: 67.2 | X31: Efectivo | AB31: =Q31+S31+T31-W31-Z31 -> 0 | AC31: SIN FACTURA | AD31: =32.2+35 -> 67.2 | AE31: 0 | AF31: 46072 | AG31: 46076 | AH31: 50 | AI31: Efectivo | AM31: =(AB31+AD31+AE31)-(AH31+AK31) -> 17.2 | AN31: C02504 | AO31: 32.2 | AP31: 0 | AQ31: 46100 | AR31: 46108.353 | AS31: 35 | AT31: Efectivo | AX31: =(AM31+AO31+AP31)-(AS31+AV31) -> 14.4 | AY31: SIN FACTURA | AZ31: 32.2 | BA31: 0 | BB31: 46131 | BC31: 24/4/2026 | BD31: 40 | BE31: Efectivo | BI31: =(AX31+AZ31+BA31)-(BD31+BG31) -> 6.6 | BK31: 32.2 | BL31: 0 | BM31: 46161 | BT31: =(BI31+BK31+BL31)-(BO31+BR31) -> 38.8
A32: 040 | B32: ZHAGUI DUGLLAY DIANA CECILIA | C32: 172.16.1.21 | D32: EN PROCESO | E32: F | G32: 0104928411 | H32: BAÑOS | I32: NO | J32: EL CALVARIO | K32: fabriciodugllay51@gmail.com | L32: 0992467080 099764171 0986234426 | N32: 44550 | O32: 650M/650M | P32: GRATIS | Q32: 83 | T32: 0 | U32: 46041 | AB32: =Q32+S32+T32-W32-Z32 -> 83 | AC32: SIN FACTURA | AE32: 0 | AF32: 46072 | AM32: =(AB32+AD32+AE32)-(AH32+AK32) -> 83 | AN32: SIN FACTURA | AP32: 0 | AQ32: 46100 | AX32: =(AM32+AO32+AP32)-(AS32+AV32) -> 83 | AY32: SIN FACTURA | BA32: 0 | BB32: 46131 | BI32: =(AX32+AZ32+BA32)-(BD32+BG32) -> 83 | BL32: 0 | BM32: 46161 | BT32: =(BI32+BK32+BL32)-(BO32+BR32) -> 83
A33: 043 | B33: MACAS GUALAN AIDA BEATRIZ | C33: 172.16.5.39 | D33: ACTIVO | E33: F | G33: 0107189680 | H33: BAÑOS | I33: SI | J33: SECTOR EL CHORRO CALLE GUADALUPANA | K33: macasaida7@gmail.com | L33: 0986292604 0989455393 | N33: 45859 | O33: 650M/650M | P33: 5 | Q33: 0 | S33: =20.54+10 -> 30.54 | T33: 0 | U33: 46036 | V33: 46049 | W33: 20.54 | X33: Efectivo | AB33: =Q33+S33+T33-W33-Z33 -> 10 | AC33: SIN FACTURA | AD33: 20.54 | AE33: 0 | AF33: 46067 | AG33: 46077 | AH33: 30.54 | AI33: Efectivo | AM33: =(AB33+AD33+AE33)-(AH33+AK33) -> 0 | AN33: SIN FACTURA | AO33: 20.54 | AP33: 0 | AQ33: 46095 | AR33: 46112.583 | AS33: 20.54 | AT33: Efectivo | AX33: =(AM33+AO33+AP33)-(AS33+AV33) -> 0 | AY33: SIN FACTURA | AZ33: 20.54 | BA33: 0 | BB33: 46126 | BI33: =(AX33+AZ33+BA33)-(BD33+BG33) -> 20.54 | BK33: 20.54 | BL33: 0 | BM33: 46156 | BT33: =(BI33+BK33+BL33)-(BO33+BR33) -> 41.08
A34: 045 | B34: SIGUA CRIOLLO CARMEN DE JESUS (PAPAS) | C34: 172.16.1.23 | D34: INACTIVO | E34: F | G34: 0103456018 | H34: BAÑOS | I34: NO | J34: VIA LAS MINAS BAÑOS | K34: carmensigua75@gmail.com | L34: 0983571157 4092792 0997217517 | N34: 44606 | O34: 100M/100M | P34: GRATIS | Q34: 0 | T34: 0 | AB34: =Q34+S34+T34-W34-Z34 -> 0 | AC34: SIN FACTURA | AE34: 0 | AM34: =(AB34+AD34+AE34)-(AH34+AK34) -> 0 | AN34: SIN FACTURA | AP34: 0 | AX34: =(AM34+AO34+AP34)-(AS34+AV34) -> 0 | AY34: SIN FACTURA | BA34: 0 | BI34: =(AX34+AZ34+BA34)-(BD34+BG34) -> 0 | BL34: 0 | BT34: =(BI34+BK34+BL34)-(BO34+BR34) -> 0
A35: 046 | B35: DUCHI GUAMAN ROSA NARCISA | C35: 172.16.1.24 | D35: ACTIVO | E35: F | G35: 0103831491 | H35: BAÑOS | I35: SI | J35: PASEO GUADALUPANA | K35: rosanarcisaduchiguaman@gmail.com | L35: 0997365597 2892124 | M35: 046roduchi | N35: 44701 | O35: 100M/100M | P35: 5 | Q35: 0 | R35: C02195 | S35: 17.25 | T35: 0 | U35: 46041 | V35: 46037 | W35: 17.25 | X35: Efectivo | AB35: =Q35+S35+T35-W35-Z35 -> 0 | AC35: C02306 | AD35: 17.25 | AE35: 0 | AF35: 46072 | AG35: 46071 | AH35: 17.25 | AI35: Efectivo | AM35: =(AB35+AD35+AE35)-(AH35+AK35) -> 0 | AN35: C02416 | AO35: 17.25 | AP35: 0 | AQ35: 46100 | AR35: 46100.63 | AS35: 17.25 | AT35: Efectivo | AX35: =(AM35+AO35+AP35)-(AS35+AV35) -> 0 | AY35: C02529 | AZ35: 17.25 | BA35: 0 | BB35: 46131 | BC35: 8/4/2026 | BD35: 17.25 | BE35: Efectivo | BI35: =(AX35+AZ35+BA35)-(BD35+BG35) -> 0 | BJ35: C02643 | BK35: 17.25 | BL35: 0 | BM35: 46161 | BT35: =(BI35+BK35+BL35)-(BO35+BR35) -> 17.25
A36: 047 | B36: PINCAY VALAREZO PAOLA MARIA | C36: 172.16.0.15 | D36: EN PROCESO | E36: F | G36: 0925492670 | H36: YANUNCAY | I36: SI | J36: CDLA. SANTA MARIA DE BAÑOS | K36: pandora_17@hotmail.com | L36: 0999214389 | N36: 44638 | O36: 100M/100M | Q36: 77.25 | T36: 0 | U36: 46041 | AB36: =Q36+S36+T36-W36-Z36 -> 77.25 | AC36: SIN FACTURA | AE36: 0 | AF36: 46072 | AM36: =(AB36+AD36+AE36)-(AH36+AK36) -> 77.25 | AN36: SIN FACTURA | AP36: 0 | AQ36: 46100 | AX36: =(AM36+AO36+AP36)-(AS36+AV36) -> 77.25 | AY36: SIN FACTURA | BA36: 0 | BB36: 46131 | BI36: =(AX36+AZ36+BA36)-(BD36+BG36) -> 77.25 | BL36: 0 | BM36: 46161 | BT36: =(BI36+BK36+BL36)-(BO36+BR36) -> 77.25
A37: 048 | B37: CAJAMARCA AYABACA MANUEL FABIAN | C37: 172.16.12.5 | D37: ACTIVO | E37: M | G37: 0104934302 | H37: YANUNCAY | I37: NO | J37: CALLE LA MACATECA | K37: cajamarcafabian857@gmail.com | L37: 0980484671 | N37: 44638 | O37: 650M/650M | Q37: 0 | R37: C02253 | S37: 23 | T37: 0 | U37: 46031 | V37: 46045.354 | W37: 23 | X37: Efectivo | AB37: =Q37+S37+T37-W37-Z37 -> 0 | AC37: C02360 | AD37: 23 | AE37: 0 | AF37: 46062 | AG37: 46064.534 | AH37: 23 | AI37: Efectivo | AM37: =(AB37+AD37+AE37)-(AH37+AK37) -> 0 | AN37: C02462 | AO37: 23 | AP37: 0 | AQ37: 46090 | AR37: 27/3/2026 | AS37: 23 | AT37: Efectivo | AX37: =(AM37+AO37+AP37)-(AS37+AV37) -> 0 | AY37: C02581 | AZ37: 23 | BA37: 0 | BB37: 46121 | BC37: 46134.472 | BD37: 23 | BE37: Efectivo | BI37: =(AX37+AZ37+BA37)-(BD37+BG37) -> 0 | BJ37: C02692 | BK37: 23 | BL37: 0 | BM37: 46151 | BT37: =(BI37+BK37+BL37)-(BO37+BR37) -> 23
A38: 049 | B38: BENENAULA CRIOLLO DARIO JAVIER | C38: 172.16.0.17 | D38: ACTIVO | E38: M | G38: 0105541270 | H38: YANUNCAY | I38: NO | J38: VIRGEN DE FATIMA ADBOCACION | K38: dariobene619@gmail.com | L38: 0968997963 0988356536 | M38: 49badariob | N38: 44641 | O38: 650M/650M | Q38: 0 | R38: C02254 | S38: 23 | T38: 0 | U38: 46047 | V38: 46048.818 | W38: 23 | X38: JEP | AB38: =Q38+S38+T38-W38-Z38 -> 0 | AC38: C02361 | AD38: 23 | AE38: 0 | AF38: 46078 | AG38: 46079 | AH38: 23 | AI38: JEP | AM38: =(AB38+AD38+AE38)-(AH38+AK38) -> 0 | AN38: C02463 | AO38: 23 | AP38: 0 | AQ38: 46106 | AR38: 26/3/2026 | AS38: 23 | AT38: JEP | AX38: =(AM38+AO38+AP38)-(AS38+AV38) -> 0 | AY38: C02580 | AZ38: 23 | BA38: 0 | BB38: 46137 | BC38: 27/04/2026 | BD38: 23 | BE38: Pichincha | BI38: =(AX38+AZ38+BA38)-(BD38+BG38) -> 0 | BJ38: C02693 | BK38: 23 | BL38: 0 | BM38: 46167 | BT38: =(BI38+BK38+BL38)-(BO38+BR38) -> 23
A39: 050 | B39: ACOSTA MERA JOSE RAMON | C39: 172.16.0.18 | D39: ACTIVO | E39: M | G39: 1309249397 | H39: YANUNCAY | I39: NO | J39: NARANCAY ALTO | K39: maritzashuir@gmail.com | L39: 0991567816 0988357336 | N39: 44642 | O39: 650M/650M | Q39: 0 | S39: 23 | T39: 0 | U39: 46041 | V39: 46050 | W39: 23 | X39: Pichincha | AB39: =Q39+S39+T39-W39-Z39 -> 0 | AC39: SIN FACTURA | AD39: 23 | AE39: 0 | AF39: 46072 | AG39: 46081 | AH39: 23 | AI39: Pichincha | AM39: =(AB39+AD39+AE39)-(AH39+AK39) -> 0 | AN39: SIN FACTURA | AO39: 23 | AP39: 0 | AQ39: 46100 | AR39: 46107.662 | AS39: 23 | AT39: Pichincha | AX39: =(AM39+AO39+AP39)-(AS39+AV39) -> 0 | AY39: SIN FACTURA | AZ39: 23 | BA39: 0 | BB39: 46131 | BC39: 29/04/2026 | BD39: 23 | BE39: Pichincha | BI39: =(AX39+AZ39+BA39)-(BD39+BG39) -> 0 | BK39: 23 | BL39: 0 | BM39: 46161 | BT39: =(BI39+BK39+BL39)-(BO39+BR39) -> 23
A40: 051 | B40: SAQUICELA GUAMAN MARIA DE LOURDES | C40: 172.16.11.3 | D40: ACTIVO | E40: F | G40: 0704053305 | H40: YANUNCAY | I40: NO | J40: MACATETA (ESQUINA) BARRIO SANTA MARIA | K40: facturas.labsll@gmail.com | L40: 0981579770 | M40: 051bamariag | N40: 44649 | O40: 650M/650M | Q40: 0 | R40: C02255 | S40: 23 | T40: 0 | U40: 46036 | V40: 46045 | W40: 23 | X40: JEP | AB40: =Q40+S40+T40-W40-Z40 -> 0 | AC40: C02362 | AD40: 23 | AE40: 0 | AF40: 46067 | AG40: 46076 | AH40: 23 | AI40: JEP | AM40: =(AB40+AD40+AE40)-(AH40+AK40) -> 0 | AN40: C02464 | AO40: 23 | AP40: 0 | AQ40: 46095 | AR40: 25/3/2026 | AS40: 23 | AT40: JEP | AX40: =(AM40+AO40+AP40)-(AS40+AV40) -> 0 | AY40: C02582 | AZ40: 23 | BA40: 0 | BB40: 46126 | BC40: 23/4/2026 | BD40: 23 | BE40: JEP | BI40: =(AX40+AZ40+BA40)-(BD40+BG40) -> 0 | BJ40: C02694 | BK40: 23 | BL40: 0 | BM40: 46156 | BT40: =(BI40+BK40+BL40)-(BO40+BR40) -> 23
A41: 052 | B41: FAJARDO SANCHEZ RENI MAGALI | C41: 172.16.0.20 | D41: ACTIVO | E41: F | G41: 0104335187 | H41: YANUNCAY | I41: SI | J41: RIO ORINOCA Y ANTONIO ULLOA | K41: renifajardo@gmail.com | L41: 0988641806 | N41: 44669 | O41: 650M/650M | Q41: 20 | S41: 16.8 | T41: 0 | U41: 46036 | V41: 46037 | W41: 36 | X41: Pichincha | AB41: =Q41+S41+T41-W41-Z41 -> 0.8 | AC41: SIN FACTURA | AD41: 0 | AE41: 0 | AF41: 46067 | AM41: =(AB41+AD41+AE41)-(AH41+AK41) -> 0.8 | AN41: SIN FACTURA | AO41: 16.8 | AP41: 0 | AQ41: 46095 | AR41: 11/3/2026 | AS41: 16.8 | AT41: Pichincha | AX41: =(AM41+AO41+AP41)-(AS41+AV41) -> 0.8 | AY41: SIN FACTURA | AZ41: 16.8 | BA41: 0 | BB41: 46126 | BC41: 22/4/2026 | BD41: 16.8 | BE41: Pichincha | BI41: =(AX41+AZ41+BA41)-(BD41+BG41) -> 0.8 | BK41: 16.8 | BL41: 0 | BM41: 46156 | BT41: =(BI41+BK41+BL41)-(BO41+BR41) -> 17.6
A42: 053 | B42: GODOY MOROCHO ROMEL ALCIDES | C42: 172.16.0.51 | D42: ACTIVO | E42: M | G42: 0104190459 | H42: YANUNCAY | I42: NO | J42: CALLE GUAUDALUPANO | K42: romelgodoy2@gmail.com | L42: 0967216403 0989493601 0969581977 | M42: 053bagodoyr | N42: 45808 | O42: 650M/650M | Q42: 8 | S42: 20 | T42: 2 | U42: 46041 | V42: 46049 | W42: 30 | X42: Pichincha | AB42: =Q42+S42+T42-W42-Z42 -> 0 | AC42: SIN FACTURA | AD42: 23 | AE42: 0 | AF42: 46072 | AG42: 46077 | AH42: 23 | AI42: Pichincha | AM42: =(AB42+AD42+AE42)-(AH42+AK42) -> 0 | AN42: SIN FACTURA | AO42: 23 | AP42: 0 | AQ42: 46100 | AR42: 25/3/2026 | AS42: 23 | AT42: Efectivo | AX42: =(AM42+AO42+AP42)-(AS42+AV42) -> 0 | AY42: SIN FACTURA | AZ42: 23 | BA42: 0 | BB42: 46131 | BC42: 28/4/2026 | BD42: 23 | BE42: Pichincha | BI42: =(AX42+AZ42+BA42)-(BD42+BG42) -> 0 | BK42: 23 | BL42: 2 | BM42: 46161 | BN42: 3/5/2026 | BO42: 23 | BP42: Pichincha | BR42: 2 | BS42: Pichincha | BT42: =(BI42+BK42+BL42)-(BO42+BR42) -> 0
A43: 054 | B43: JADAN AUQUILLA PEDRO DANIEL | C43: 172.16.11.4 | D43: INACTIVO | E43: M | G43: 0101812105 | H43: YANUNCAY | I43: NO | J43: RIO MANZANARES Y RIO PANAMA | K43: auquilla.daniel@yahoo.com | L43: 0967478309 0993797160 | M43: 054bajadan | N43: 44699 | O43: 800M/800M | Q43: -2.72 | S43: 15.24 | T43: 4 | U43: 46041 | V43: 46030 | W43: 16 | X43: Pichincha | Z43: 4 | AA43: Pichincha | AB43: =Q43+S43+T43-W43-Z43 -> -3.48 | AC43: SIN FACTURA | AD43: 15.24 | AE43: 4 | AF43: 46072 | AG43: 46062 | AH43: 15.76 | AI43: Pichincha | AM43: =(AB43+AD43+AE43)-(AH43+AK43) -> 0 | AN43: SIN FACTURA | AO43: 0 | AP43: 0 | AQ43: 46100 | AX43: =(AM43+AO43+AP43)-(AS43+AV43) -> 0 | AY43: SIN FACTURA | AZ43: 0 | BA43: 0 | BB43: 46131 | BI43: =(AX43+AZ43+BA43)-(BD43+BG43) -> 0 | BK43: 0 | BL43: 0 | BM43: 46161 | BT43: =(BI43+BK43+BL43)-(BO43+BR43) -> 0
A44: 055 | B44: LOJA MOCHA JESSICA XIMENA | C44: 172.16.6.11 | D44: ACTIVO | E44: F | G44: 0106829195 | H44: BAÑOS | I44: SI | J44: COCHAPAMBA | K44: ximenaloja78@gmail.com | L44: 969960338 1(646)2077179 | N44: 45828 | O44: 100M/100M | P44: GRATIS | Q44: 0 | R44: C02196 | S44: 17.25 | T44: 0 | U44: 46041 | V44: 46036 | W44: 17.25 | X44: Efectivo | AB44: =Q44+S44+T44-W44-Z44 -> 0 | AC44: C02307 | AD44: 17.25 | AE44: 0 | AF44: 46072 | AG44: 46064 | AH44: 17.25 | AI44: Efectivo | AM44: =(AB44+AD44+AE44)-(AH44+AK44) -> 0 | AN44: C02417 | AO44: 17.25 | AP44: 0 | AQ44: 46100 | AR44: 46097.692 | AS44: 17.25 | AT44: Efectivo | AX44: =(AM44+AO44+AP44)-(AS44+AV44) -> 0 | AY44: C02530 | AZ44: 17.25 | BA44: 0 | BB44: 46131 | BC44: 14/4/2026 | BD44: 17.25 | BE44: Efectivo | BI44: =(AX44+AZ44+BA44)-(BD44+BG44) -> 0 | BJ44: C02644 | BK44: 17.25 | BL44: 0 | BM44: 46161 | BT44: =(BI44+BK44+BL44)-(BO44+BR44) -> 17.25
A45: 056 | B45: JACOME ALEMAN FELIX RICARDO | C45: 172.16.0.23 | D45: ACTIVO | E45: M | G45: 0103390571 | H45: BAÑOS | I45: NO | J45: PASEO GUADALUPANO SUBIDA A LA CAPILLA | K45: marianalucia8a@gmail.com | L45: 0989936333 0967639711 | M45: 56bafelixj | N45: 44729 | O45: 650M/650M | P45: GRATIS | Q45: 0 | R45: C02256 | S45: 23 | T45: 0 | U45: 46041 | V45: 46045 | W45: 23 | X45: JEP | AB45: =Q45+S45+T45-W45-Z45 -> 0 | AC45: C02363 | AD45: 23 | AE45: 0 | AF45: 46072 | AG45: 46076 | AH45: 23 | AI45: Efectivo | AM45: =(AB45+AD45+AE45)-(AH45+AK45) -> 0 | AN45: C02465 | AO45: 23 | AP45: 0 | AQ45: 46100 | AR45: 25/03/2026 | AS45: 23 | AT45: JEP | AX45: =(AM45+AO45+AP45)-(AS45+AV45) -> 0 | AY45: C02583 | AZ45: 23 | BA45: 0 | BB45: 46131 | BC45: 28/3/2026 | BD45: 23 | BE45: Efectivo | BI45: =(AX45+AZ45+BA45)-(BD45+BG45) -> 0 | BJ45: C02695 | BK45: 23 | BL45: 0 | BM45: 46161 | BT45: =(BI45+BK45+BL45)-(BO45+BR45) -> 23
A46: 057 | B46: CELI OCHOA MAYRA ELIZABETH | C46: 172.16.1.26 | D46: ACTIVO | E46: F | G46: 1104783210 | H46: BAÑOS | I46: SI | J46: EL CALVARIO TRES CRUCES | K46: mayraceliochoa@yahoo.es | L46: 0988170391 | N46: 45063 | O46: 100M/100M | P46: GRATIS | Q46: -0.02 | R46: C02197 | S46: 17.25 | T46: 0 | U46: 46041 | V46: 46143 | W46: 17.25 | X46: JEP | AB46: =Q46+S46+T46-W46-Z46 -> -0.02 | AC46: C02308 | AD46: 17.25 | AE46: 0 | AF46: 46072 | AG46: 46059 | AH46: 17.25 | AI46: JEP | AM46: =(AB46+AD46+AE46)-(AH46+AK46) -> -0.02 | AN46: C02418 | AO46: 17.25 | AP46: 0 | AQ46: 46100 | AR46: 4/3/2026 | AS46: 17.25 | AT46: JEP | AX46: =(AM46+AO46+AP46)-(AS46+AV46) -> -0.02 | AY46: C02531 | AZ46: 17.25 | BA46: 0 | BB46: 46131 | BC46: 7/4/2026 | BD46: 17.25 | BE46: JEP | BI46: =(AX46+AZ46+BA46)-(BD46+BG46) -> -0.02 | BJ46: C02645 | BK46: 17.25 | BL46: 0 | BM46: 46161 | BN46: 6/5/2026 | BO46: 17.25 | BP46: Pichincha | BT46: =(BI46+BK46+BL46)-(BO46+BR46) -> -0.02
A47: 058 | B47: TOBAY ALVAREZ MANUEL GONZALO | C47: 172.16.0.24 | D47: EN PROCESO | E47: M | G47: 0103496865 | H47: BAÑOS | I47: NO | J47: NARANCAY ALTO - CUCHILOMA | K47: jackysusana1975@gmail.com | L47: 0991572875 +1 609 9030762 | N47: 44743 | O47: 650M/650M | P47: GRATIS | Q47: 120 | T47: 0 | AB47: =Q47+S47+T47-W47-Z47 -> 120 | AC47: SIN FACTURA | AE47: 0 | AM47: =(AB47+AD47+AE47)-(AH47+AK47) -> 120 | AN47: SIN FACTURA | AP47: 0 | AX47: =(AM47+AO47+AP47)-(AS47+AV47) -> 120 | AY47: SIN FACTURA | BA47: 0 | BI47: =(AX47+AZ47+BA47)-(BD47+BG47) -> 120 | BL47: 0 | BT47: =(BI47+BK47+BL47)-(BO47+BR47) -> 120
A48: 061 | B48: ARBITO CADA ROSA MARIA | C48: 10.65.3.253 | D48: INACTIVO | E48: F | G48: 0102936861 | H48: BAÑOS | I48: NO | J48: BAÑOS SECTOR UNION ALTA | K48: meguayaarbito@gmail.com | L48: 0993170731 0992223220 | M48: 061barosaa | N48: 44771 | O48: 800M/800M | P48: 20 | Q48: 0 | T48: 0 | AB48: =Q48+S48+T48-W48-Z48 -> 0 | AC48: SIN FACTURA | AE48: 0 | AM48: =(AB48+AD48+AE48)-(AH48+AK48) -> 0 | AN48: SIN FACTURA | AP48: 0 | AX48: =(AM48+AO48+AP48)-(AS48+AV48) -> 0 | AY48: SIN FACTURA | BA48: 0 | BI48: =(AX48+AZ48+BA48)-(BD48+BG48) -> 0 | BL48: 0 | BT48: =(BI48+BK48+BL48)-(BO48+BR48) -> 0
A49: 063 | B49: ORDOÑEZ SIGUA ROBERTH GERMAN | C49: 172.16.0.25 | D49: INACTIVO | G49: 0105108245 | H49: BAÑOS | I49: NO | J49: VIA NARANCAY ALTO | K49: roberthgo05@gmail.com | L49: 0998665994 0983924978 | M49: 063basigua | N49: 44837 | O49: 650M/650M | P49: GRATIS | Q49: 0 | T49: 0 | AB49: =Q49+S49+T49-W49-Z49 -> 0 | AC49: SIN FACTURA | AE49: 0 | AM49: =(AB49+AD49+AE49)-(AH49+AK49) -> 0 | AN49: SIN FACTURA | AP49: 0 | AX49: =(AM49+AO49+AP49)-(AS49+AV49) -> 0 | AY49: SIN FACTURA | BA49: 0 | BI49: =(AX49+AZ49+BA49)-(BD49+BG49) -> 0 | BL49: 0 | BT49: =(BI49+BK49+BL49)-(BO49+BR49) -> 0
A50: 065 | B50: GUAMAN GUAMAN JORGE JEOVANY | C50: 172.16.0.27 | D50: EN PROCESO | G50: 0103833653 | H50: YANUNCAY | I50: NO | J50: CALLE LA MACATETA, BAÑOS SANTA MARIA | K50: jorgeguaman428@gmail.com | L50: 0990038171 | N50: 44839 | O50: 650M/650M | Q50: 0 | T50: 0 | AB50: =Q50+S50+T50-W50-Z50 -> 0 | AC50: SIN FACTURA | AE50: 0 | AM50: =(AB50+AD50+AE50)-(AH50+AK50) -> 0 | AN50: SIN FACTURA | AP50: 0 | AX50: =(AM50+AO50+AP50)-(AS50+AV50) -> 0 | AY50: SIN FACTURA | BA50: 0 | BI50: =(AX50+AZ50+BA50)-(BD50+BG50) -> 0 | BL50: 0 | BT50: =(BI50+BK50+BL50)-(BO50+BR50) -> 0
A51: 067 | B51: CRIOLLO CRIOLLO HORTENCIA SUSANA | C51: 172.16.1.28 | D51: ACTIVO | E51: F | G51: 0102738770 | H51: BAÑOS | I51: NO | J51: ENSAYANA CAMINO A BAÑOS | K51: hortencia.criollo20.05@gmail.com | L51: 0967823002 0959299880 | N51: 44887 | O51: 650M/650M | P51: 0 | Q51: 0 | R51: C02257 | S51: 23 | T51: 0 | U51: 46041 | V51: 46045 | W51: 23 | X51: Pichincha | AB51: =Q51+S51+T51-W51-Z51 -> 0 | AC51: C02364 | AD51: 23 | AE51: 0 | AF51: 46072 | AG51: 46076.721 | AH51: 23 | AI51: Efectivo | AM51: =(AB51+AD51+AE51)-(AH51+AK51) -> 0 | AN51: C02466 | AO51: 23 | AP51: 0 | AQ51: 46100 | AR51: 24/3/2026 | AS51: 23 | AT51: JEP | AX51: =(AM51+AO51+AP51)-(AS51+AV51) -> 0 | AY51: C02584 | AZ51: 23 | BA51: 0 | BB51: 46131 | BC51: 46133.583 | BD51: 23 | BE51: Efectivo | BI51: =(AX51+AZ51+BA51)-(BD51+BG51) -> 0 | BJ51: C02696 | BK51: 23 | BL51: 0 | BM51: 46161 | BT51: =(BI51+BK51+BL51)-(BO51+BR51) -> 23
A52: 069 | B52: BARBECHO ZHIÑIN XIMENA ALEXANDRA | C52: 172.16.1.30 | D52: ACTIVO | E52: F | G52: 0105022560 | H52: BAÑOS | I52: NO | J52: SECTOR EL CALVARIO | K52: alexabarbecho06@gmail.com | L52: 0967952013 | N52: 45389 | O52: 650M/650M | P52: 9 | Q52: 0 | S52: 23 | T52: 0 | U52: 46031 | V52: 46034 | W52: 23 | X52: Efectivo | AB52: =Q52+S52+T52-W52-Z52 -> 0 | AC52: SIN FACTURA | AD52: 23 | AE52: 0 | AF52: 46062 | AG52: 46065 | AH52: 23 | AI52: Efectivo | AM52: =(AB52+AD52+AE52)-(AH52+AK52) -> 0 | AN52: SIN FACTURA | AO52: 23 | AP52: 0 | AQ52: 46090 | AR52: 46090.513 | AS52: 23 | AT52: Efectivo | AX52: =(AM52+AO52+AP52)-(AS52+AV52) -> 0 | AY52: SIN FACTURA | AZ52: 23 | BA52: 0 | BB52: 46121 | BC52: 14/4/2026 | BD52: 23 | BE52: Efectivo | BI52: =(AX52+AZ52+BA52)-(BD52+BG52) -> 0 | BK52: 23 | BL52: 0 | BM52: 46151 | BT52: =(BI52+BK52+BL52)-(BO52+BR52) -> 23
A53: 070 | B53: MACAS NAMCELA MARIA MERCEDES | C53: 172.16.0.31 | D53: ACTIVO | E53: F | G53: 1103427447 | H53: BAÑOS | I53: SI | J53: SECTOR EL CHORRO CALLE GUADALUPANA | K53: rosamarianamacasnamcela@gmail.com | L53: 0986347428 0967759439 0985702275 0990674265 | N53: 45634 | O53: 100M/100M | P53: 0 | Q53: 0 | S53: 17.25 | T53: 0 | U53: 46031 | V53: 46050 | W53: 15 | X53: Efectivo | AB53: =Q53+S53+T53-W53-Z53 -> 2.25 | AC53: SIN FACTURA | AD53: 17.25 | AE53: 0 | AF53: 46062 | AG53: 46077 | AH53: 19.5 | AI53: Efectivo | AM53: =(AB53+AD53+AE53)-(AH53+AK53) -> 0 | AN53: SIN FACTURA | AO53: 17.25 | AP53: 0 | AQ53: 46090 | AR53: 25/3/2026 | AS53: 17.25 | AT53: Efectivo | AX53: =(AM53+AO53+AP53)-(AS53+AV53) -> 0 | AY53: SIN FACTURA | AZ53: 17.25 | BA53: 0 | BB53: 46121 | BC53: 28/4/2026 | BD53: 17.25 | BE53: Efectivo | BI53: =(AX53+AZ53+BA53)-(BD53+BG53) -> 0 | BK53: 17.25 | BL53: 0 | BM53: 46151 | BT53: =(BI53+BK53+BL53)-(BO53+BR53) -> 17.25
A54: 071 | B54: AUCAY YUNGA GABRIELA GRIMANES | C54: 172.16.0.32 | D54: ACTIVO | E54: 0 | G54: 0106512833 | H54: BAÑOS | I54: SI | J54: BARRIO GUADALUPANO SECTOR ROSALES | K54: jofreayara@gmail.com | L54: 0986755629 0958946191 | M54: 71baaucayg | N54: 44930 | O54: 650M/650M | P54: 10 | Q54: 0 | R54: C02258 | S54: 23 | T54: 0 | U54: 46041 | V54: 46047 | W54: 23 | X54: Pichincha | AB54: =Q54+S54+T54-W54-Z54 -> 0 | AC54: C02365 | AD54: 23 | AE54: 0 | AF54: 46072 | AG54: 46073.748 | AH54: 23 | AI54: Efectivo | AM54: =(AB54+AD54+AE54)-(AH54+AK54) -> 0 | AN54: C02467 | AO54: 23 | AP54: 0 | AQ54: 46100 | AR54: 20/3/2026 | AS54: 23 | AT54: Efectivo | AX54: =(AM54+AO54+AP54)-(AS54+AV54) -> 0 | AY54: C02585 | AZ54: 23 | BA54: 0 | BB54: 46131 | BC54: 28/4/2026 | BD54: 23 | BE54: Efectivo | BI54: =(AX54+AZ54+BA54)-(BD54+BG54) -> 0 | BJ54: C02697 | BK54: 23 | BL54: 0 | BM54: 46161 | BT54: =(BI54+BK54+BL54)-(BO54+BR54) -> 23
A55: 072 | B55: MEDINA VERA MAYRA ALEXANDRA | C55: 172.16.0.33 | D55: ACTIVO | E55: F | G55: 1105951048 | H55: YANUNCAY | I55: SI | J55: SECTOR EL CHORRO CALLE GUADALUPANO | K55: mayritaalexandramedina@gmail.com | L55: 0995067776 0995964624 | N55: 44931 | O55: 650M/650M | P55: 10 | Q55: 0 | R55: C02259 | S55: 23 | T55: 0 | U55: 46041 | V55: 46045 | W55: 23 | X55: Pichincha | AB55: =Q55+S55+T55-W55-Z55 -> 0 | AC55: C02366 | AD55: 23 | AE55: 0 | AF55: 46072 | AG55: 46076 | AH55: 23 | AI55: Efectivo | AM55: =(AB55+AD55+AE55)-(AH55+AK55) -> 0 | AN55: C02468 | AO55: 23 | AP55: 0 | AQ55: 46100 | AR55: 25/3/2026 | AS55: 23 | AT55: Efectivo | AX55: =(AM55+AO55+AP55)-(AS55+AV55) -> 0 | AY55: C02586 | AZ55: 23 | BA55: 0 | BB55: 46131 | BC55: 28/4/2026 | BD55: 23 | BE55: Efectivo | BI55: =(AX55+AZ55+BA55)-(BD55+BG55) -> 0 | BJ55: C02698 | BK55: 23 | BL55: 0 | BM55: 46161 | BT55: =(BI55+BK55+BL55)-(BO55+BR55) -> 23
A56: 073 | B56: MEDINA MACAS ROSA CARMEN | C56: 172.16.0.34 | D56: ACTIVO | E56: F | G56: 1105947889 | H56: BAÑOS | I56: SI | J56: SECTOR EL CHORRO CALLE GUADALUPANO | K56: willammacas@gmail.com | L56: 0997873287 0985391560 | N56: 45544 | O56: 800M/800M | P56: 10 | Q56: 10 | S56: 30 | T56: 0 | U56: 46051 | V56: 46050 | W56: 30 | X56: Pichincha | AB56: =Q56+S56+T56-W56-Z56 -> 10 | AC56: SIN FACTURA | AD56: 30 | AE56: 0 | AF56: 46082 | AG56: 46079 | AH56: =30+10 -> 40 | AI56: Efectivo | AM56: =(AB56+AD56+AE56)-(AH56+AK56) -> 0 | AN56: SIN FACTURA | AO56: 30 | AP56: 0 | AQ56: 46113 | AR56: 21/3/2026 | AS56: 30 | AT56: Pichincha | AX56: =(AM56+AO56+AP56)-(AS56+AV56) -> 0 | AY56: SIN FACTURA | AZ56: 30 | BA56: 0 | BB56: 46143 | BC56: 2/5/2026 | BD56: 30 | BE56: Pichincha | BI56: =(AX56+AZ56+BA56)-(BD56+BG56) -> 0 | BK56: 30 | BL56: 0 | BM56: 46174 | BT56: =(BI56+BK56+BL56)-(BO56+BR56) -> 30
A57: 074 | B57: JARAMILLO RAMON JESSICA CATALINA | C57: 172.16.3.5 | D57: ACTIVO | E57: F | G57: 0106106040 | H57: YANUNCAY | I57: SI | J57: CALLE VILLALLBOS Y TARREGA | K57: jessyjaramillo2000@gmail.com | L57: 0993586094 | N57: 44939 | O57: 650M/650M | P57: 20 | Q57: -0.6 | R57: C02260 | S57: 23 | T57: 0 | U57: 46031 | V57: 46204 | W57: 23 | X57: Pichincha | AB57: =Q57+S57+T57-W57-Z57 -> -0.6 | AC57: C02367 | AD57: 23 | AE57: 0 | AF57: 46062 | AG57: 46064 | AH57: 23 | AI57: Pichincha | AM57: =(AB57+AD57+AE57)-(AH57+AK57) -> -0.6 | AN57: C02469 | AO57: 23 | AP57: 0 | AQ57: 46090 | AR57: 4/3/2026 | AS57: 23 | AT57: Pichincha | AX57: =(AM57+AO57+AP57)-(AS57+AV57) -> -0.6 | AY57: C02587 | AZ57: 23 | BA57: 0 | BB57: 46121 | BC57: 7/4/2026 | BD57: 23 | BE57: Pichincha | BI57: =(AX57+AZ57+BA57)-(BD57+BG57) -> -0.6 | BJ57: C02699 | BK57: 23 | BL57: 0 | BM57: 46151 | BT57: =(BI57+BK57+BL57)-(BO57+BR57) -> 22.4
A58: 077 | B58: TAPIA ANGAMARCA LAURA CRISTINA | C58: 172.16.12.4 | D58: ACTIVO | E58: F | G58: 0105608806 | H58: YANUNCAY | I58: SI | J58: VICENTE MINDERAS Y AV. RICARDO DURAN | K58: geriatricocuatrorios@gmail.com | L58: 0983814102 0968279022 | M58: 77balaurac | N58: 44953 | O58: 800M/800M | P58: 10 | Q58: -0.2 | R58: C02294 | S58: 32.2 | T58: 3.16 | U58: 46031 | V58: 46204 | W58: 32.2 | X58: JEP | Z58: 3.16 | AA58: JEP | AB58: =Q58+S58+T58-W58-Z58 -> -0.2 | AC58: C02396 | AD58: 32.2 | AE58: 3.16 | AF58: 46062 | AG58: 46059 | AH58: 32.2 | AI58: JEP | AK58: 3.16 | AL58: JEP | AM58: =(AB58+AD58+AE58)-(AH58+AK58) -> -0.2 | AN58: C02500 | AO58: 32.2 | AP58: 4 | AQ58: 46090 | AR58: 10/3/2026 | AS58: 31.76 | AT58: JEP | AV58: 4 | AW58: JEP | AX58: =(AM58+AO58+AP58)-(AS58+AV58) -> 0.24 | AY58: C02625 | AZ58: 32.2 | BA58: 3.16 | BB58: 46121 | BC58: 6/4/2026 | BD58: 32.2 | BE58: JEP | BG58: 3.16 | BH58: JEP | BI58: =(AX58+AZ58+BA58)-(BD58+BG58) -> 0.24 | BJ58: C02732 | BK58: 32.2 | BL58: 3.16 | BM58: 46151 | BN58: 4/5/2026 | BO58: 32.2 | BP58: Pichincha | BR58: 3.16 | BS58: Pichincha | BT58: =(BI58+BK58+BL58)-(BO58+BR58) -> 0.24
A59: 078 | B59: CARRION CALDERON ANGEL MIGUEL | C59: 172.16.1.32 | D59: ACTIVO | E59: M | G59: 1103760342 | H59: BAÑOS | I59: SI | J59: TRES CRUCES | K59: yoliguaman_1980@hotmail.com | L59: 0987655894 0993484816 0987324080 | M59: 78baangelc | N59: 44968 | O59: 650M/650M | P59: 0 | Q59: 0 | R59: C02261 | S59: 25 | U59: 46031 | V59: 46035 | W59: 25 | X59: JEP | AB59: =Q59+S59+T59-W59-Z59 -> 0 | AC59: SIN FACTURA | AD59: 25 | AF59: 46062 | AG59: 46065 | AH59: 25 | AI59: JEP | AM59: =(AB59+AD59+AE59)-(AH59+AK59) -> 0 | AN59: C02505 | AO59: 25 | AQ59: 46090 | AR59: 11/03/2026 | AS59: 25 | AT59: JEP | AX59: =(AM59+AO59+AP59)-(AS59+AV59) -> 0 | AY59: C02615 | AZ59: 25 | BB59: 46121 | BC59: 11/4/2026 | BD59: 25 | BE59: JEP | BI59: =(AX59+AZ59+BA59)-(BD59+BG59) -> 0 | BJ59: C02727 | BK59: 25 | BM59: 46151 | BT59: =(BI59+BK59+BL59)-(BO59+BR59) -> 25
A60: 080 | B60: PRECIADO BEGNETT MARIA MELBA | C60: 172.16.2.17 | D60: ACTIVO | E60: F | G60: 0802922195 | H60: BAÑOS | I60: SI | J60: GUADALUPANO ALTO | K60: caicedowilson81@gmail.com | L60: 0987875722 0995388377 | M60: 80bamariap | N60: 44986 | O60: 650M/650M | P60: 15 | Q60: 0 | R60: C02262 | S60: 38 | T60: 4 | U60: 46031 | V60: 46042 | W60: 38 | X60: Efectivo | Z60: 4 | AA60: Efectivo | AB60: =Q60+S60+T60-W60-Z60 -> 0 | AC60: SIN FACTURA | AD60: 38 | AE60: 4 | AF60: 46062 | AG60: 46072.496 | AH60: 42 | AI60: Efectivo | AM60: =(AB60+AD60+AE60)-(AH60+AK60) -> 0 | AN60: C02506 | AO60: 23 | AP60: 4 | AQ60: 46090 | AR60: 11/03/2026 | AS60: 23 | AT60: Efectivo | AV60: 4 | AW60: Efectivo | AX60: =(AM60+AO60+AP60)-(AS60+AV60) -> 0 | AY60: C02588 | AZ60: 23 | BA60: 4 | BB60: 46121 | BC60: 14/4/2026 | BD60: 23 | BE60: Efectivo | BG60: 4 | BH60: Efectivo | BI60: =(AX60+AZ60+BA60)-(BD60+BG60) -> 0 | BJ60: C02700 | BK60: 23 | BL60: 4 | BM60: 46151 | BT60: =(BI60+BK60+BL60)-(BO60+BR60) -> 27
A61: 081 | B61: MENDOZA CONTRERAS ANDREINA INDAURA | C61: 172.16.0.37 | D61: EN PROCESO | G61: 0952689297 | H61: BAÑOS | I61: SI | J61: AV. RICARDO DURAN SECTOR 4 ESQUINAS | K61: andreiinaindaura@gmail.com | L61: 0991369005 0968215337 | N61: 44989 | O61: 650M/650M | P61: GRATIS | Q61: 0 | T61: 0 | AB61: =Q61+S61+T61-W61-Z61 -> 0 | AC61: SIN FACTURA | AE61: 0 | AM61: =(AB61+AD61+AE61)-(AH61+AK61) -> 0 | AN61: SIN FACTURA | AP61: 0 | AX61: =(AM61+AO61+AP61)-(AS61+AV61) -> 0 | AY61: SIN FACTURA | BA61: 0 | BI61: =(AX61+AZ61+BA61)-(BD61+BG61) -> 0 | BL61: 0 | BT61: =(BI61+BK61+BL61)-(BO61+BR61) -> 0
A62: 082 | B62: VELASCO GONZALEZ DANNY GONZALO | C62: 172.16.17.8 | D62: ACTIVO | E62: M | G62: 0103770723 | H62: BAÑOS | I62: NO | J62: SECTOR COLEGIO MANUEL CORDOVA GALARZA | K62: dannyvelascogonzalez@gmail.com | L62: 0969576129 0998489033 | M62: 82badannyv | N62: 45010 | O62: 800M/800M | P62: 27 | Q62: 70 | R62: C02293 | S62: 32.2 | T62: 0 | U62: 46031 | V62: 46143 | W62: 32.2 | X62: Pichincha | AB62: =Q62+S62+T62-W62-Z62 -> 70 | AC62: C02397 | AD62: 32.2 | AE62: 0 | AF62: 46062 | AG62: 46057 | AH62: 32.2 | AI62: JEP | AM62: =(AB62+AD62+AE62)-(AH62+AK62) -> 70 | AN62: C02499 | AO62: 32.2 | AP62: 0 | AQ62: 46090 | AR62: 7/3/2026 | AS62: 32.2 | AT62: Pichincha | AX62: =(AM62+AO62+AP62)-(AS62+AV62) -> 70 | AY62: C02626 | AZ62: 32.2 | BA62: 0 | BB62: 46121 | BC62: 1/4/2026 | BD62: 32.2 | BE62: Pichincha | BI62: =(AX62+AZ62+BA62)-(BD62+BG62) -> 70 | BJ62: C02733 | BK62: 32.2 | BL62: 0 | BM62: 46151 | BN62: 5/5/2026 | BO62: 32.2 | BP62: Pichincha | BT62: =(BI62+BK62+BL62)-(BO62+BR62) -> 70
A63: 083 | B63: BARBECHO MOCHA JENNY TATIANA | C63: 172.16.0.36 | D63: INACTIVO | E63: F | G63: 0106416316 | H63: BAÑOS | I63: SI | J63: GUADALUPANO | K63: tatybarbecho97@gmail.com | L63: 0939008487 0997213899 0985141497 | M63: 83bajennyb | N63: 45012 | O63: 650M/650M | P63: 30 | Q63: 0 | T63: 0 | AB63: =Q63+S63+T63-W63-Z63 -> 0 | AC63: SIN FACTURA | AE63: 0 | AM63: =(AB63+AD63+AE63)-(AH63+AK63) -> 0 | AN63: SIN FACTURA | AP63: 0 | AX63: =(AM63+AO63+AP63)-(AS63+AV63) -> 0 | AY63: SIN FACTURA | BA63: 0 | BI63: =(AX63+AZ63+BA63)-(BD63+BG63) -> 0 | BL63: 0 | BT63: =(BI63+BK63+BL63)-(BO63+BR63) -> 0
A64: 084 | B64: GORDILLO CARDENAS MARIA NATALI | C64: 172.16.5.3 | D64: ACTIVO | E64: F | G64: 0106768021 | H64: BAÑOS | I64: SI | J64: AV. RICARDO DURAN Y LA PASADA | K64: nataligordillo08@hotmail.com | L64: 0983924978 0980876208 | N64: 45014 | O64: 650M/650M | Q64: -5.4 | R64: C02263 | S64: 23 | T64: 0 | U64: 46041 | V64: 46037 | W64: 23.6 | X64: Pichincha | AB64: =Q64+S64+T64-W64-Z64 -> -6 | AC64: SIN FACTURA | AD64: 23 | AE64: 0 | AF64: 46072 | AG64: 46067 | AH64: 18.2 | AI64: Efectivo | AM64: =(AB64+AD64+AE64)-(AH64+AK64) -> -1.2 | AN64: SIN FACTURA | AO64: 23 | AP64: 0 | AQ64: 46100 | AR64: 16/3/2026 | AS64: 21.8 | AT64: Pichincha | AX64: =(AM64+AO64+AP64)-(AS64+AV64) -> 0 | AY64: SIN FACTURA | AZ64: 23 | BA64: 0 | BB64: 46131 | BC64: 13/4/2026 | BD64: 23 | BE64: Pichincha | BI64: =(AX64+AZ64+BA64)-(BD64+BG64) -> 0 | BK64: 23 | BL64: 0 | BM64: 46161 | BT64: =(BI64+BK64+BL64)-(BO64+BR64) -> 23
A65: 085 | B65: MALLA MALLA JORGE EDWIN | C65: 172.16.0.46 | D65: ACTIVO | E65: M | F65: 12 | G65: 1105234007 | H65: BAÑOS | I65: SI | J65: PASEO DE LA GUADALUPANA Y CALLE LA CALIZA | K65: jmallamalla2011@hotmail.com | L65: 0990646671 0969534853 | M65: 85bajorgem | N65: 45567 | O65: 650M/650M | Q65: 0 | R65: C02264 | S65: 23 | T65: 0 | U65: 46031 | V65: 46031 | W65: 23 | X65: Efectivo | AB65: =Q65+S65+T65-W65-Z65 -> 0 | AC65: C02368 | AD65: 23 | AE65: 0 | AF65: 46062 | AG65: 46064.741 | AH65: 23 | AI65: Efectivo | AM65: =(AB65+AD65+AE65)-(AH65+AK65) -> 0 | AN65: C02470 | AO65: 23 | AP65: 0 | AQ65: 46090 | AR65: 20/03/2026 | AS65: 23 | AT65: Efectivo | AX65: =(AM65+AO65+AP65)-(AS65+AV65) -> 0 | AY65: C02589 | AZ65: 23 | BA65: 0 | BB65: 46121 | BC65: 46120.652 | BD65: 23 | BE65: Efectivo | BI65: =(AX65+AZ65+BA65)-(BD65+BG65) -> 0 | BJ65: C02701 | BK65: 23 | BL65: 0 | BM65: 46151 | BT65: =(BI65+BK65+BL65)-(BO65+BR65) -> 23
A66: 086 | B66: RAMON TAPIA WILSON HERMEL | C66: 172.16.5.4 | D66: ACTIVO | E66: M | G66: 0101675023 | H66: BAÑOS | I66: NO | J66: AV. RICARDO DURAN Y CALLE LA PASADA | K66: wilsonramontapia61@gmail.com | L66: 0988585409 2893396 | M66: 86bawilsonh | N66: 45022 | O66: 600M/600M | P66: 300 | Q66: 0 | S66: =89.6+55+15 -> 159.6 | T66: 40 | U66: 46036 | V66: 22/1/2026 | W66: 89.6 | X66: Efectivo | Z66: 40 | AA66: Efectivo | AB66: =Q66+S66+T66-W66-Z66 -> 70 | AC66: SIN FACTURA | AD66: =89.6 -> 89.6 | AE66: 40 | AF66: 46067 | AG66: 46079 | AH66: =70+129.6 -> 199.6 | AI66: Efectivo | AM66: =(AB66+AD66+AE66)-(AH66+AK66) -> 0 | AN66: SIN FACTURA | AO66: =89.6 -> 89.6 | AP66: 40 | AQ66: 46095 | AR66: 46113 | AS66: 129.6 | AT66: Efectivo | AX66: =(AM66+AO66+AP66)-(AS66+AV66) -> 0 | AY66: SIN FACTURA | AZ66: =89.6 -> 89.6 | BA66: 40 | BB66: 46126 | BC66: 46135.409 | BD66: 129.6 | BE66: Efectivo | BI66: =(AX66+AZ66+BA66)-(BD66+BG66) -> 0 | BK66: =89.6 -> 89.6 | BL66: 40 | BM66: 46156 | BT66: =(BI66+BK66+BL66)-(BO66+BR66) -> 129.6
A67: 088 | B67: PESANTEZ MOROCHO SEGUNDO AGUSTIN | C67: 172.16.1.34 | D67: ACTIVO | E67: M | G67: 0104504477 | H67: BAÑOS | I67: SI | J67: PASEO DE LA GUADALUPANO Y ALFONSO CARRION | K67: apesantez01@gmail.com | L67: 0994764616 0991792520 | M67: 88basegundoa | N67: 45026 | O67: 650M/650M | P67: 8 | Q67: 2.5 | S67: =23+21.5 -> 44.5 | T67: 0 | U67: 46031 | AB67: =Q67+S67+T67-W67-Z67 -> 47 | AC67: SIN FACTURA | AD67: 23 | AE67: 0 | AF67: 46062 | AG67: 46058 | AH67: =40+30 -> 70 | AI67: Efectivo | AM67: =(AB67+AD67+AE67)-(AH67+AK67) -> 0 | AN67: SIN FACTURA | AO67: 23 | AP67: 0 | AQ67: 46090 | AR67: 31/3/2026 | AS67: 23 | AT67: Efectivo | AX67: =(AM67+AO67+AP67)-(AS67+AV67) -> 0 | AY67: SIN FACTURA | AZ67: 23 | BA67: 0 | BB67: 46121 | BC67: 30/4/2026 | BD67: 23 | BE67: Efectivo | BI67: =(AX67+AZ67+BA67)-(BD67+BG67) -> 0 | BK67: 23 | BL67: 0 | BM67: 46151 | BT67: =(BI67+BK67+BL67)-(BO67+BR67) -> 23
A68: 089 | B68: VIZHCO SIGUA AMANDA LORENA | C68: 172.16.1.35 | D68: ACTIVO | E68: F | G68: 0105784300 | H68: BAÑOS | I68: SI | J68: AV. RICARDO DURAN CENTRO DE BAÑOS | K68: amalore_001@hotmail.com | L68: 0982748616 (0981193958 solo de emergecia) | M68: 89baamandav | N68: 45028 | O68: 650M/650M | P68: 5 | Q68: 0 | R68: C02265 | S68: 23 | T68: 0 | U68: 46031 | V68: 46048.759 | W68: 23 | X68: Efectivo | AB68: =Q68+S68+T68-W68-Z68 -> 0 | AC68: C02369 | AD68: 23 | AE68: 0 | AF68: 46062 | AG68: 46071 | AH68: 23 | AI68: Efectivo | AM68: =(AB68+AD68+AE68)-(AH68+AK68) -> 0 | AN68: C02471 | AO68: 23 | AP68: 0 | AQ68: 46090 | AR68: 46093.381 | AS68: 23 | AT68: Efectivo | AX68: =(AM68+AO68+AP68)-(AS68+AV68) -> 0 | AY68: C02590 | AZ68: 23 | BA68: 0 | BB68: 46121 | BC68: 20/4/2026 | BD68: 23 | BE68: Efectivo | BI68: =(AX68+AZ68+BA68)-(BD68+BG68) -> 0 | BJ68: C02702 | BK68: 23 | BL68: 0 | BM68: 46151 | BT68: =(BI68+BK68+BL68)-(BO68+BR68) -> 23
A69: 090_1 | B69: MATINEZ PATIÑO ROBERT ALEJANDRO (201) | C69: 172.16.1.62 | D69: ACTIVO | E69: F | G69: 0704566462 | H69: BAÑOS | I69: SI | J69: PASEO DE LA GUADALUPANA Y CALLE LA CALIZA | K69: alejandr10281@gmail.com | L69: 0978656550 0978773502 | M69: 090_1bapatriciag | N69: 45971 | O69: 600M/600M | P69: GRATIS | Q69: 0 | S69: 20.54 | T69: 0 | U69: 46046 | V69: 26/1/2026 | W69: 20.54 | X69: Pichincha | AB69: =Q69+S69+T69-W69-Z69 -> 0 | AC69: SIN FACTURA | AD69: 20.54 | AE69: 0 | AF69: 46077 | AG69: 46076 | AH69: 20.54 | AI69: JEP | AM69: =(AB69+AD69+AE69)-(AH69+AK69) -> 0 | AN69: SIN FACTURA | AO69: 20.54 | AP69: 0 | AQ69: 46105 | AR69: 22/3/2026 | AS69: 20.54 | AT69: Pichincha | AX69: =(AM69+AO69+AP69)-(AS69+AV69) -> 0 | AY69: SIN FACTURA | AZ69: 20.54 | BA69: 0 | BB69: 46136 | BC69: 23/4/2026 | BD69: 20.54 | BE69: Pichincha | BI69: =(AX69+AZ69+BA69)-(BD69+BG69) -> 0 | BK69: 20.54 | BL69: 0 | BM69: 46166 | BT69: =(BI69+BK69+BL69)-(BO69+BR69) -> 20.54
A70: 090_2 | B70: LOJA MOCHA JAIME ROMULO (303) | C70: 172.16.1.61 | D70: ACTIVO | E70: M | G70: 0152524625 | H70: BAÑOS | I70: SI | J70: PASEO DE LA GUADALUPANA | K70: patriciagalarza869@gmail.com | L70: 0967391098 0981070687 | N70: 45295 | O70: 600M/600M | P70: GRATIS | Q70: 0 | S70: 20.54 | T70: 0 | U70: 46023 | V70: 46048 | W70: 20.5 | X70: Pichincha | AB70: =Q70+S70+T70-W70-Z70 -> 0.04 | AC70: SIN FACTURA | AD70: 20.54 | AE70: 0 | AF70: 46054 | AG70: 46076 | AH70: 20.54 | AI70: Pichincha | AM70: =(AB70+AD70+AE70)-(AH70+AK70) -> 0.04 | AN70: SIN FACTURA | AO70: 20.54 | AP70: 0 | AQ70: 46082 | AR70: 26/3/2026 | AS70: 20 | AT70: JEP | AX70: =(AM70+AO70+AP70)-(AS70+AV70) -> 0.58 | AY70: SIN FACTURA | AZ70: 20.54 | BA70: 0 | BB70: 46113 | BC70: 28/4/2026 | BD70: 21.12 | BE70: Efectivo | BI70: =(AX70+AZ70+BA70)-(BD70+BG70) -> 0 | BK70: 20.54 | BL70: 0 | BM70: 46143 | BT70: =(BI70+BK70+BL70)-(BO70+BR70) -> 20.54
A71: 090_3 | B71: MORA SABOGAL YEDISON DARIAN (401) | C71: 172.16.1.68 | D71: EN PROCESO | E71: M | F71: 12 | G71: 1.023.942.344 | H71: BAÑOS | I71: SI | J71: PASEO DE LA GUADALUPANA Y CALLE LA CALIZA | L71: 0995252818 0987704482 | M71: 090_3moray | N71: 45728 | O71: 600M/600M | P71: GRATIS | Q71: 0 | S71: 20.54 | T71: 0 | U71: 46041 | AB71: =Q71+S71+T71-W71-Z71 -> 20.54 | AC71: SIN FACTURA | AD71: 10 | AE71: 0 | AF71: 46072 | AM71: =(AB71+AD71+AE71)-(AH71+AK71) -> 30.54 | AN71: SIN FACTURA | AO71: 10 | AP71: 0 | AQ71: 46100 | AX71: =(AM71+AO71+AP71)-(AS71+AV71) -> 40.54 | AY71: SIN FACTURA | AZ71: 10 | BA71: 0 | BB71: 46131 | BI71: =(AX71+AZ71+BA71)-(BD71+BG71) -> 50.54 | BK71: 10 | BL71: 0 | BM71: 46161 | BT71: =(BI71+BK71+BL71)-(BO71+BR71) -> 60.54
A72: 090_4 | B72: ALVAREZ PINTO DIEGO ARMANDO (301) | C72: 172.16.1.64 | D72: ACTIVO | G72: 24273724 | H72: BAÑOS | I72: SI | J72: PASEO DE LA GUADALUPANA Y CALLE LA CALIZA | K72: alvarezdieg1806@gmail.com | L72: 0968474516 | M72: 090_4bafarhanr | N72: 45959 | O72: 600M/600M | P72: GRATIS | Q72: 0 | S72: 20.54 | T72: 0 | U72: 46045 | V72: 26/1/2026 | W72: 20.55 | X72: Efectivo | AB72: =Q72+S72+T72-W72-Z72 -> -0.01 | AC72: SIN FACTURA | AD72: 20.54 | AE72: 0 | AF72: 46076 | AM72: =(AB72+AD72+AE72)-(AH72+AK72) -> 20.53 | AN72: SIN FACTURA | AO72: 20.54 | AP72: 0 | AQ72: 46104 | AX72: =(AM72+AO72+AP72)-(AS72+AV72) -> 41.07 | AY72: SIN FACTURA | AZ72: 20.54 | BA72: 0 | BB72: 46135 | BI72: =(AX72+AZ72+BA72)-(BD72+BG72) -> 61.61 | BK72: 20.54 | BL72: 0 | BM72: 46165 | BT72: =(BI72+BK72+BL72)-(BO72+BR72) -> 82.15
A73: 090_5 | B73: CABRERA ORTEGA KATHERINE JOMAIRA (402) | C73: 172.16.1.63 | D73: ACTIVO | E73: F | G73: 0105691992 | H73: BAÑOS | I73: SI | J73: PASEO DE LA GUADALUPANA Y CALLE LA CALIZA | K73: kethsa7726@hotmail.com | L73: 0994466328 | M73: 090_5bacabrerak | N73: 45521 | O73: 600M/600M | P73: GRATIS | Q73: 0 | S73: 20.54 | T73: 0 | U73: 46032 | V73: 46033 | W73: 20.54 | X73: JEP | AB73: =Q73+S73+T73-W73-Z73 -> 0 | AC73: SIN FACTURA | AD73: 20.54 | AE73: 0 | AF73: 46063 | AG73: 46063 | AH73: 20.54 | AI73: JEP | AM73: =(AB73+AD73+AE73)-(AH73+AK73) -> 0 | AN73: SIN FACTURA | AO73: 20.54 | AP73: 0 | AQ73: 46091 | AR73: 8/3/2026 | AS73: 20.54 | AT73: JEP | AX73: =(AM73+AO73+AP73)-(AS73+AV73) -> 0 | AY73: SIN FACTURA | AZ73: 20.54 | BA73: 0 | BB73: 46122 | BC73: 1/4/2026 | BD73: 20.54 | BE73: JEP | BI73: =(AX73+AZ73+BA73)-(BD73+BG73) -> 0 | BK73: 20.54 | BL73: 0 | BM73: 46152 | BT73: =(BI73+BK73+BL73)-(BO73+BR73) -> 20.54
A74: 090_6 | B74: TORRES NIEVECELA ROBERTO CARLOS (302) | C74: 172.16.1.60 | D74: ACTIVO | E74: F | F74: 24 | G74: 0105764419 | H74: BAÑOS | I74: SI | J74: PASEO DE LA GUADALUPANA Y CALLE LA CALIZA | K74: etotorres05@gmail.com | L74: 0984700259 0987196463 0969894581 | N74: 46146 | O74: 600M/600M | P74: GRATIS | Q74: 0 | S74: 20.54 | T74: 0 | U74: 46031 | V74: 46044 | W74: 20.54 | X74: Efectivo | AB74: =Q74+S74+T74-W74-Z74 -> 0 | AC74: SIN FACTURA | AD74: 20.54 | AE74: 0 | AF74: 46062 | AG74: 46073.765 | AH74: 20.54 | AI74: JEP | AM74: =(AB74+AD74+AE74)-(AH74+AK74) -> 0 | AN74: SIN FACTURA | AO74: 20.54 | AP74: 0 | AQ74: 46090 | AR74: 19/3/2026 | AS74: 20.55 | AT74: Efectivo | AX74: =(AM74+AO74+AP74)-(AS74+AV74) -> -0.01 | AY74: SIN FACTURA | AZ74: 20.54 | BA74: 0 | BB74: 46121 | BC74: 28/4/2026 | BD74: 20.53 | BE74: Efectivo | BI74: =(AX74+AZ74+BA74)-(BD74+BG74) -> 0 | BK74: 20.54 | BL74: 0 | BM74: 46151 | BT74: =(BI74+BK74+BL74)-(BO74+BR74) -> 20.54 | BU74: FACTURAR
A75: 090_7 | B75: CRIOLLO CRIOLLO ADRIANA CATALINA (402) | C75: 172.16.1.36 | D75: ACTIVO | E75: F | F75: 12 | G75: 0150084853 | H75: BAÑOS | I75: SI | J75: PASEO DE LA GUADALUPANA Y CALLE LA CALIZA | K75: criollo3cata93@gmail.com | L75: 0989993087 | N75: 45901 | O75: 600M/600M | P75: GRATIS | Q75: 0 | S75: 20.54 | T75: 2 | U75: 46023 | V75: 46030 | W75: 20.54 | X75: Pichincha | Z75: 2 | AA75: Pichincha | AB75: =Q75+S75+T75-W75-Z75 -> 0 | AC75: SIN FACTURA | AD75: 20.54 | AE75: 2 | AF75: 46054 | AG75: 46062 | AH75: 20.54 | AI75: Pichincha | AK75: 2 | AL75: Pichincha | AM75: =(AB75+AD75+AE75)-(AH75+AK75) -> 0 | AN75: SIN FACTURA | AO75: 20.54 | AP75: 2 | AQ75: 46082 | AR75: 6/3/2026 | AS75: 20.54 | AT75: Pichincha | AV75: 2 | AW75: Pichincha | AX75: =(AM75+AO75+AP75)-(AS75+AV75) -> 0 | AY75: SIN FACTURA | AZ75: 20.54 | BA75: 2 | BB75: 46113 | BC75: 7/4/2026 | BD75: 22.54 | BE75: Pichincha | BI75: =(AX75+AZ75+BA75)-(BD75+BG75) -> 0 | BK75: 20.54 | BL75: 2 | BM75: 46143 | BN75: 5/4/2026 | BO75: 20.54 | BP75: Pichincha | BR75: 2 | BS75: Pichincha | BT75: =(BI75+BK75+BL75)-(BO75+BR75) -> 0
A76: 090 | B76: DON JULIO EDIFICIO | C76: 172.16.1.66 | D76: ACTIVO | E76: F | G76: 0703139949 | H76: BAÑOS | I76: SI | J76: PASEO DE LA GUADALUPANA Y CALLE LA CALIZA | K76: julioguambana1972@gmail.com | L76: 0969667542 | M76: Aubajulioj | N76: 45047 | O76: 600M/600M | P76: GRATIS | Q76: 0 | S76: 60.2 | T76: 4.8 | U76: 46036 | V76: 46041 | W76: 60.2 | X76: Efectivo | Z76: 4.8 | AA76: Efectivo | AB76: =Q76+S76+T76-W76-Z76 -> 0 | AC76: SIN FACTURA | AD76: =40.2+15+5+5 -> 65.2 | AE76: 4.8 | AF76: 46067 | AG76: 46056 | AH76: 70 | AI76: Efectivo | AM76: =(AB76+AD76+AE76)-(AH76+AK76) -> 0 | AN76: SIN FACTURA | AO76: =40.2 -> 40.2 | AP76: 4.8 | AQ76: 46095 | AR76: 46109.461 | AS76: 45 | AT76: Efectivo | AX76: =(AM76+AO76+AP76)-(AS76+AV76) -> 0 | AY76: SIN FACTURA | AZ76: =40.2 -> 40.2 | BA76: 4.8 | BB76: 46126 | BC76: 2/5/2026 | BD76: 45 | BE76: Efectivo | BI76: =(AX76+AZ76+BA76)-(BD76+BG76) -> 0 | BK76: =40.2 -> 40.2 | BL76: 4.8 | BM76: 46156 | BT76: =(BI76+BK76+BL76)-(BO76+BR76) -> 45
A77: 090_8 | B77: MOCHA ZHINGRE CHRISTIAN RONALDO (203) | C77: 172.16.1.65 | D77: ACTIVO | E77: F | G77: 0107422545 | H77: BAÑOS | I77: SI | J77: PASEO DE LA GUADALUPANA Y CALLE LA CALIZA | L77: 0990302664 | M77: 90_8bamiltonc | N77: 45738 | O77: 600M/600M | P77: GRATIS | Q77: 0 | R77: C02209 | S77: 20.54 | T77: 0 | U77: 46047 | V77: 46035 | W77: 20.54 | X77: Efectivo | AB77: =Q77+S77+T77-W77-Z77 -> 0 | AC77: SIN FACTURA | AD77: 20.54 | AE77: 0 | AF77: 46078 | AG77: 46065.671 | AH77: 20.54 | AI77: Efectivo | AM77: =(AB77+AD77+AE77)-(AH77+AK77) -> 0 | AN77: C02507 | AO77: 20.54 | AP77: 0 | AQ77: 46106 | AR77: 19/3/2026 | AS77: 20.54 | AT77: Efectivo | AX77: =(AM77+AO77+AP77)-(AS77+AV77) -> 0 | AY77: C02542 | AZ77: 20.54 | BA77: 0 | BB77: 46137 | BC77: 46126.372 | BD77: 20.54 | BE77: Efectivo | BI77: =(AX77+AZ77+BA77)-(BD77+BG77) -> 0 | BJ77: C02656 | BK77: 20.54 | BL77: 0 | BM77: 46167 | BT77: =(BI77+BK77+BL77)-(BO77+BR77) -> 20.54
A78: 090_9 | B78: SANCHEZ HERRERA RORAIMA CAROLINA | C78: 172.16.1.38 | D78: ACTIVO | E78: F | G78: 0152174777 | H78: BAÑOS | I78: SI | J78: PASEO DE LA GUADALUPANA Y CALLE LA CALIZA | K78: rorac28@gmail.com | L78: 0960054945 0983211562 | N78: 45084 | O78: 600M/600M | P78: GRATIS | Q78: -0.1 | S78: 20.54 | T78: 0 | U78: 46041 | V78: 46043 | W78: 21 | X78: Pichincha | AB78: =Q78+S78+T78-W78-Z78 -> -0.56 | AC78: SIN FACTURA | AD78: 20.54 | AE78: 0 | AF78: 46072 | AG78: 46072 | AH78: 20.54 | AI78: Pichincha | AM78: =(AB78+AD78+AE78)-(AH78+AK78) -> -0.56 | AN78: SIN FACTURA | AO78: 20.54 | AP78: 0 | AQ78: 46100 | AR78: 19/3/2026 | AS78: 20.35 | AT78: Pichincha | AX78: =(AM78+AO78+AP78)-(AS78+AV78) -> -0.37 | AY78: SIN FACTURA | AZ78: 20.54 | BA78: 0 | BB78: 46131 | BC78: 10/04/2026 | BD78: 20 | BE78: Pichincha | BI78: =(AX78+AZ78+BA78)-(BD78+BG78) -> 0.17 | BK78: 20.54 | BL78: 0 | BM78: 46161 | BT78: =(BI78+BK78+BL78)-(BO78+BR78) -> 20.71
A79: 091 | B79: LOJA CRIOLLO DEISY ESTHER | C79: 172.16.1.37 | D79: ACTIVO | E79: F | G79: 0104161716 | H79: BAÑOS | I79: NO | J79: CALLE EL CALVARIO | K79: facturas.labsll@gmail.com | L79: 0939113102 0993462699 | N79: 45777 | O79: 650M/650M | P79: 15 | Q79: 0 | S79: 23 | T79: 0 | U79: 46031 | V79: 22/1/2026 | W79: 23 | X79: Efectivo | AB79: =Q79+S79+T79-W79-Z79 -> 0 | AC79: SIN FACTURA | AD79: 23 | AE79: 0 | AF79: 46062 | AG79: 46071 | AH79: 23 | AI79: Efectivo | AM79: =(AB79+AD79+AE79)-(AH79+AK79) -> 0 | AN79: SIN FACTURA | AO79: 23 | AP79: 0 | AQ79: 46090 | AR79: 46099.398 | AS79: 23 | AT79: Efectivo | AX79: =(AM79+AO79+AP79)-(AS79+AV79) -> 0 | AY79: SIN FACTURA | AZ79: 23 | BA79: 0 | BB79: 46121 | BC79: 17/04/2026 | BD79: 23 | BE79: Efectivo | BI79: =(AX79+AZ79+BA79)-(BD79+BG79) -> 0 | BK79: 23 | BL79: 0 | BM79: 46151 | BT79: =(BI79+BK79+BL79)-(BO79+BR79) -> 23
A80: 093 | B80: VIZHCO ZHINGRI EDGAR PATRICIO | C80: 172.16.2.19 | D80: CORTESIA | E80: M | H80: BAÑOS | I80: NO | L80: 0999183220 | M80: 93baedgarv | N80: 45068 | O80: 100M/100M | P80: GRATIS | Q80: 0 | T80: 0 | AB80: =Q80+S80+T80-W80-Z80 -> 0 | AC80: SIN FACTURA | AE80: 0 | AM80: =(AB80+AD80+AE80)-(AH80+AK80) -> 0 | AN80: SIN FACTURA | AP80: 0 | AX80: =(AM80+AO80+AP80)-(AS80+AV80) -> 0 | AY80: SIN FACTURA | BA80: 0 | BI80: =(AX80+AZ80+BA80)-(BD80+BG80) -> 0 | BL80: 0 | BT80: =(BI80+BK80+BL80)-(BO80+BR80) -> 0
A81: 096 | B81: DAMIAN NIVICELA BYRON MARCELO | C81: 172.16.3.6 | D81: INACTIVO | E81: M | F81: 18 | G81: 0151121738 | H81: YANUNCAY | I81: NO | J81: PANAMERICANA FRENTE A LA CALLE DEL TUCUMAN | K81: nivicelamarcelo7@gmail.com | L81: 0979254659 | N81: 45079 | O81: 650M/650M | P81: 15 | Q81: 123 | T81: 0 | U81: 46041 | AB81: =Q81+S81+T81-W81-Z81 -> 123 | AC81: SIN FACTURA | AE81: 0 | AF81: 46072 | AM81: =(AB81+AD81+AE81)-(AH81+AK81) -> 123 | AN81: SIN FACTURA | AP81: 0 | AQ81: 46100 | AX81: =(AM81+AO81+AP81)-(AS81+AV81) -> 123 | AY81: SIN FACTURA | BA81: 0 | BB81: 46131 | BI81: =(AX81+AZ81+BA81)-(BD81+BG81) -> 123 | BL81: 0 | BM81: 46161 | BT81: =(BI81+BK81+BL81)-(BO81+BR81) -> 123
A82: 097 | B82: NIVICELA MOROCHO CARLOS ABDON | C82: 172.16.0.38 | D82: INACTIVO | E82: M | F82: 18 | G82: 0103288171 | H82: BAÑOS | I82: NO | J82: NARANCAY | K82: nivicela2@icloud.com | L82: 1 (203) 832 9607 0980704449 0980271941 | N82: 45092 | O82: 100M/100M | P82: 15 | Q82: 0 | T82: 0 | AB82: =Q82+S82+T82-W82-Z82 -> 0 | AC82: SIN FACTURA | AE82: 0 | AM82: =(AB82+AD82+AE82)-(AH82+AK82) -> 0 | AN82: SIN FACTURA | AP82: 0 | AX82: =(AM82+AO82+AP82)-(AS82+AV82) -> 0 | AY82: SIN FACTURA | BA82: 0 | BI82: =(AX82+AZ82+BA82)-(BD82+BG82) -> 0 | BL82: 0 | BT82: =(BI82+BK82+BL82)-(BO82+BR82) -> 0
A83: 098 | B83: SALAZAR SALAZAR JESUS ARLEY | C83: 172.16.0.39 | D83: INACTIVO | G83: 0996430424 | H83: BAÑOS | I83: SI | J83: AV. RICARDO DURAN Y SALVADOR J. FERNANDEZ | K83: paolabuitron0907@gmail.com | L83: 0996430424 0961779501 | N83: 45104 | O83: 650M/650M | P83: GRATIS | Q83: 0 | T83: 0 | AB83: =Q83+S83+T83-W83-Z83 -> 0 | AC83: SIN FACTURA | AE83: 0 | AM83: =(AB83+AD83+AE83)-(AH83+AK83) -> 0 | AN83: SIN FACTURA | AP83: 0 | AX83: =(AM83+AO83+AP83)-(AS83+AV83) -> 0 | AY83: SIN FACTURA | BA83: 0 | BI83: =(AX83+AZ83+BA83)-(BD83+BG83) -> 0 | BL83: 0 | BT83: =(BI83+BK83+BL83)-(BO83+BR83) -> 0
A84: 099 | B84: ALVARADO BAQUE ABIGAIL JOHANNA | C84: 172.16.1.39 | D84: INACTIVO | F84: 12 | G84: 0919352153 | H84: BAÑOS | I84: SI | J84: AV. RICARDO DURAN Y ALFONSO CARRION | K84: lababy1721@gmail.com | L84: 0960824725 0990222506 0990783443 | N84: 45113 | O84: 650M/650M | P84: GRATIS | Q84: 0 | T84: 0 | AB84: =Q84+S84+T84-W84-Z84 -> 0 | AC84: SIN FACTURA | AE84: 0 | AM84: =(AB84+AD84+AE84)-(AH84+AK84) -> 0 | AN84: SIN FACTURA | AP84: 0 | AX84: =(AM84+AO84+AP84)-(AS84+AV84) -> 0 | AY84: SIN FACTURA | BA84: 0 | BI84: =(AX84+AZ84+BA84)-(BD84+BG84) -> 0 | BL84: 0 | BT84: =(BI84+BK84+BL84)-(BO84+BR84) -> 0
A85: 100 | B85: CARDENAS CORTEZ DAMARIZ DAYANA | C85: 172.16.4.12 | D85: EN PROCESO | E85: F | G85: 0151207362 | H85: BAÑOS | I85: SI | J85: ALFONSO CARION Y AV. RICARDO DURAN | K85: damaruz99@gmail.com | L85: 0962657457 0992281848 | N85: 45118 | O85: 650M/650M | P85: GRATIS | Q85: 0 | R85: C02266 | S85: 23 | T85: 0 | U85: 46041 | AB85: =Q85+S85+T85-W85-Z85 -> 23 | AC85: C02370 | AD85: 10 | AE85: 0 | AF85: 46072 | AM85: =(AB85+AD85+AE85)-(AH85+AK85) -> 33 | AN85: SIN FACTURA | AO85: =10+15 -> 25 | AP85: 0 | AQ85: 46100 | AR85: 12/3/2026 | AS85: 58 | AT85: Efectivo | AX85: =(AM85+AO85+AP85)-(AS85+AV85) -> 0 | AY85: SIN FACTURA | AZ85: 0 | BA85: 0 | BB85: 46131 | BI85: =(AX85+AZ85+BA85)-(BD85+BG85) -> 0 | BK85: 0 | BL85: 0 | BM85: 46161 | BT85: =(BI85+BK85+BL85)-(BO85+BR85) -> 0
A86: 101 | B86: IBAÑEZ QUIROLA GLENDA MARISOL | C86: 172.16.1.40 | D86: INACTIVO | E86: F | G86: 0703383893 | H86: BAÑOS | I86: SI | J86: VIA MINAS | K86: glendamarisol78@gmail.com | L86: 0985583757 | M86: 101baglendai | N86: 45120 | O86: 650M/650M | P86: GRATIS | Q86: 0 | R86: C02267 | S86: 10 | T86: 0 | U86: 46052 | V86: 46174 | W86: 10 | X86: Efectivo | AB86: =Q86+S86+T86-W86-Z86 -> 0 | AC86: SIN FACTURA | AD86: 0 | AE86: 0 | AF86: 46083 | AM86: =(AB86+AD86+AE86)-(AH86+AK86) -> 0 | AN86: SIN FACTURA | AO86: 0 | AP86: 0 | AQ86: 46114 | AX86: =(AM86+AO86+AP86)-(AS86+AV86) -> 0 | AY86: SIN FACTURA | AZ86: 0 | BA86: 0 | BB86: 46144 | BI86: =(AX86+AZ86+BA86)-(BD86+BG86) -> 0 | BK86: 0 | BL86: 0 | BM86: 46175 | BT86: =(BI86+BK86+BL86)-(BO86+BR86) -> 0
A87: 102 | B87: IBAÑEZ QUIROLA FRANCISCO ENRIQUE | C87: 172.16.1.41 | D87: INACTIVO | G87: 1716387830 | H87: BAÑOS | I87: SI | J87: VIA MINAS | K87: frankibanezquirola@gmail.com | L87: 0990860328 0967896005 | M87: 102bafranciscoi | N87: 45127 | O87: 650M/650M | P87: GRATIS | Q87: 0 | T87: 0 | AB87: =Q87+S87+T87-W87-Z87 -> 0 | AC87: SIN FACTURA | AE87: 0 | AM87: =(AB87+AD87+AE87)-(AH87+AK87) -> 0 | AN87: SIN FACTURA | AP87: 0 | AX87: =(AM87+AO87+AP87)-(AS87+AV87) -> 0 | AY87: SIN FACTURA | BA87: 0 | BI87: =(AX87+AZ87+BA87)-(BD87+BG87) -> 0 | BL87: 0 | BT87: =(BI87+BK87+BL87)-(BO87+BR87) -> 0
A88: 103 | B88: PEREZ GUAMAN OLGER ALONSO | C88: 172.16.1.42 | D88: INACTIVO | E88: M | G88: 0106292097 | H88: BAÑOS | I88: SI | J88: TRES CRUCES | K88: operezguaman@gmail.com | L88: 0981269456 | N88: 45132 | O88: 650M/650M | P88: 20 | Q88: 0 | T88: 0 | AB88: =Q88+S88+T88-W88-Z88 -> 0 | AC88: SIN FACTURA | AE88: 0 | AM88: =(AB88+AD88+AE88)-(AH88+AK88) -> 0 | AN88: SIN FACTURA | AP88: 0 | AX88: =(AM88+AO88+AP88)-(AS88+AV88) -> 0 | AY88: SIN FACTURA | BA88: 0 | BI88: =(AX88+AZ88+BA88)-(BD88+BG88) -> 0 | BL88: 0 | BT88: =(BI88+BK88+BL88)-(BO88+BR88) -> 0
A89: 104 | B89: MACHUCA PULLA BLANCA NATIVIDAD | C89: 172.16.5.6 | D89: ACTIVO | E89: F | G89: 0103797643 | H89: BAÑOS | I89: NO | J89: AV. RICARDO DURAN Y 24 DE MAYO | K89: blankima98@gmail.com | L89: 0989783695 0969698550 | M89: 104bablancam | N89: 45916 | O89: 650M/650M | P89: GRATIS | Q89: 0 | S89: 25 | T89: 0 | U89: 46041 | V89: 46037 | W89: 25 | X89: Pichincha | AB89: =Q89+S89+T89-W89-Z89 -> 0 | AC89: SIN FACTURA | AD89: 25 | AE89: 0 | AF89: 46072 | AG89: 46076 | AH89: 25 | AI89: Pichincha | AM89: =(AB89+AD89+AE89)-(AH89+AK89) -> 0 | AN89: C02508 | AO89: 25 | AP89: 0 | AQ89: 46100 | AR89: 18/3/2026 | AS89: 25 | AT89: JEP | AX89: =(AM89+AO89+AP89)-(AS89+AV89) -> 0 | AY89: C02616 | AZ89: =25+35 -> 60 | BA89: 0 | BB89: 46131 | BC89: 15/4/2026 | BD89: 25 | BE89: JEP | BI89: =(AX89+AZ89+BA89)-(BD89+BG89) -> 35 | BK89: =25+35 -> 60 | BL89: 0 | BM89: 46161 | BT89: =(BI89+BK89+BL89)-(BO89+BR89) -> 95
A90: 105 | B90: MORAN MOREJON JESSICA ALEXANDRA | C90: 172.16.2.20 | D90: ACTIVO | E90: FISICO | F90: 24 | G90: 0924314578 | H90: BAÑOS | I90: SI | J90: PASEO DE LA GUADALUPANA | K90: jessi_kmoran_84@hotmail.com | L90: 0981973771 | M90: 106bajessicam | N90: 46051 | O90: 650M/650M | P90: GRATIS | Q90: -0.2 | R90: C02268 | S90: 23 | T90: 0 | U90: 46041 | V90: 22/1/2026 | W90: 23 | X90: JEP | AB90: =Q90+S90+T90-W90-Z90 -> -0.2 | AC90: C02371 | AD90: 23 | AE90: 0 | AF90: 46072 | AG90: 46076 | AH90: 23 | AI90: JEP | AM90: =(AB90+AD90+AE90)-(AH90+AK90) -> -0.2 | AN90: C02472 | AO90: 23 | AP90: 0 | AQ90: 46100 | AR90: 22/3/2026 | AS90: 23 | AT90: JEP | AX90: =(AM90+AO90+AP90)-(AS90+AV90) -> -0.2 | AY90: C02591 | AZ90: 23 | BA90: 0 | BB90: 46131 | BC90: 15/4/2026 | BD90: 25 | BE90: JEP | BI90: =(AX90+AZ90+BA90)-(BD90+BG90) -> -2.2 | BJ90: C02703 | BK90: 23 | BL90: 0 | BM90: 46161 | BT90: =(BI90+BK90+BL90)-(BO90+BR90) -> 20.8
A91: 106 | B91: MORALES TIGRE ROSA FABIOLA | C91: 172.16.2.21 | D91: INACTIVO | E91: F | G91: 0105899157 | H91: BAÑOS | I91: SI | J91: CALLE GUADALUPANO ALTO | K91: fabiolamorales22@hotmail.com | L91: 0996616621 0998012082 | N91: 45163 | O91: 650M/650M | P91: 15 | Q91: 0 | T91: 0 | AB91: =Q91+S91+T91-W91-Z91 -> 0 | AC91: SIN FACTURA | AE91: 0 | AM91: =(AB91+AD91+AE91)-(AH91+AK91) -> 0 | AN91: SIN FACTURA | AP91: 0 | AX91: =(AM91+AO91+AP91)-(AS91+AV91) -> 0 | AY91: SIN FACTURA | BA91: 0 | BI91: =(AX91+AZ91+BA91)-(BD91+BG91) -> 0 | BL91: 0 | BT91: =(BI91+BK91+BL91)-(BO91+BR91) -> 0
A92: 107 | B92: GUAMAN YUPANGUI LAURA GUADALUPE | C92: 172.16.1.43 | D92: ACTIVO | E92: FISICO | G92: 0103794244 | H92: BAÑOS | I92: NO | J92: CEMENTERIO VIA MINAS | K92: miazoe2011@icloud.com | L92: 1(203)788-4370 0995479010 0991556055 | N92: 45169 | O92: 650M/650M | P92: GRATIS | Q92: 0 | R92: C02269 | S92: 23 | T92: 0 | U92: 46031 | V92: 46031 | W92: 25 | X92: JEP | AB92: =Q92+S92+T92-W92-Z92 -> -2 | AC92: C02372 | AD92: 23 | AE92: 0 | AF92: 46062 | AG92: 46066 | AH92: =21+23 -> 44 | AI92: JEP | AM92: =(AB92+AD92+AE92)-(AH92+AK92) -> -23 | AN92: C02473 | AO92: 23 | AP92: 0 | AQ92: 46090 | AX92: =(AM92+AO92+AP92)-(AS92+AV92) -> 0 | AY92: C02592 | AZ92: 23 | BA92: 0 | BB92: 46121 | BC92: 22/4/2026 | BD92: 23 | BE92: JEP | BI92: =(AX92+AZ92+BA92)-(BD92+BG92) -> 0 | BJ92: C02704 | BK92: 23 | BL92: 0 | BM92: 46151 | BT92: =(BI92+BK92+BL92)-(BO92+BR92) -> 23
A93: 108 | B93: FEGANS CHAMBA TANIA GABRIELA | C93: 172.16.11.5 | D93: ACTIVO | E93: NO HAY | G93: 0107419582 | H93: BAÑOS | I93: NO | J93: RIO PORAÑO Y RIO MISSISIPI | K93: gonzalezmjs54@gmail.com | L93: 0958847439 | M93: 108bafegansc | N93: 6692583 | O93: 650M/650M | P93: GRATIS | Q93: 0.2 | R93: C02270 | S93: 23 | T93: 0 | U93: 46041 | V93: 46034 | W93: 23 | X93: Pichincha | AB93: =Q93+S93+T93-W93-Z93 -> 0.2 | AC93: C02373 | AD93: 23 | AE93: 0 | AF93: 46072 | AG93: 46066 | AH93: 23 | AI93: Pichincha | AM93: =(AB93+AD93+AE93)-(AH93+AK93) -> 0.2 | AN93: C02474 | AO93: 23 | AP93: 0 | AQ93: 46100 | AX93: 10 | AY93: C02593 | AZ93: 23 | BA93: 0 | BB93: 46131 | BI93: =(AX93+AZ93+BA93)-(BD93+BG93) -> 33 | BJ93: C02705 | BK93: 23 | BL93: 0 | BM93: 46161 | BT93: =(BI93+BK93+BL93)-(BO93+BR93) -> 56
A94: 109 | B94: NAREA CASTRO ADRIANA MAGDALENA | C94: 172.16.1.44 | D94: INACTIVO | G94: 0104867627 | H94: BAÑOS | I94: SI | J94: CAPILLA COCHAPAMBA BAÑOS | K94: adrivalentina1@hotmail.com | L94: 0960587655 0962963303 | M94: 109baadrianan | N94: 45175 | O94: 650M/650M | P94: 45 | Q94: 0 | T94: 0 | AB94: =Q94+S94+T94-W94-Z94 -> 0 | AC94: SIN FACTURA | AE94: 0 | AM94: =(AB94+AD94+AE94)-(AH94+AK94) -> 0 | AN94: SIN FACTURA | AP94: 0 | AX94: =(AM94+AO94+AP94)-(AS94+AV94) -> 0 | AY94: SIN FACTURA | BA94: 0 | BI94: =(AX94+AZ94+BA94)-(BD94+BG94) -> 0 | BL94: 0 | BT94: =(BI94+BK94+BL94)-(BO94+BR94) -> 0
A95: 110 | B95: GUAMAN DURAN EDGAR IVAN | C95: 172.16.4.2 | D95: ACTIVO | E95: NO HAY | G95: 0102055993 | H95: BAÑOS | I95: NO | J95: ALFONSO CARION Y AV. RICARDO DURAN | K95: reparacionesdieselguanman@hotmail.com | L95: 0992319726 | M95: 110baguamane | N95: 45176 | O95: 650M/650M | P95: GRATIS | Q95: 0 | S95: 23 | T95: 0 | U95: 46041 | V95: 46046.756 | W95: 23 | X95: Efectivo | AB95: =Q95+S95+T95-W95-Z95 -> 0 | AC95: C02374 | AD95: 23 | AE95: 0 | AF95: 46072 | AG95: 46075.864 | AH95: 20 | AI95: Efectivo | AM95: =(AB95+AD95+AE95)-(AH95+AK95) -> 3 | AN95: C02475 | AO95: 23 | AP95: 0 | AQ95: 46100 | AR95: 46111.777 | AS95: 26 | AT95: Efectivo | AX95: =(AM95+AO95+AP95)-(AS95+AV95) -> 0 | AY95: C02594 | AZ95: 23 | BA95: 0 | BB95: 46131 | BC95: 27/4/2026 | BD95: 23 | BE95: Efectivo | BI95: =(AX95+AZ95+BA95)-(BD95+BG95) -> 0 | BJ95: C02706 | BK95: 23 | BL95: 0 | BM95: 46161 | BT95: =(BI95+BK95+BL95)-(BO95+BR95) -> 23
A96: 111 | B96: VIZHCO HORTENCIA MARGARITA | C96: 172.16.1.45 | D96: EN PROCESO | E96: F | H96: BAÑOS | I96: NO | J96: MINAS BAÑOS | N96: 45181 | O96: 600M/600M | P96: GRATIS | Q96: 40.54 | T96: 0 | U96: 46036 | AB96: =Q96+S96+T96-W96-Z96 -> 40.54 | AC96: SIN FACTURA | AE96: 0 | AF96: 46067 | AM96: =(AB96+AD96+AE96)-(AH96+AK96) -> 40.54 | AN96: SIN FACTURA | AP96: 0 | AQ96: 46095 | AX96: =(AM96+AO96+AP96)-(AS96+AV96) -> 40.54 | AY96: SIN FACTURA | BA96: 0 | BB96: 46126 | BI96: =(AX96+AZ96+BA96)-(BD96+BG96) -> 40.54 | BL96: 0 | BM96: 46156 | BT96: =(BI96+BK96+BL96)-(BO96+BR96) -> 40.54
A97: 112 | B97: RAMON TAPIA WILSON HERMEL (CABAÑAS) | C97: 172.16.16.2 | D97: ACTIVO | E97: M | G97: 0101675023 | H97: BAÑOS | I97: NO | J97: AV. RICARDO DURAN | K97: wilsonramontapia61@gmail.com | N97: 45189 | O97: 650M/650M | P97: GRATIS | Q97: 0 | S97: 27 | T97: 4 | U97: 46036 | W97: 31 | AB97: =Q97+S97+T97-W97-Z97 -> 0 | AC97: SIN FACTURA | AD97: 27 | AE97: 4 | AF97: 46067 | AG97: 46090 | AH97: 30.4 | AI97: Efectivo | AM97: =(AB97+AD97+AE97)-(AH97+AK97) -> 0.6 | AN97: SIN FACTURA | AO97: 27 | AP97: 4 | AQ97: 46095 | AR97: 1/4/2026 | AS97: 27 | AT97: Efectivo | AV97: 4.6 | AW97: Efectivo | AX97: =(AM97+AO97+AP97)-(AS97+AV97) -> 0 | AY97: SIN FACTURA | AZ97: 27 | BA97: 4 | BB97: 46126 | BC97: 46135.409 | BD97: 31 | BE97: Efectivo | BI97: =(AX97+AZ97+BA97)-(BD97+BG97) -> 0 | BK97: 27 | BL97: 4 | BM97: 46156 | BT97: =(BI97+BK97+BL97)-(BO97+BR97) -> 31
A98: 113 | B98: GUERRERO DUCHI MERI GUADALUPE | C98: 172.16.4.3 | D98: EN PROCESO | E98: F | G98: 0101849339 | H98: BAÑOS | I98: NO | J98: ALFONSO CARION Y AV. RICARDO DURAN | K98: facturas.labsll@gmail.com | L98: 0989482929 | N98: 45183 | O98: 100M/100M | P98: GRATIS | Q98: 0 | T98: 0 | AB98: =Q98+S98+T98-W98-Z98 -> 0 | AC98: SIN FACTURA | AE98: 0 | AM98: =(AB98+AD98+AE98)-(AH98+AK98) -> 0 | AN98: SIN FACTURA | AP98: 0 | AX98: =(AM98+AO98+AP98)-(AS98+AV98) -> 0 | AY98: SIN FACTURA | BA98: 0 | BI98: =(AX98+AZ98+BA98)-(BD98+BG98) -> 0 | BL98: 0 | BT98: =(BI98+BK98+BL98)-(BO98+BR98) -> 0
A99: 114 | B99: ARMIJOS HUANCA EDWIN REMIGIO | C99: 172.16.2.22 | D99: INACTIVO | G99: 1103819650 | H99: BAÑOS | I99: SI | J99: CALLE LA CALIZA Y AV. RICARDO DURAN | K99: edwinarmijos740@gmail.com | L99: 0986077600 | M99: 114baedwina | N99: 45193 | O99: 650M/650M | P99: GRATIS | Q99: 0 | T99: 0 | AB99: =Q99+S99+T99-W99-Z99 -> 0 | AC99: SIN FACTURA | AE99: 0 | AM99: =(AB99+AD99+AE99)-(AH99+AK99) -> 0 | AN99: SIN FACTURA | AP99: 0 | AX99: =(AM99+AO99+AP99)-(AS99+AV99) -> 0 | AY99: SIN FACTURA | BA99: 0 | BI99: =(AX99+AZ99+BA99)-(BD99+BG99) -> 0 | BL99: 0 | BT99: =(BI99+BK99+BL99)-(BO99+BR99) -> 0
A100: 115 | B100: URGILES CHACON SARA VERONICA | C100: 172.16.7.21 | D100: ACTIVO | E100: F | G100: 0103863122 | H100: BAÑOS | I100: SI | J100: CALLE LA CALIZA Y AV. RICARDO DURAN | K100: lizurgileszg@gmail.com | L100: 0986562562 | M100: 114basarau | N100: 46177 | O100: 650M/650M | P100: GRATIS | Q100: 0 | R100: C02198 | S100: 17.25 | T100: 0 | U100: 46032 | V100: 46036 | W100: 17.25 | X100: Efectivo | AB100: =Q100+S100+T100-W100-Z100 -> 0 | AC100: C02309 | AD100: 17.25 | AE100: 0 | AF100: 46063 | AG100: 46062 | AH100: 17.25 | AI100: Efectivo | AM100: =(AB100+AD100+AE100)-(AH100+AK100) -> 0 | AN100: C02419 | AO100: 17.25 | AP100: 0 | AQ100: 46091 | AR100: 19/3/2026 | AS100: 17.25 | AT100: Efectivo | AX100: =(AM100+AO100+AP100)-(AS100+AV100) -> 0 | AY100: C02532 | AZ100: 17.25 | BA100: 0 | BB100: 46122 | BC100: 16/4/2026 | BD100: 17.25 | BE100: Efectivo | BI100: =(AX100+AZ100+BA100)-(BD100+BG100) -> 0 | BJ100: C02646 | BK100: 17.25 | BL100: 0 | BM100: 46152 | BT100: =(BI100+BK100+BL100)-(BO100+BR100) -> 17.25
...

Sheet SAYAUSI
B1: NAME | C1: IP | D1: ESTADO | E1: CED | F1: TIEMPO | G1: DOCUMENTS | H1: PARISH | I1: RENT | J1: DIRECTION | K1: MAIL | L1: CEL | M1: CUENTA | N1: INSTALATION DATE | O1: PLAN | P1: INS_PAYMENT | Q1: SALDO | R1: FACT DE DIC | S1: DECEMBER | T1: APP | U1: PAYMENT DATE | V1: CLIENT PAYMENT DATE | W1: INTERNET PAYMENT | X1: BANK | Y1: COD | Z1: TV | AA1: BANK | AB1: SALDO | AC1: FACT JANUARY | AD1: INTERNET PAYMENT | AE1: APP | AF1: PAYMENT DATE | AG1: CLIENT PAYMENT DATE | AH1: INTERNET PAYMENT | AI1: BANK | AJ1: COD | AK1: PLUS | AL1: BANK_PLUS | AM1: SALDO | AN1: FACTURAS | AO1: INTERNET PAYMENT | AP1: APP | AQ1: PAYMENT DATE | AR1: CLIENT PAYMENT DATE | AS1: INTERNET PAYMENT | AT1: BANK | AU1: COD | AV1: PLUS | AW1: BANK_PLUS | AX1: SALDO | AY1: FACTURAS | AZ1: INTERNET PAYMENT | BA1: APP | BB1: PAYMENT DATE | BC1: CLIENT PAYMENT DATE | BD1: INTERNET PAYMENT | BE1: BANK | BF1: COD | BG1: PLUS | BH1: BANK_PLUS | BI1: SALDO | BJ1: FACTURAS | BK1: INTERNET PAYMENT | BL1: APP | BM1: PAYMENT DATE | BN1: CLIENT PAYMENT DATE | BO1: INTERNET PAYMENT | BP1: BANK | BQ1: COD | BR1: PLUS | BS1: BANK_PLUS | BT1: SALDO | BU1: FACTURAS
A2: 001 | B2: YANEZ OCHOA MICHAEL LEONARDO | C2: 172.18.4.5 | D2: ACTIVO | E2: NO | F2: 24 | G2: 0105542450 | H2: SAYAUSI | I2: SI | J2: ORDOÑEZ LASSO SECTOR SANTA MARIA | K2: yaneztarquino91@gmail.com | L2: 0959229482 0980598322 0980650419 +593 98 079 8919 | N2: 46051 | O2: 600M/600M | P2: 16.8 | Q2: 0 | S2: 17.25 | U2: 46032 | V2: 46038 | W2: 17.25 | X2: Pichincha | Y2: 120476 | AB2: =S2+T2-W2-Z2 -> 0 | AC2: SIN FACTURA | AD2: 20.54 | AF2: 46063 | AG2: 46067 | AH2: 20.54 | AI2: Pichincha | AJ2: 128542 | AM2: =(AB2+AD2+AE2)-(AH2+AK2) -> 0 | AN2: SIN FACTURA | AO2: 20.54 | AQ2: 46091 | AR2: 24/3/2026 | AS2: 20.54 | AT2: Pichincha | AU2: 138498 | AX2: =(AM2+AO2+AP2)-(AS2+AV2) -> 0 | AY2: SIN FACTURA | AZ2: 20.54 | BB2: 46122 | BC2: 19/4/2026 | BD2: 20.54 | BE2: Pichincha | BF2: 142032 | BI2: =(AX2+AZ2+BA2)-(BD2+BG2) -> 0 | BK2: 20.54 | BM2: 46152 | BT2: =(BI2+BK2+BL2)-(BO2+BR2) -> 20.54
A3: 002 | B3: PACHECO PRADO FELIX JOSE | C3: 172.18.2.9 | D3: ACTIVO | E3: M | G3: 0104107701 | H3: SAYAUSI | I3: NO | J3: ORDOÑEZ LASSO FRENTE GASOLINERA PRIMAX | K3: facturas.labsll@gmail.com | L3: 0986600649 0999790946 | M3: 02sayafelixp | N3: 44481 | O3: 650M/650M | P3: GRATIS | Q3: 2.75 | S3: 17.25 | U3: 46041 | V3: 46045 | W3: 20 | X3: Pichincha | AB3: =Q3+S3+T3-W3-Z3 -> 0 | AC3: SIN FACTURA | AD3: 17.25 | AF3: 46072 | AG3: 46080 | AH3: 20 | AI3: Pichincha | AM3: =(AB3+AD3+AE3)-(AH3+AK3) -> -2.75 | AN3: SIN FACTURA | AO3: 17.25 | AQ3: 46100 | AR3: 30/3/2026 | AS3: 20 | AT3: Pichincha | AX3: =(AM3+AO3+AP3)-(AS3+AV3) -> -5.5 | AY3: SIN FACTURA | AZ3: 17.25 | BB3: 46131 | BI3: =(AX3+AZ3+BA3)-(BD3+BG3) -> 11.75 | BK3: 17.25 | BM3: 46161 | BT3: =(BI3+BK3+BL3)-(BO3+BR3) -> 29
A4: 006 | B4: GUTAMA EHUÑIR DIGNA NOEMI | C4: 172.18.2.4 | D4: INACTIVO | G4: 0107345217 | H4: SAYAUSI | I4: SI | J4: ORDOÑEZ LASSO Y HIERBA LUISA | K4: dignagutama9@hotmail.com | L4: 0986096326 | N4: 45184 | O4: 100M/100M | P4: GRATIS | Q4: 0 | AB4: =S4+T4-W4-Z4 -> 0 | AC4: SIN FACTURA | AM4: =(AB4+AD4+AE4)-(AH4+AK4) -> 0 | AN4: SIN FACTURA | AX4: =(AM4+AO4+AP4)-(AS4+AV4) -> 0 | AY4: SIN FACTURA | BI4: =(AX4+AZ4+BA4)-(BD4+BG4) -> 0 | BT4: =(BI4+BK4+BL4)-(BO4+BR4) -> 0
A5: 007 | B5: FONSECA SILVA MARCOS ENRIQUE | C5: 172.18.2.55 | D5: ACTIVO | E5: M | G5: 0152598603 | H5: SAYAUSI | I5: SI | J5: VIA DEL TEJAR | K5: fonsecam199.5@gmail.com | L5: 0963154411 0978797350 | N5: 44508 | O5: 650M/650M | P5: GRATIS | Q5: 0 | S5: 23 | U5: 46041 | V5: 46043 | W5: 23 | X5: Pichincha | AB5: =S5+T5-W5-Z5 -> 0 | AC5: C0360 | AD5: 23 | AF5: 46072 | AG5: 46072 | AH5: 23 | AI5: Pichincha | AJ5: 129768 | AM5: =(AB5+AD5+AE5)-(AH5+AK5) -> 0 | AN5: C0408 | AO5: 23 | AQ5: 46100 | AR5: 24/3/2026 | AS5: 23 | AT5: Pichincha | AU5: 138500 | AX5: =(AM5+AO5+AP5)-(AS5+AV5) -> 0 | AY5: C0453 | AZ5: 23 | BB5: 46131 | BC5: 20/4/2026 | BD5: 23 | BE5: Pichincha | BI5: =(AX5+AZ5+BA5)-(BD5+BG5) -> 0 | BJ5: C0497 | BK5: 23 | BM5: 46161 | BT5: =(BI5+BK5+BL5)-(BO5+BR5) -> 23
A6: 009 | B6: PACHO VILLA NORMA MAGDALENA | C6: 172.18.2.6 | D6: CORTESIA | E6: F | G6: 0105168165 | H6: SAYAUSI | I6: SI | J6: ORDOÑEZ LASSO FRENTE A LA BOMBA PRIMAX | K6: villanorma755@gmail.com | L6: 0986963187 0980269740 | M6: 52sayanormap | N6: 44508 | O6: 650M/650M | P6: GRATIS | Q6: 0 | S6: 0 | U6: 46038 | AB6: =S6+T6-W6-Z6 -> 0 | AC6: SIN FACTURA | AD6: 0 | AF6: 46069 | AM6: =(AB6+AD6+AE6)-(AH6+AK6) -> 0 | AN6: SIN FACTURA | AO6: 0 | AQ6: 46097 | AX6: =(AM6+AO6+AP6)-(AS6+AV6) -> 0 | AY6: SIN FACTURA | AZ6: 0 | BB6: 46128 | BI6: =(AX6+AZ6+BA6)-(BD6+BG6) -> 0 | BK6: 0 | BM6: 46158 | BT6: =(BI6+BK6+BL6)-(BO6+BR6) -> 0
A7: 010 | B7: VELECELA GUNCAY MARTHA LUCIA | C7: 172.18.1.3 | D7: ACTIVO | E7: F | G7: 0104301726 | H7: SAYAUSI | I7: NO | J7: LA HERMITA SAYAUSI | K7: mvelecela.1981@gmail.com | L7: 0997365619 0997439598 | N7: 44513 | O7: 650M/650M | P7: GRATIS | Q7: 0 | S7: 23 | U7: 46041 | V7: 46049 | W7: 23 | X7: JEP | AB7: =S7+T7-W7-Z7 -> 0 | AC7: C0361 | AD7: 23 | AF7: 46072 | AG7: 46076 | AH7: 23 | AI7: JEP | AM7: =(AB7+AD7+AE7)-(AH7+AK7) -> 0 | AN7: C0409 | AO7: 23 | AQ7: 46100 | AR7: 25/3/2026 | AS7: 23 | AT7: JEP | AX7: =(AM7+AO7+AP7)-(AS7+AV7) -> 0 | AY7: C0454 | AZ7: 23 | BB7: 46131 | BC7: 28/04/2026 | BD7: 23 | BE7: JEP | BI7: =(AX7+AZ7+BA7)-(BD7+BG7) -> 0 | BJ7: C0498 | BK7: 23 | BM7: 46161 | BT7: =(BI7+BK7+BL7)-(BO7+BR7) -> 23
A8: 011 | B8: GOMEZ SANGURIMA MARCO OSWALDO | C8: 172.18.1.4 | D8: ACTIVO | E8: M | G8: 0106626161 | H8: SAYAUSI | I8: NO | J8: SAN MIGUEL - LA HERMITA | K8: marco-gomez04@hotmail.com | L8: 0983509196 0992504946 074189279 | N8: 46091 | O8: 100M/100M | P8: GRATIS | Q8: 0 | S8: 17.25 | U8: 46036 | V8: 21/1/2026 | W8: 17.25 | X8: Pichincha | AB8: =S8+T8-W8-Z8 -> 0 | AC8: SIN FACTURA | AD8: 17.25 | AF8: 46067 | AG8: 46058 | AH8: 17.25 | AI8: Pichincha | AM8: =(AB8+AD8+AE8)-(AH8+AK8) -> 0 | AN8: SIN FACTURA | AO8: 17.25 | AQ8: 46095 | AR8: 4/3/2026 | AS8: 17.25 | AT8: JEP | AX8: =(AM8+AO8+AP8)-(AS8+AV8) -> 0 | AY8: SIN FACTURA | AZ8: 17.25 | BB8: 46126 | BC8: 6/4/2026 | BD8: 17.25 | BE8: Pichincha | BI8: =(AX8+AZ8+BA8)-(BD8+BG8) -> 0 | BK8: 17.25 | BM8: 46156 | BT8: =(BI8+BK8+BL8)-(BO8+BR8) -> 17.25
A9: 012 | B9: CAJAMARCA FAJARDO CLAUDIO RIGOBERTO | C9: 172.18.2.10 | D9: ACTIVO | E9: M | G9: 0104009352 | H9: SAYAUSI | I9: NO | J9: AV. TEJAR Y CAMINO SAN MIGUEL DE PUTUSHI | K9: claudio78cajamarca@gmail.com | L9: 0979416436 0991275404 | M9: 12sayasoniaa | N9: 45783 | O9: 100M/100M | P9: GRATIS | Q9: 0 | S9: 17.25 | T9: 4 | U9: 46041 | V9: 46045 | W9: 17.25 | X9: Pichincha | Z9: 4 | AA9: Pichincha | AB9: =S9+T9-W9-Z9 -> 0 | AC9: SIN FACTURA | AD9: 17.25 | AE9: 4 | AF9: 46072 | AG9: 46076 | AH9: 17.25 | AI9: JEP | AK9: 4 | AL9: JEP | AM9: =(AB9+AD9+AE9)-(AH9+AK9) -> 0 | AN9: SIN FACTURA | AO9: 17.25 | AP9: 4 | AQ9: 46100 | AR9: 26/26/2026 | AS9: 17.25 | AT9: Pichincha | AV9: 4 | AW9: Pichincha | AX9: =(AM9+AO9+AP9)-(AS9+AV9) -> 0 | AY9: SIN FACTURA | AZ9: 17.25 | BA9: 4 | BB9: 46131 | BC9: 1/4/2026 | BD9: 17.25 | BE9: JEP | BG9: 4 | BH9: JEP | BI9: =(AX9+AZ9+BA9)-(BD9+BG9) -> 0 | BK9: 17.25 | BL9: 4 | BM9: 46161 | BT9: =(BI9+BK9+BL9)-(BO9+BR9) -> 21.25
A10: 013 | B10: MORALES TENEGAÑAY JESSICA LUCIA | C10: 172.18.1.34 | D10: INACTIVO | E10: F | G10: 0105659502 | H10: SAYAUSI | I10: SI | J10: SUBIDA A SAN MIGUEL SECTOR IGLESIA NUEVA | K10: rosiparedes714@gmail.com | L10: 0992964104 | N10: 44592 | O10: 100M/100M | P10: GRATIS | Q10: 37.25 | AB10: =S10+T10-W10-Z10 -> 0 | AC10: SIN FACTURA | AM10: =(AB10+AD10+AE10)-(AH10+AK10) -> 0 | AN10: SIN FACTURA | AX10: =(AM10+AO10+AP10)-(AS10+AV10) -> 0 | AY10: SIN FACTURA | BI10: =(AX10+AZ10+BA10)-(BD10+BG10) -> 0 | BT10: =(BI10+BK10+BL10)-(BO10+BR10) -> 0
A11: 017 | B11: LEON VILLA SEGUNDO RODOLFO | C11: 10.67.2.254 | D11: INACTIVO | E11: M | G11: 0103229399 | H11: SAYAUSI | I11: NO | J11: SAN MIGUEL SECTOR TEMPLO CHINO | K11: facturas.labsll@gmail.com | L11: 0993568122 0995674041 | N11: 44516 | O11: 650M/650M | P11: GRATIS | Q11: 0 | AB11: =S11+T11-W11-Z11 -> 0 | AC11: SIN FACTURA | AM11: =(AB11+AD11+AE11)-(AH11+AK11) -> 0 | AN11: SIN FACTURA | AX11: =(AM11+AO11+AP11)-(AS11+AV11) -> 0 | AY11: SIN FACTURA | BI11: =(AX11+AZ11+BA11)-(BD11+BG11) -> 0 | BT11: =(BI11+BK11+BL11)-(BO11+BR11) -> 0
A12: 018 | B12: CEDILLO PALTA ANGEL AMBROCIO | C12: 172.18.2.15 | D12: INACTIVO | G12: 0102600814 | H12: SAYAUSI | I12: NO | J12: ORDOÑEZ LASO Y ROSAL | K12: angelambrosiocedillo@hotmail.com | L12: 0992304985 4193019 | N12: 44510 | O12: 650M/650M | P12: GRATIS | Q12: 0 | AB12: =S12+T12-W12-Z12 -> 0 | AC12: SIN FACTURA | AM12: =(AB12+AD12+AE12)-(AH12+AK12) -> 0 | AN12: SIN FACTURA | AX12: =(AM12+AO12+AP12)-(AS12+AV12) -> 0 | AY12: SIN FACTURA | BI12: =(AX12+AZ12+BA12)-(BD12+BG12) -> 0 | BT12: =(BI12+BK12+BL12)-(BO12+BR12) -> 0
A13: 020 | B13: ROSERO CAJAMARCA EDUARDO MARCIAL | C13: 172.18.2.17 | D13: ACTIVO | E13: M | F13: 12 | G13: 2100399233 | H13: SAYAUSI | I13: SI | J13: ORDOÑEZ LASO Y HIERBA LUISA | K13: eduardorosero2012@hotmail.com | L13: 0962191932 | N13: 44888 | O13: 100M/100M | P13: 5 | Q13: 0 | S13: 17.25 | U13: 46031 | V13: 21/1/2026 | W13: 17.25 | X13: Pichincha | AB13: =S13+T13-W13-Z13 -> 0 | AC13: SIN FACTURA | AD13: 17.25 | AF13: 46062 | AG13: 46072 | AH13: 17.25 | AI13: Pichincha | AJ13: 129770 | AM13: =(AB13+AD13+AE13)-(AH13+AK13) -> 0 | AN13: SIN FACTURA | AO13: 17.25 | AQ13: 46090 | AR13: 30/3/2026 | AS13: 17.25 | AT13: Pichincha | AX13: =(AM13+AO13+AP13)-(AS13+AV13) -> 0 | AY13: SIN FACTURA | AZ13: 17.25 | BB13: 46121 | BC13: 11/4/2026 | BD13: 17.25 | BE13: Pichincha | BF13: 141504 | BI13: =(AX13+AZ13+BA13)-(BD13+BG13) -> 0 | BK13: 17.25 | BM13: 46151 | BT13: =(BI13+BK13+BL13)-(BO13+BR13) -> 17.25
A14: 021 | B14: PACHECO PANGOL JENNY MARISOL | C14: 172.18.1.5 | D14: ACTIVO | E14: F | F14: 24 | G14: 0104551742 | H14: SAYAUSI | I14: NO | J14: SAN MIGUEL SECTOR HERMITA | K14: marcocalu1710@gmail.com | L14: 0980870614 0997132402 | N14: 45567 | O14: 650M/650M | P14: GRATIS | Q14: 0.4 | S14: 23 | U14: 46041 | V14: 46043 | W14: 23 | X14: JEP | AB14: =S14+T14-W14-Z14 -> 0 | AC14: C0362 | AD14: 23 | AF14: 46072 | AG14: 46072 | AH14: 23 | AI14: JEP | AM14: =(AB14+AD14+AE14)-(AH14+AK14) -> 0 | AN14: C0410 | AO14: 23 | AQ14: 46100 | AR14: 25/3/2026 | AS14: 23 | AT14: JEP | AX14: =(AM14+AO14+AP14)-(AS14+AV14) -> 0 | AY14: C0455 | AZ14: 23 | BB14: 46131 | BC14: 28/4/2026 | BD14: 23 | BE14: JEP | BI14: =(AX14+AZ14+BA14)-(BD14+BG14) -> 0 | BJ14: C0499 | BK14: 23 | BM14: 46161 | BT14: =(BI14+BK14+BL14)-(BO14+BR14) -> 23
A15: 023 | B15: LEON PAREDES ROSA ESPERANZA | C15: 172.18.1.6 | D15: ACTIVO | E15: F | G15: 0107040628 | H15: SAYAUSI | I15: NO | J15: SAN MIGUEL - LA HERMITA | K15: rosaleon5681@gmail.com | L15: 099 986 9789 | N15: 44534 | O15: 100M/100M | P15: GRATIS | Q15: 0 | S15: 17.25 | U15: 46046 | V15: 46051 | W15: 17.25 | X15: JEP | AB15: =S15+T15-W15-Z15 -> 0 | AC15: SIN FACTURA | AD15: 17.25 | AF15: 46077 | AG15: 46079 | AH15: 17.25 | AI15: JEP | AM15: =(AB15+AD15+AE15)-(AH15+AK15) -> 0 | AN15: SIN FACTURA | AO15: 17.25 | AQ15: 46105 | AR15: 18/3/2026 | AS15: 17.25 | AT15: Pichincha | AX15: =(AM15+AO15+AP15)-(AS15+AV15) -> 0 | AY15: SIN FACTURA | AZ15: 17.25 | BB15: 46136 | BC15: 20/4/2026 | BD15: 17.25 | BE15: JEP | BI15: =(AX15+AZ15+BA15)-(BD15+BG15) -> 0 | BK15: 17.25 | BM15: 46166 | BT15: =(BI15+BK15+BL15)-(BO15+BR15) -> 17.25
A16: 024 | B16: SANCHEZ CONDO MILTON BOLIVAR | C16: 172.18.2.19 | D16: INACTIVO | G16: 0703816272 | H16: SAYAUSI | I16: SI | J16: ORDOÑEZ LAZO FRENTE A LA BOMBA PRIMAX | K16: miltonbolivarsanchezcondo@gmail.com | L16: 0991340276 0968925246 | N16: 04/12/2021 | O16: 100M/100M | P16: GRATIS | Q16: 0 | AB16: =S16+T16-W16-Z16 -> 0 | AC16: SIN FACTURA | AM16: =(AB16+AD16+AE16)-(AH16+AK16) -> 0 | AN16: SIN FACTURA | AX16: =(AM16+AO16+AP16)-(AS16+AV16) -> 0 | AY16: SIN FACTURA | BI16: =(AX16+AZ16+BA16)-(BD16+BG16) -> 0 | BT16: =(BI16+BK16+BL16)-(BO16+BR16) -> 0
A17: 027 | B17: LEON PINTADO JOSE MIGUEL | C17: 172.18.1.56 | D17: ACTIVO | E17: M | G17: 0101814556 | H17: SAYAUSI | I17: NO | J17: SECTOR LA HERMITA | L17: 0988570402 0968739394 | N17: 44560 | O17: 650M/650M | P17: GRATIS | Q17: 0 | S17: 25 | U17: 46041 | V17: 46048 | W17: 25 | X17: Pichincha | AB17: =S17+T17-W17-Z17 -> 0 | AC17: SIN FACTURA | AD17: 25 | AF17: 46072 | AG17: 46075 | AH17: 25 | AI17: Pichincha | AJ17: 130637 | AM17: =(AB17+AD17+AE17)-(AH17+AK17) -> 0 | AN17: C0403 | AO17: 25 | AQ17: 46100 | AR17: 25/3/2026 | AS17: 25 | AT17: Pichincha | AX17: =(AM17+AO17+AP17)-(AS17+AV17) -> 0 | AY17: SIN FACTURA | AZ17: 25 | BB17: 46131 | BC17: 20/4/2026 | BD17: 25 | BE17: Pichincha | BF17: 142088 | BI17: =(AX17+AZ17+BA17)-(BD17+BG17) -> 0 | BK17: 25 | BM17: 46161 | BT17: =(BI17+BK17+BL17)-(BO17+BR17) -> 25
A18: 028 | B18: BARRIONUEVO FERNANDEZ FANNY SUSANA | C18: 172.18.2.21 | D18: ACTIVO | E18: ESTA EN EL CHAT | F18: 24 | G18: 1203804750 | H18: SAYAUSI | I18: NO | J18: SECTOR QUINTA CARMITA | K18: fernandezsusy052@gmail.com | L18: 0992051025 0969063324 0989454709 0985313311 | M18: 28safannyb | N18: 46081 | O18: 650M/650M | P18: GRATIS | Q18: -6 | S18: 23 | T18: 0 | U18: 46031 | V18: 46174 | W18: 23 | X18: JEP | AB18: =Q18+S18+T18-W18-Z18 -> -6 | AC18: C0363 | AD18: 23 | AE18: 0 | AF18: 46062 | AG18: 46058 | AH18: 23 | AI18: JEP | AM18: =(AB18+AD18+AE18)-(AH18+AK18) -> -6 | AN18: C0411 | AO18: 23 | AP18: 0 | AQ18: 46090 | AR18: 4/3/2026 | AS18: 23 | AT18: Pichincha | AX18: =(AM18+AO18+AP18)-(AS18+AV18) -> -6 | AY18: C0456 | AZ18: 23 | BA18: 0 | BB18: 46121 | BC18: 7/4/2026 | BD18: 23 | BE18: Pichincha | BI18: =(AX18+AZ18+BA18)-(BD18+BG18) -> -6 | BJ18: C0500 | BK18: 23 | BL18: 0 | BM18: 46151 | BT18: =(BI18+BK18+BL18)-(BO18+BR18) -> 17
A19: 029 | B19: MOROCHO LEON ANGELA ANDREA | C19: 172.18.1.9 | D19: ACTIVO | E19: F | F19: 24 | G19: 0107166399 | H19: SAYAUSI | I19: NO | J19: SAN MIGUEL - SECTOR LA HERMITA | K19: morochoangela704@gmail.com | L19: 0991151608 0990222192 0994631432 | N19: 45503 | O19: 650M/650M | P19: GRATIS | Q19: 0 | S19: 23 | U19: 46031 | V19: 46038 | W19: 23 | X19: Pichincha | Y19: 120478 | AB19: =S19+T19-W19-Z19 -> 0 | AC19: C0364 | AD19: 23 | AF19: 46062 | AG19: 46067 | AH19: 23 | AI19: Pichincha | AJ19: 128538 | AM19: =(AB19+AD19+AE19)-(AH19+AK19) -> 0 | AN19: C0412 | AO19: 23 | AQ19: 46090 | AR19: 18/3/2026 | AS19: 23 | AT19: Pichincha | AU19: 137514 | AX19: =(AM19+AO19+AP19)-(AS19+AV19) -> 0 | AY19: C0457 | AZ19: 23 | BB19: 46121 | BC19: 19/4/2026 | BD19: 23 | BE19: Pichincha | BI19: =(AX19+AZ19+BA19)-(BD19+BG19) -> 0 | BJ19: C0501 | BK19: 23 | BM19: 46151 | BT19: =(BI19+BK19+BL19)-(BO19+BR19) -> 23
A20: 031 | B20: ROBLES PERALTA LUIS ALBERTO | C20: 172.18.2.22 | D20: INACTIVO | E20: M | G20: 0940305378 | H20: SAYAUSI | I20: SI | J20: ORDOÑEZ LAZO Y HIERBA LUISA | K20: ortizjenny716@gmail.com | L20: 0985621316 0992136760 | N20: 44957 | O20: 650M/650M | P20: GRATIS | Q20: 0 | AB20: =S20+T20-W20-Z20 -> 0 | AC20: SIN FACTURA | AM20: =(AB20+AD20+AE20)-(AH20+AK20) -> 0 | AN20: SIN FACTURA | AX20: =(AM20+AO20+AP20)-(AS20+AV20) -> 0 | AY20: SIN FACTURA | BI20: =(AX20+AZ20+BA20)-(BD20+BG20) -> 0 | BT20: =(BI20+BK20+BL20)-(BO20+BR20) -> 0
A21: 032 | B21: MUÑOZ ORTEGA JUAN ESTEBAN | C21: 172.18.4.3 | D21: ACTIVO | E21: F | G21: 0101866556 | H21: SAYAUSI | I21: NO | J21: LA LIBERTAD SECTOR LA PIEDRA GRANDE | K21: jmunoz@cdazuay.com | L21: 0994922373 0997012335 | M21: 32samunozj | N21: 44569 | O21: 650M/650M | P21: 20 | Q21: 0 | S21: 23 | T21: 0 | U21: 46041 | V21: 46043 | W21: 23 | X21: Pichincha | AB21: =S21+T21-W21-Z21 -> 0 | AC21: C0365 | AD21: 23 | AE21: 0 | AF21: 46072 | AG21: 46072 | AH21: 23 | AI21: Pichincha | AJ21: 129772 | AM21: =(AB21+AD21+AE21)-(AH21+AK21) -> 0 | AN21: C0413 | AO21: 23 | AP21: 0 | AQ21: 46100 | AR21: 24/3/2026 | AS21: 23 | AT21: Pichincha | AU21: 138504 | AX21: =(AM21+AO21+AP21)-(AS21+AV21) -> 0 | AY21: C0458 | AZ21: 23 | BA21: 0 | BB21: 46131 | BC21: 23/4/2026 | BD21: 23 | BE21: Pichincha | BI21: =(AX21+AZ21+BA21)-(BD21+BG21) -> 0 | BJ21: C0502 | BK21: 23 | BL21: 0 | BM21: 46161 | BT21: =(BI21+BK21+BL21)-(BO21+BR21) -> 23
A22: 033 | B22: TENEPAGUAY PULLA MARIA ISABEL | C22: 172.18.1.12 | D22: ACTIVO | E22: F | G22: 0103343687 | H22: SAYAUSI | I22: NO | J22: SUBIDA A SAN MIGUEL SECTOR IGLESIA NUEVA | K22: isabeltenempaguay@gmail.com | L22: 0982780021 0991891662 0998871453 | N22: 44579 | O22: 100M/100M | P22: 35 | Q22: -5.03 | S22: 17.25 | U22: 46031 | V22: 46031 | W22: 18.25 | X22: JEP | AB22: =Q22+S22+T22-W22-Z22 -> -6.03 | AC22: SIN FACTURA | AD22: 17.25 | AF22: 46062 | AG22: 46062 | AH22: 18.25 | AI22: JEP | AM22: =(AB22+AD22+AE22)-(AH22+AK22) -> -7.03 | AN22: SIN FACTURA | AO22: 17.25 | AQ22: 46090 | AR22: 7/3/2026 | AS22: 17 | AT22: JEP | AX22: =(AM22+AO22+AP22)-(AS22+AV22) -> -6.78 | AY22: SIN FACTURA | AZ22: 17.25 | BB22: 46121 | BC22: 7/4/2026 | BD22: 17.52 | BE22: JEP | BI22: =(AX22+AZ22+BA22)-(BD22+BG22) -> -7.05 | BK22: 17.25 | BM22: 46151 | BT22: =(BI22+BK22+BL22)-(BO22+BR22) -> 10.2
A23: 034 | B23: BERMEO SANGURIMA MANUELA BEATRIZ | C23: 172.18.1.13 | D23: ACTIVO | E23: F | G23: 0102236015 | H23: SAYAUSI | I23: NO | J23: SAN MIGUEL SECTOR LA HERMITA | L23: 0997060665 0984939313 | N23: 44579 | O23: 100M/100M | P23: GRATIS | Q23: 0 | S23: 17.25 | U23: 46041 | V23: 46034 | W23: 17.25 | X23: Pichincha | Y23: 119415 | AB23: =S23+T23-W23-Z23 -> 0 | AC23: C0353 | AD23: 17.25 | AF23: 46072 | AG23: 46075 | AH23: 17.25 | AI23: Pichincha | AJ23: 131108 | AM23: =(AB23+AD23+AE23)-(AH23+AK23) -> 0 | AN23: C0385 | AO23: 17.25 | AQ23: 46100 | AR23: 18/3/2026 | AS23: 17.25 | AT23: Pichincha | AU23: 137516 | AX23: =(AM23+AO23+AP23)-(AS23+AV23) -> 0 | AY23: C0435 | AZ23: 17.25 | BB23: 46131 | BC23: 20/4/2026 | BD23: 17.25 | BE23: Pichincha | BI23: =(AX23+AZ23+BA23)-(BD23+BG23) -> 0 | BJ23: C02734 | BK23: 17.25 | BM23: 46161 | BT23: =(BI23+BK23+BL23)-(BO23+BR23) -> 17.25
A24: 035 | B24: QUIROZ ORTIZ EDGAR FERNANDO | C24: 172.18.1.14 | D24: INACTIVO | G24: 0103305363 | H24: SAYAUSI | I24: SI | J24: SUBIDA A SAN MIGUEL SECTOR IGLESIA NUEVA | K24: edgarfq22@gmail.com | L24: 0991699938 0987501595 | N24: 44586 | O24: 100M/100M | Q24: 0 | AB24: =S24+T24-W24-Z24 -> 0 | AC24: SIN FACTURA | AM24: =(AB24+AD24+AE24)-(AH24+AK24) -> 0 | AN24: SIN FACTURA | AX24: =(AM24+AO24+AP24)-(AS24+AV24) -> 0 | AY24: SIN FACTURA | BI24: =(AX24+AZ24+BA24)-(BD24+BG24) -> 0 | BT24: =(BI24+BK24+BL24)-(BO24+BR24) -> 0
A25: 036 | B25: SALDAÑA TENEPAGUAY ESTEBAN XAVIER | C25: 172.18.1.23 | D25: ACTIVO | E25: M | G25: 0107173551 | H25: SAYAUSI | I25: SI | J25: ORDOÑEZ LAZO CINCO ESQUINAS | K25: stebanxavier@outlook.es | L25: 0984275252 0983897071 | N25: 44590 | O25: 650M/650M | Q25: 0 | S25: 23 | U25: 46036 | V25: 46045 | W25: 23 | X25: Pichincha | AB25: =S25+T25-W25-Z25 -> 0 | AC25: C0366 | AD25: 23 | AF25: 46067 | AG25: 46077 | AH25: 23 | AI25: Pichincha | AM25: =(AB25+AD25+AE25)-(AH25+AK25) -> 0 | AN25: C0414 | AO25: =23+50 -> 73 | AQ25: 46095 | AR25: 11/3/2026 | AS25: =50+23 -> 73 | AT25: Pichincha | AU25: 138502 | AX25: =(AM25+AO25+AP25)-(AS25+AV25) -> 0 | AY25: C0459 | AZ25: 23 | BB25: 46126 | BC25: 23/4/2026 | BD25: 23 | BE25: Pichincha | BI25: =(AX25+AZ25+BA25)-(BD25+BG25) -> 0 | BJ25: C0503 | BK25: 23 | BM25: 46156 | BT25: =(BI25+BK25+BL25)-(BO25+BR25) -> 23
A26: 037 | B26: MOSQUERA MORENO CARLOS VICENTE | C26: 172.18.2.23 | D26: ACTIVO | E26: M | G26: 0103071072 | H26: SAYAUSI | I26: NO | J26: AV EL TEJAR Y LA ORTIGA | K26: carlosmosqueramoreno@hotmail.com | L26: 0994132660 0998214894 | N26: 44595 | O26: 650M/650M | P26: GRATIS | Q26: 0 | S26: 23 | U26: 46036 | V26: 46024 | W26: 23 | X26: JEP | AB26: =S26+T26-W26-Z26 -> 0 | AC26: C0367 | AD26: 23 | AF26: 46067 | AG26: 411298 | AH26: 23 | AI26: JEP | AM26: =(AB26+AD26+AE26)-(AH26+AK26) -> 0 | AN26: C0415 | AO26: 23 | AQ26: 46095 | AR26: 1/3/2026 | AS26: 23 | AT26: JEP | AX26: =(AM26+AO26+AP26)-(AS26+AV26) -> 0 | AY26: C0460 | AZ26: 23 | BB26: 46126 | BC26: 1/4/2026 | BD26: 23 | BE26: JEP | BI26: =(AX26+AZ26+BA26)-(BD26+BG26) -> 0 | BJ26: C0504 | BK26: 23 | BM26: 46156 | BT26: =(BI26+BK26+BL26)-(BO26+BR26) -> 23
A27: 038 | B27: LEON PAREDES ANGEL RIGOBERTO | C27: 172.18.1.15 | D27: ACTIVO | E27: M | G27: 0105463962 | H27: SAYAUSI | I27: NO | J27: LA LOMA DE LA HERMITA | K27: leonparedes2001@gmail.com | L27: 0995282564 4138425 | N27: 44600 | O27: 100M/100M | P27: GRATIS | Q27: 0 | S27: 17.25 | U27: 46036 | V27: 46048 | W27: 17.25 | X27: Pichincha | AB27: =S27+T27-W27-Z27 -> 0 | AC27: SIN FACTURA | AD27: 17.25 | AF27: 46067 | AH27: 17.25 | AI27: Pichincha | AJ27: 134508 | AM27: =(AB27+AD27+AE27)-(AH27+AK27) -> 0 | AN27: SIN FACTURA | AO27: 17.25 | AQ27: 46095 | AR27: 7/3/2026 | AS27: 17.25 | AT27: Pichincha | AX27: =(AM27+AO27+AP27)-(AS27+AV27) -> 0 | AY27: SIN FACTURA | AZ27: 17.25 | BB27: 46126 | BI27: =(AX27+AZ27+BA27)-(BD27+BG27) -> 17.25 | BK27: 17.25 | BM27: 46156 | BT27: =(BI27+BK27+BL27)-(BO27+BR27) -> 34.5
A28: 039 | B28: FAJARDO ALVARRACIN NELI ESPERANZA | C28: 172.18.2.24 | D28: ACTIVO | E28: F | G28: 0103747374 | H28: SAYAUSI | I28: NO | J28: AV DEL TEJAR CERCA A LA ESCUAELA JESUS V | L28: 0987610096 | N28: 44603 | O28: 650M/650M | P28: GRATIS | Q28: -51.75 | S28: 17.25 | AB28: =Q28+S28+T28-W28-Z28 -> -34.5 | AC28: SIN FACTURA | AD28: 17.25 | AM28: =(AB28+AD28+AE28)-(AH28+AK28) -> -17.25 | AN28: SIN FACTURA | AO28: 17.25 | AX28: =(AM28+AO28+AP28)-(AS28+AV28) -> 0 | AY28: SIN FACTURA | AZ28: 17.25 | BI28: =(AX28+AZ28+BA28)-(BD28+BG28) -> 17.25 | BK28: 17.25 | BT28: =(BI28+BK28+BL28)-(BO28+BR28) -> 34.5
A29: 040 | B29: TENEPAGUAY PANGOL ENMA JOHANA | C29: 172.18.1.26 | D29: ACTIVO | E29: F | G29: 0104728498 | H29: SAYAUSI | I29: NO | J29: SAN MIGUEL LA HERMITA | K29: johannatenepaguay@gmail.com | L29: 0983586299 0986251027 1 (929) 507-2392 | N29: 44607 | O29: 650M/650M | Q29: 0 | S29: 23 | U29: 46031 | V29: 46043 | W29: 23 | X29: Pichincha | AB29: =S29+T29-W29-Z29 -> 0 | AC29: C0368 | AD29: 23 | AF29: 46062 | AG29: 46062 | AH29: 23 | AI29: Pichincha | AM29: =(AB29+AD29+AE29)-(AH29+AK29) -> 0 | AN29: C0416 | AO29: 23 | AQ29: 46090 | AR29: 9/3/2026 | AS29: 23 | AT29: Pichincha | AX29: =(AM29+AO29+AP29)-(AS29+AV29) -> 0 | AY29: C0461 | AZ29: 23 | BB29: 46121 | BC29: 28/4/2026 | BD29: 23 | BE29: Pichincha | BI29: =(AX29+AZ29+BA29)-(BD29+BG29) -> 0 | BJ29: C0505 | BK29: 23 | BM29: 46151 | BT29: =(BI29+BK29+BL29)-(BO29+BR29) -> 23
A30: 041 | B30: SANGURIMA BERMEO JORGE TEODORO | C30: 172.18.1.16 | D30: ACTIVO | E30: M | G30: 0302101902 | H30: SAYAUSI | I30: NO | J30: SAYAUSI - SECTOR LA HERMITA | K30: georgesangurima@hotmail.com | L30: 0982322878 0999141729 | N30: 44614 | O30: 100M/100M | P30: 20 | Q30: 0 | S30: 17.25 | U30: 46031 | V30: 46044 | W30: 17.25 | X30: JEP | AB30: =S30+T30-W30-Z30 -> 0 | AC30: SIN FACTURA | AD30: 17.25 | AF30: 46062 | AG30: 46071 | AH30: 17.25 | AI30: JEP | AM30: =(AB30+AD30+AE30)-(AH30+AK30) -> 0 | AN30: SIN FACTURA | AO30: 17.25 | AQ30: 46090 | AR30: 19/3/2026 | AS30: 17.25 | AT30: Pichincha | AX30: =(AM30+AO30+AP30)-(AS30+AV30) -> 0 | AY30: SIN FACTURA | AZ30: 17.25 | BB30: 46121 | BC30: 22/4/2026 | BD30: 17.25 | BE30: JEP | BI30: =(AX30+AZ30+BA30)-(BD30+BG30) -> 0 | BK30: 17.25 | BM30: 46151 | BT30: =(BI30+BK30+BL30)-(BO30+BR30) -> 17.25
A31: 045 | B31: RAMON ORDOÑEZ JESSICA ALEXANDRA | C31: 10.68.2.254 | D31: INACTIVO | G31: 0105768022 | H31: SAYAUSI | I31: SI | J31: LOS LADRILLEROS | K31: jessicaalexis52510@gmail.com | L31: 0997192807 0968967821 | N31: 44644 | O31: 650M/650M | P31: 30 | Q31: 0 | AB31: =S31+T31-W31-Z31 -> 0 | AC31: SIN FACTURA | AM31: =(AB31+AD31+AE31)-(AH31+AK31) -> 0 | AN31: SIN FACTURA | AX31: =(AM31+AO31+AP31)-(AS31+AV31) -> 0 | AY31: SIN FACTURA | BI31: =(AX31+AZ31+BA31)-(BD31+BG31) -> 0 | BT31: =(BI31+BK31+BL31)-(BO31+BR31) -> 0
A32: 046 | B32: BACULIMA LEON LUZ VERONICA | C32: 172.18.1.18 | D32: ACTIVO | E32: F | G32: 0103995767 | H32: SAYAUSI | I32: NO | J32: SAN MIGUEL SECTOR EL PROGRESO | K32: veronicabaculima@gmail.com | L32: 0959616296 4189060 | N32: 44651 | O32: 100M/100M | P32: GRATIS | Q32: -17.25 | S32: 17.25 | U32: 46031 | V32: 46034 | W32: 17.25 | X32: Pichincha | AB32: =S32+T32-W32-Z32 -> 0 | AC32: C0354 | AD32: 17.25 | AF32: 46062 | AG32: 46057 | AH32: 17.25 | AI32: Pichincha | AM32: =(AB32+AD32+AE32)-(AH32+AK32) -> 0 | AN32: C0386 | AO32: 17.25 | AQ32: 46090 | AR32: 14/3/2026 | AS32: 17.25 | AT32: Pichincha | AX32: =(AM32+AO32+AP32)-(AS32+AV32) -> 0 | AY32: C0436 | AZ32: 17.25 | BB32: 46121 | BC32: 8/4/2026 | BD32: 17.25 | BE32: Pichincha | BI32: =(AX32+AZ32+BA32)-(BD32+BG32) -> 0 | BJ32: C02735 | BK32: 17.25 | BM32: 46151 | BT32: =(BI32+BK32+BL32)-(BO32+BR32) -> 17.25
A33: 047 | B33: MUÑOZ MUÑOZ AIDA JOSEFA | C33: 172.18.6.3 | D33: ACTIVO | E33: F | G33: 0106036081 | H33: SAYAUSI | I33: NO | J33: BUENOS AIRES SECTOR CEBADAPAMBA | K33: CONSUMIDOR FINAL | L33: 0969499237 | N33: 45726 | O33: 650M/650M | P33: 42.5 | Q33: 0 | S33: 23 | U33: 46031 | V33: 46034 | W33: 23 | X33: Pichincha | Y33: 119417 | AB33: =S33+T33-W33-Z33 -> 0 | AC33: SIN FACTURA | AD33: 23 | AF33: 46062 | AG33: 46077 | AH33: 23 | AI33: Pichincha | AM33: =(AB33+AD33+AE33)-(AH33+AK33) -> 0 | AN33: SIN FACTURA | AO33: 23 | AQ33: 46090 | AR33: 24/3/2026 | AS33: 23 | AT33: Pichincha | AU33: 138510 | AX33: =(AM33+AO33+AP33)-(AS33+AV33) -> 0 | AY33: SIN FACTURA | AZ33: 23 | BB33: 46121 | BC33: 19/4/2026 | BD33: 23 | BE33: Pichincha | BI33: =(AX33+AZ33+BA33)-(BD33+BG33) -> 0 | BK33: 23 | BM33: 46151 | BT33: =(BI33+BK33+BL33)-(BO33+BR33) -> 23
A34: 048 | B34: SOLIS GUITIERRES HECTOR ROMAN | C34: 172.18.6.2 | D34: ACTIVO | E34: M | F34: 36 | G34: 0103487575 | H34: SAYAUSI | I34: NO | J34: BUENOS AIRES SECTOR MUYERINA | K34: mauricioguarango385@gmail.com | L34: 0963004541 0998828811 | N34: 45727 | O34: 650M/650M | P34: 45 | Q34: 0 | S34: 23 | U34: 46031 | V34: 46034 | W34: 23 | X34: Pichincha | Y34: 119419 | AB34: =S34+T34-W34-Z34 -> 0 | AC34: SIN FACTURA | AD34: 23 | AF34: 46062 | AG34: 46067 | AH34: 23 | AI34: Pichincha | AJ34: 128529 | AM34: =(AB34+AD34+AE34)-(AH34+AK34) -> 0 | AN34: SIN FACTURA | AO34: 23 | AQ34: 46090 | AR34: 14/3/2026 | AS34: 23 | AT34: JEP | AX34: =(AM34+AO34+AP34)-(AS34+AV34) -> 0 | AY34: SIN FACTURA | AZ34: 23 | BB34: 46121 | BC34: 19/4/2026 | BD34: 23 | BE34: Pichincha | BF34: 142038 | BI34: =(AX34+AZ34+BA34)-(BD34+BG34) -> 0 | BK34: 23 | BM34: 46151 | BT34: =(BI34+BK34+BL34)-(BO34+BR34) -> 23
A35: 050 | B35: GOMEZ SANGURIMA MARCO OSWALDO (PAPAS) | C35: 172.18.1.20 | D35: ACTIVO | G35: 0106626161 | H35: SAYAUSI | I35: NO | J35: SAN MIGUEL - LA HERMITA | K35: marco-gomez04@hotmail.com | L35: 0992504946 074189279 | N35: 44665 | O35: 100M/100M | Q35: 0 | AB35: =S35+T35-W35-Z35 -> 0 | AC35: SIN FACTURA | AM35: =(AB35+AD35+AE35)-(AH35+AK35) -> 0 | AN35: SIN FACTURA | AX35: =(AM35+AO35+AP35)-(AS35+AV35) -> 0 | AY35: SIN FACTURA | BI35: =(AX35+AZ35+BA35)-(BD35+BG35) -> 0 | BT35: =(BI35+BK35+BL35)-(BO35+BR35) -> 0
A36: 051 | B36: PAREDES TENEPAGUAY MIRIAM JANETH | C36: 172.18.1.21 | D36: ACTIVO | E36: F | F36: 24 | G36: 0105753040 | H36: SAYAUSI | I36: NO | J36: SUBIDA A SAN MIGUEL SECTOR IGLESIA NUEVA | K36: facturas.labsll@gmail.com | L36: 0983923428 0984032934 | O36: 650M/650M | Q36: 0 | S36: 23 | U36: 46031 | V36: 22/1/2026 | W36: 23 | X36: JEP | AB36: =S36+T36-W36-Z36 -> 0 | AC36: C0369 | AD36: 23 | AF36: 46062 | AG36: 46077 | AH36: 23 | AI36: JEP | AM36: =(AB36+AD36+AE36)-(AH36+AK36) -> 0 | AN36: C0417 | AO36: 23 | AQ36: 46090 | AR36: 25/3/2026 | AS36: 25 | AT36: JEP | AX36: =(AM36+AO36+AP36)-(AS36+AV36) -> -2 | AY36: C0462 | AZ36: 23 | BB36: 46121 | BC36: 23/4/2026 | BD36: 22 | BE36: JEP | BI36: =(AX36+AZ36+BA36)-(BD36+BG36) -> -1 | BJ36: C0506 | BK36: 23 | BM36: 46151 | BT36: =(BI36+BK36+BL36)-(BO36+BR36) -> 22
A37: 053 | B37: SOLIS GUTIERRES LUIS ABELARDO | C37: 172.18.1.52 | D37: INACTIVO | E37: M | G37: 0103909123 | H37: SAYAUSI | I37: NO | J37: BUENOS AIRES, SECTOR MOLLERINA | K37: facturas.labsll@gmail.com | L37: 0983435461 | N37: 44691 | O37: 650M/650M | P37: GRATIS | Q37: 83 | S37: 10 | U37: 46031 | AB37: 0 | AC37: SIN FACTURA | AD37: 10 | AF37: 46062 | AM37: =(AB37+AD37+AE37)-(AH37+AK37) -> 10 | AN37: SIN FACTURA | AO37: 10 | AQ37: 46090 | AX37: =(AM37+AO37+AP37)-(AS37+AV37) -> 20 | AY37: SIN FACTURA | AZ37: 10 | BB37: 46121 | BI37: =(AX37+AZ37+BA37)-(BD37+BG37) -> 30 | BK37: 10 | BM37: 46151 | BT37: =(BI37+BK37+BL37)-(BO37+BR37) -> 40
A38: 054 | B38: ALVARADO JIMENEZ SANDRA PATRICIA | C38: 172.18.2.30 | D38: ACTIVO | E38: F | F38: 24 | G38: 0105391759 | H38: SAYAUSI | I38: NO | J38: SAN MIGUEL SECTOR QUINTA CARMITA | K38: alevizh01@gmail.com | L38: 0969675884 0986364408 | N38: 46097 | O38: 650M/650M | P38: GRATIS | Q38: 0 | S38: 23 | U38: 46041 | V38: 46043 | W38: 23 | X38: Pichincha | AB38: =S38+T38-W38-Z38 -> 0 | AC38: C02405 | AD38: 23 | AF38: 46072 | AG38: 46067 | AH38: 23 | AI38: Pichincha | AJ38: 128531 | AM38: =(AB38+AD38+AE38)-(AH38+AK38) -> 0 | AN38: C0418 | AO38: 23 | AQ38: 46100 | AR38: 18/3/2026 | AS38: 23 | AT38: Pichincha | AX38: =(AM38+AO38+AP38)-(AS38+AV38) -> 0 | AY38: C0463 | AZ38: 23 | BB38: 46131 | BC38: 15/4/2026 | BD38: 23 | BE38: Pichincha | BI38: =(AX38+AZ38+BA38)-(BD38+BG38) -> 0 | BJ38: C0507 | BK38: 23 | BM38: 46161 | BT38: =(BI38+BK38+BL38)-(BO38+BR38) -> 23
A39: 055 | B39: GARCIA SOLIS JULIA LETICIA | C39: 172.18.2.31 | D39: INACTIVO | E39: F | G39: 0102072923 | H39: SAYAUSI | I39: SI | J39: AV. ORDOÑEZ LAZO SECTOR 5 ESQUINAS | K39: juliag1887@gmail.com | L39: 0988281009 0994145780 | N39: 44695 | O39: 100M/100M | P39: GRATIS | Q39: 0 | AB39: =S39+T39-W39-Z39 -> 0 | AC39: SIN FACTURA | AM39: =(AB39+AD39+AE39)-(AH39+AK39) -> 0 | AN39: SIN FACTURA | AX39: =(AM39+AO39+AP39)-(AS39+AV39) -> 0 | AY39: SIN FACTURA | BI39: =(AX39+AZ39+BA39)-(BD39+BG39) -> 0 | BT39: =(BI39+BK39+BL39)-(BO39+BR39) -> 0
A40: 056 | B40: ORTIZ QUIROZ JONNATHAN FABRICIO | C40: 172.18.6.7 | D40: ACTIVO | E40: M | F40: 12 | G40: 0105716641 | H40: SAYAUSI | I40: SI | J40: CAMINO DEL TEJAR Y DE LA MENTA | K40: jhonlion2107@gmail.com | L40: 0990795612 0990893872 | M40: 056sayajonnathano | N40: 45525 | O40: 800M/800M | P40: GRATIS | Q40: 0 | S40: 32.2 | U40: 46031 | W40: 32.2 | X40: Pichincha | Y40: 117678 | AB40: =S40+T40-W40-Z40 -> 0 | AC40: SIN FACTURA | AD40: 32.2 | AF40: 46062 | AG40: 46059 | AH40: 32.2 | AI40: Pichincha | AJ40: 125419 | AM40: =(AB40+AD40+AE40)-(AH40+AK40) -> 0 | AN40: SIN FACTURA | AO40: 32.2 | AQ40: 46090 | AR40: 7/3/2026 | AS40: 32.2 | AT40: Pichincha | AX40: =(AM40+AO40+AP40)-(AS40+AV40) -> 0 | AY40: SIN FACTURA | AZ40: 32.2 | BB40: 46121 | BC40: 11/4/2026 | BD40: 32.2 | BE40: Pichincha | BF40: 141506 | BI40: =(AX40+AZ40+BA40)-(BD40+BG40) -> 0 | BK40: 32.2 | BM40: 46151 | BT40: =(BI40+BK40+BL40)-(BO40+BR40) -> 32.2
A41: 057 | B41: GRANDA MOROCHO MACLOVIA MERCEDES | C41: 172.18.1.22 | D41: ACTIVO | E41: F | G41: 0104854542 | H41: SAYAUSI | I41: NO | J41: SECTOR LA HERMITA | L41: 0983385789 | N41: 44704 | O41: 650M/650M | P41: GRATIS | Q41: 0 | S41: 17.25 | U41: 46041 | V41: 46038 | W41: 17.25 | X41: Pichincha | Y41: 120480 | AB41: =S41+T41-W41-Z41 -> 0 | AC41: C0355 | AD41: 17.25 | AF41: 46072 | AG41: 46072 | AH41: 17.25 | AI41: Pichincha | AJ41: 129774 | AM41: =(AB41+AD41+AE41)-(AH41+AK41) -> 0 | AN41: C0387 | AO41: 17.25 | AQ41: 46100 | AR41: 16/3/2026 | AS41: 17.25 | AT41: Pichincha | AX41: =(AM41+AO41+AP41)-(AS41+AV41) -> 0 | AY41: C0437 | AZ41: 17.25 | BB41: 46131 | BC41: 19/4/2026 | BD41: 17.25 | BE41: Pichincha | BF41: 142040 | BI41: =(AX41+AZ41+BA41)-(BD41+BG41) -> 0 | BJ41: C02736 | BK41: 17.25 | BM41: 46161 | BT41: =(BI41+BK41+BL41)-(BO41+BR41) -> 17.25
A42: 059 | B42: CORTE VALENCIA ESTHER GUILLERMINA | C42: 172.18.2.34 | D42: EN PROCESO | E42: F | G42: 0105119705 | H42: SAYAUSI | I42: NO | J42: AV. ORDONEZ LASSO | K42: corteandrea11@gmail.com | L42: 0994972993 0993469867 0989692689 0991025960 | N42: 44728 | O42: 650M/650M | P42: GRATIS | Q42: 0 | S42: 23 | U42: 46041 | V42: 46050 | W42: 23 | X42: Pichincha | AB42: =S42+T42-W42-Z42 -> 0 | AC42: C0370 | AD42: 23 | AF42: 46072 | AG42: 46081 | AH42: 23 | AI42: Pichincha | AJ42: 133870 | AM42: =(AB42+AD42+AE42)-(AH42+AK42) -> 0 | AN42: C0419 | AO42: 23 | AQ42: 46100 | AR42: 24/3/2026 | AS42: 23 | AT42: Pichincha | AX42: =(AM42+AO42+AP42)-(AS42+AV42) -> 0 | AY42: C0464 | AZ42: 23 | BB42: 46131 | BI42: =(AX42+AZ42+BA42)-(BD42+BG42) -> 23 | BJ42: C0508 | BK42: 10 | BM42: 46161 | BT42: =(BI42+BK42+BL42)-(BO42+BR42) -> 33
A43: 060 | B43: SOLORZANO CALLE KAISER APOLINARIO | C43: 172.18.2.35 | D43: ACTIVO | E43: M | G43: 0105471767 | H43: SAYAUSI | I43: SI | J43: AV. ORNODEZ LASSO Y DE LA ORTIGA | K43: geovannyminchala123@gmail.com | L43: 0959157268 0968551601 | N43: 44732 | O43: 600M/600M | P43: GRATIS | Q43: 0 | S43: 20.54 | U43: 46046 | V43: 46053 | W43: 18.05 | X43: Pichincha | AB43: =S43+T43-W43-Z43 -> 2.49 | AC43: SIN FACTURA | AD43: =20.54-2.46 -> 18.08 | AF43: 46077 | AG43: 46081 | AH43: 20.57 | AI43: Pichincha | AJ43: 133872 | AM43: =(AB43+AD43+AE43)-(AH43+AK43) -> 0 | AN43: SIN FACTURA | AO43: 20.54 | AQ43: 46105 | AR43: 25/3/2026 | AS43: 20.54 | AT43: Pichincha | AX43: =(AM43+AO43+AP43)-(AS43+AV43) -> 0 | AY43: SIN FACTURA | AZ43: 20.54 | BB43: 46136 | BC43: 28/4/2026 | BD43: 20.54 | BE43: Pichincha | BF43: 143113 | BI43: =(AX43+AZ43+BA43)-(BD43+BG43) -> 0 | BK43: 20.54 | BM43: 46166 | BT43: =(BI43+BK43+BL43)-(BO43+BR43) -> 20.54
A44: 078 | B44: SOLORZANO CALLE KAISER APOLINARIO (LOCAL) | C44: 172.18.2.49 | D44: ACTIVO | E44: M | G44: 0105471767 | H44: SAYAUSI | I44: SI | J44: CALLE DEL TEJAR Y VIA A SAN MIGUEL | K44: geovannyminchala123@gmail.com | L44: 0959157268 09686551601 | N44: 44995 | O44: 100M/100M | P44: GRATIS | Q44: 0 | S44: 17.25 | U44: 46046 | V44: 46053 | W44: 17.25 | X44: Pichincha | AB44: =S44+T44-W44-Z44 -> 0 | AC44: SIN FACTURA | AD44: 17.25 | AF44: 46077 | AG44: 46081 | AH44: 17.25 | AI44: Pichincha | AJ44: 133874 | AM44: =(AB44+AD44+AE44)-(AH44+AK44) -> 0 | AN44: SIN FACTURA | AO44: 17.25 | AQ44: 46105 | AR44: 30/3/2026 | AS44: 17.25 | AT44: Pichincha | AX44: =(AM44+AO44+AP44)-(AS44+AV44) -> 0 | AY44: SIN FACTURA | AZ44: 17.25 | BB44: 46136 | BC44: 28/4/2026 | BD44: 17.25 | BE44: Pichincha | BF44: 143115 | BI44: =(AX44+AZ44+BA44)-(BD44+BG44) -> 0 | BK44: 17.25 | BM44: 46166 | BT44: =(BI44+BK44+BL44)-(BO44+BR44) -> 17.25
A45: 064 | B45: MOROCHO ROMERO DIANA MARLENE | C45: 172.18.2.39 | D45: INACTIVO | G45: 1105991945 | H45: SAYAUSI | I45: SI | J45: AV. ORDOÑEZ LASSO Y HIERVA LUISA | K45: marlemfresita02@gmail.com | L45: 0991356989 0990278334 | N45: 44800 | O45: 650M/650M | P45: GRATIS | Q45: 0 | AB45: =S45+T45-W45-Z45 -> 0 | AC45: SIN FACTURA | AM45: =(AB45+AD45+AE45)-(AH45+AK45) -> 0 | AN45: SIN FACTURA | AX45: =(AM45+AO45+AP45)-(AS45+AV45) -> 0 | AY45: SIN FACTURA | BI45: =(AX45+AZ45+BA45)-(BD45+BG45) -> 0 | BT45: =(BI45+BK45+BL45)-(BO45+BR45) -> 0
A46: 067 | B46: ZARUMA SANGURIMA CRUZ CELINDA | C46: 172.18.1.50 | D46: ACTIVO | E46: F | G46: 0105398747 | H46: SAYAUSI | I46: NO | J46: SECTOR INGAPIRCA SAYAUSI | K46: sangurimacelinda@gmail.com | L46: 0964072104 0939368877 0995341685 0958726529 | N46: 44816 | O46: 650M/650M | P46: 15 | Q46: 0 | S46: 23 | U46: 46031 | V46: 46031 | W46: 23 | X46: JEP | AB46: =S46+T46-W46-Z46 -> 0 | AC46: C0371 | AD46: 23 | AF46: 46062 | AG46: 46066 | AH46: 23 | AI46: JEP | AM46: =(AB46+AD46+AE46)-(AH46+AK46) -> 0 | AN46: C0420 | AO46: 23 | AQ46: 46090 | AR46: 23/3/2026 | AS46: 23 | AT46: JEP | AX46: =(AM46+AO46+AP46)-(AS46+AV46) -> 0 | AY46: C0465 | AZ46: 23 | BB46: 46121 | BC46: 9/04/2026 | BD46: 23 | BE46: JEP | BI46: =(AX46+AZ46+BA46)-(BD46+BG46) -> 0 | BJ46: C0485 | BK46: 23 | BM46: 46151 | BT46: =(BI46+BK46+BL46)-(BO46+BR46) -> 23
A47: 068 | B47: MORALES TIÑAGAÑAY JORGE ENRIQUE (ENTRADA SAN MIGUEL) | C47: 172.18.2.42 | D47: ACTIVO | E47: M | G47: 0107113441 | H47: SAYAUSI | I47: SI | J47: CALLE CARLOS ELIZABETH VELASQUEZ Y ENTRADA A SAN MIGUEL | K47: jorge.enrique14@hotmail.com | L47: 0968917250 0983851053 0964161277 | N47: 44820 | O47: 100M/100M | P47: 10 | Q47: 0 | S47: 17.25 | U47: 46031 | V47: 46038 | W47: 17.25 | X47: Pichincha | AB47: =S47+T47-W47-Z47 -> 0 | AC47: SIN FACTURA | AD47: 17.25 | AF47: 46062 | AG47: 46072 | AH47: 15.25 | AI47: Pichincha | AM47: =(AB47+AD47+AE47)-(AH47+AK47) -> 2 | AN47: SIN FACTURA | AO47: 17.25 | AQ47: 46090 | AR47: 16/3/2026 | AS47: 19.25 | AT47: Pichincha | AX47: =(AM47+AO47+AP47)-(AS47+AV47) -> 0 | AY47: SIN FACTURA | AZ47: 17.25 | BB47: 46121 | BC47: 16/4/2026 | BD47: 17.25 | BE47: Pichincha | BI47: =(AX47+AZ47+BA47)-(BD47+BG47) -> 0 | BK47: 17.25 | BM47: 46151 | BT47: =(BI47+BK47+BL47)-(BO47+BR47) -> 17.25
A48: 069 | B48: CORTE VALENCIA MARIA CLOTILDE | C48: 172.18.1.24 | D48: ACTIVO | E48: F | G48: 0106357635 | H48: SAYAUSI | I48: NO | J48: SAN MIGUEL SECTOR MEDIA HERMITA | L48: 0986216436 0989186536 0989692689 | N48: 44824 | O48: 650M/650M | P48: 20 | Q48: 0 | S48: 23 | U48: 46036 | V48: 46038 | W48: 23 | X48: Pichincha | Y48: 120482 | AB48: =S48+T48-W48-Z48 -> 0 | AC48: C0372 | AD48: 23 | AF48: 46067 | AG48: 46077 | AH48: 23 | AI48: Pichincha | AM48: =(AB48+AD48+AE48)-(AH48+AK48) -> 0 | AN48: C0421 | AO48: 23 | AQ48: 46095 | AR48: 24/3/2026 | AS48: 23 | AT48: Pichincha | AX48: =(AM48+AO48+AP48)-(AS48+AV48) -> 0 | AY48: C0466 | AZ48: 23 | BB48: 46126 | BC48: 23/4/2026 | BD48: 23 | BE48: Pichincha | BI48: =(AX48+AZ48+BA48)-(BD48+BG48) -> 0 | BJ48: C0509 | BK48: 23 | BM48: 46156 | BT48: =(BI48+BK48+BL48)-(BO48+BR48) -> 23
A49: 070 | B49: CAJAMARCA QUITUISACA MARIA MANUELA | C49: 172.18.1.25 | D49: ACTIVO | E49: F | G49: 0102457447 | H49: SAYAUSI | I49: NO | J49: SAN MIGUEL MEDIA LA HERMITA | K49: kevinuyga@gmail.com | L49: 0939085236 0994043203 | N49: 44896 | O49: 650M/650M | P49: 20 | Q49: 0 | S49: 23 | U49: 46031 | V49: 20/1/2026 | W49: 23 | X49: Pichincha | Y49: 117680 | AB49: =S49+T49-W49-Z49 -> 0 | AC49: SIN FACTURA | AD49: 23 | AF49: 46062 | AG49: 46059 | AH49: 23 | AI49: Pichincha | AJ49: 125421 | AM49: =(AB49+AD49+AE49)-(AH49+AK49) -> 0 | AN49: SIN FACTURA | AO49: 23 | AQ49: 46090 | AR49: 7/3/2026 | AS49: 23 | AT49: Pichincha | AX49: =(AM49+AO49+AP49)-(AS49+AV49) -> 0 | AY49: SIN FACTURA | AZ49: 23 | BB49: 46121 | BC49: 11/4/2026 | BD49: 23 | BE49: Pichincha | BF49: 141508 | BI49: =(AX49+AZ49+BA49)-(BD49+BG49) -> 0 | BK49: 23 | BM49: 46151 | BT49: =(BI49+BK49+BL49)-(BO49+BR49) -> 23
A50: 071 | B50: PEÑALOZA DOMINGUEZ HECTOR GABRIEL | C50: 172.18.2.43 | D50: ACTIVO | E50: M | G50: 0104862024 | H50: SAYAUSI | I50: SI | J50: AV. ORDOÑEZ LASSO Y SIN RETORNO | K50: penalozahector400@gmail.com | L50: 0992672160 | N50: 44926 | O50: 650M/650M | P50: 10 | Q50: 0 | S50: 23 | U50: 46041 | V50: 26/1/2026 | W50: 23 | X50: JEP | AB50: =S50+T50-W50-Z50 -> 0 | AC50: C0373 | AD50: 23 | AF50: 46072 | AG50: 46076 | AH50: 23 | AI50: JEP | AM50: =(AB50+AD50+AE50)-(AH50+AK50) -> 0 | AN50: C0422 | AO50: 23 | AQ50: 46100 | AR50: 25/3/2026 | AS50: 23 | AT50: JEP | AX50: =(AM50+AO50+AP50)-(AS50+AV50) -> 0 | AY50: C0467 | AZ50: 23 | BB50: 46131 | BC50: 46140 | BD50: 23 | BE50: JEP | BI50: =(AX50+AZ50+BA50)-(BD50+BG50) -> 0 | BJ50: C0510 | BK50: 23 | BM50: 46161 | BT50: =(BI50+BK50+BL50)-(BO50+BR50) -> 23
A51: 073 | B51: GUNCAY MOROCHO RUTH SELENA | C51: 172.18.1.27 | D51: INACTIVO | G51: 0107413965 | H51: SAYAUSI | I51: NO | J51: VIA SAN MIGUEL Y TEODORO LEON | K51: selenaguncay8@gmail.com | L51: 0995674041 0984903456 | N51: 2/15/2023 | O51: 650M/650M | Q51: 0 | AB51: =S51+T51-W51-Z51 -> 0 | AC51: SIN FACTURA | AM51: =(AB51+AD51+AE51)-(AH51+AK51) -> 0 | AN51: SIN FACTURA | AX51: =(AM51+AO51+AP51)-(AS51+AV51) -> 0 | AY51: SIN FACTURA | BI51: =(AX51+AZ51+BA51)-(BD51+BG51) -> 0 | BT51: =(BI51+BK51+BL51)-(BO51+BR51) -> 0
A52: 074 | B52: SARANGO PERALTA MONICA ALEXANDRA | C52: 172.18.2.45 | D52: ACTIVO | E52: F | G52: 0105359020 | H52: SAYAUSI | I52: NO | J52: ELIZABETH VELASQUEZ Y CAMINO A SAN MIGUEL DE PUTUSHI | K52: dcmoni_sp@hotmail.es | L52: 0984730996 074189496 | N52: 44973 | O52: 800M/800M | P52: 10 | Q52: 0 | S52: 23 | U52: 46041 | V52: 46043 | W52: 23 | X52: JEP | AB52: =S52+T52-W52-Z52 -> 0 | AC52: SIN FACTURA | AD52: 23 | AF52: 46072 | AG52: 46056 | AH52: 23 | AI52: JEP | AM52: =(AB52+AD52+AE52)-(AH52+AK52) -> 0 | AN52: SIN FACTURA | AO52: 23 | AQ52: 46100 | AR52: 20/3/2026 | AS52: 23 | AT52: JEP | AX52: =(AM52+AO52+AP52)-(AS52+AV52) -> 0 | AY52: SIN FACTURA | AZ52: 23 | BB52: 46131 | BC52: 24/04/2026 | BD52: 23 | BE52: JEP | BI52: =(AX52+AZ52+BA52)-(BD52+BG52) -> 0 | BK52: 23 | BM52: 46161 | BT52: =(BI52+BK52+BL52)-(BO52+BR52) -> 23
A53: 075 | B53: GUAMAN CRIOLLO ERIKA GABRIELA | C53: 172.18.2.46 | D53: ACTIVO | E53: F | G53: 0106760457 | H53: SAYAUSI | I53: SI | J53: CALLE HIERBA LUISA Y AV. DEL TEJAR | K53: eryka69@outlook.es | L53: 0992938044 0992933044 0984045561 | N53: 44988 | O53: 650M/650M | P53: GRATIS | Q53: 0 | S53: 23 | U53: 46031 | V53: 46034 | W53: 23 | X53: Pichincha | Y53: 119421 | AB53: =S53+T53-W53-Z53 -> 0 | AC53: SIN FACTURA | AD53: 23 | AF53: 46062 | AG53: 46072 | AH53: 23 | AI53: Pichincha | AJ53: 129776 | AM53: =(AB53+AD53+AE53)-(AH53+AK53) -> 0 | AN53: SIN FACTURA | AO53: 23 | AQ53: 46090 | AR53: 18/3/2026 | AS53: 23 | AT53: Pichincha | AU53: 137518 | AX53: =(AM53+AO53+AP53)-(AS53+AV53) -> 0 | AY53: SIN FACTURA | AZ53: 23 | BB53: 46121 | BC53: 11/4/2026 | BD53: 23 | BE53: Pichincha | BF53: 141510 | BI53: =(AX53+AZ53+BA53)-(BD53+BG53) -> 0 | BK53: 23 | BM53: 46151 | BT53: =(BI53+BK53+BL53)-(BO53+BR53) -> 23
A54: 076 | B54: LOJA ORELLANA TANIA MARISOL | C54: 172.18.2.47 | D54: ACTIVO | E54: F | G54: 0106839558 | H54: SAYAUSI | I54: SI | J54: CALLE HIERBA LUISA ENTRE AV. ORDOÑEZ LASSO Y TEJAR | K54: facturas.labsll@gmail.com | L54: 0939875522 0992270068 | M54: 76sayatanial | N54: 44993 | O54: 650M/650M | P54: GRATIS | Q54: 0 | S54: 17.25 | U54: 46041 | V54: 46050 | W54: 17.25 | X54: Pichincha | AB54: =S54+T54-W54-Z54 -> 0 | AC54: SIN FACTURA | AD54: 17.25 | AF54: 46072 | AG54: 46081 | AH54: 17.25 | AI54: Pichincha | AM54: =(AB54+AD54+AE54)-(AH54+AK54) -> 0 | AN54: SIN FACTURA | AO54: 17.25 | AQ54: 46100 | AR54: 25/3/2026 | AS54: 17.25 | AT54: Pichincha | AX54: =(AM54+AO54+AP54)-(AS54+AV54) -> 0 | AY54: SIN FACTURA | AZ54: 17.25 | BB54: 46131 | BC54: 30/4/2026 | BD54: 17.25 | BE54: Pichincha | BF54: 144634 | BI54: =(AX54+AZ54+BA54)-(BD54+BG54) -> 0 | BK54: 17.25 | BM54: 46161 | BT54: =(BI54+BK54+BL54)-(BO54+BR54) -> 17.25
A55: 077 | B55: MALO ANDRADE JESSICA KARINA | C55: 172.18.2.48 | D55: ACTIVO | E55: F | G55: 0151311164 | H55: SAYAUSI | I55: SI | J55: AV. ORDOÑEZ LASSO Y HIERBA LUISA | K55: rosendo2000zeas@gmail.com | L55: 0992886082 | N55: 44993 | O55: 650M/650M | P55: GRATIS | Q55: 0 | S55: 23 | U55: 46031 | V55: 46034 | W55: 23 | X55: Pichincha | Y55: 119423 | AB55: =S55+T55-W55-Z55 -> 0 | AC55: C0374 | AD55: 23 | AF55: 46062 | AG55: 46067 | AH55: 23 | AI55: Pichincha | AJ55: 128533 | AM55: =(AB55+AD55+AE55)-(AH55+AK55) -> 0 | AN55: C0423 | AO55: 23 | AQ55: 46090 | AR55: 11/3/2026 | AS55: 23 | AT55: Pichincha | AX55: =(AM55+AO55+AP55)-(AS55+AV55) -> 0 | AY55: C0468 | AZ55: 23 | BB55: 46121 | BC55: 21/4/2026 | BD55: 23 | BE55: Pichincha | BF55: 142042 | BI55: =(AX55+AZ55+BA55)-(BD55+BG55) -> 0 | BJ55: C0511 | BK55: 23 | BM55: 46151 | BT55: =(BI55+BK55+BL55)-(BO55+BR55) -> 23
A56: 079 | B56: ORTEGA GUAZHAMBO ALEXANDRA JAQUELINE | C56: 172.18.2.50 | D56: ACTIVO | E56: F | G56: 0102909355 | H56: SAYAUSI | I56: NO | J56: AV. TEJAR Y CDLA. ORTIGA | K56: alex_ortega37@hotmail.com | L56: 0979416070 0927103326 | N56: 45000 | O56: 800M/800M | P56: GRATIS | Q56: -8.08 | S56: 32.2 | U56: 46036 | V56: 46035 | W56: 33 | X56: JEP | AB56: =Q56+S56+T56-W56-Z56 -> -8.88 | AC56: C0384 | AD56: 32.2 | AF56: 46067 | AG56: 46066 | AH56: 33 | AI56: JEP | AM56: =(AB56+AD56+AE56)-(AH56+AK56) -> -9.68 | AN56: SIN FACTURA | AO56: 32.2 | AQ56: 46095 | AR56: 10/3/2026 | AS56: 22.55 | AT56: JEP | AX56: =(AM56+AO56+AP56)-(AS56+AV56) -> -0.03 | AY56: SIN FACTURA | AZ56: 32.2 | BB56: 46126 | BC56: 17.04 | BD56: 32.2 | BE56: JEP | BI56: =(AX56+AZ56+BA56)-(BD56+BG56) -> -0.03 | BK56: 32.2 | BM56: 46156 | BT56: =(BI56+BK56+BL56)-(BO56+BR56) -> 32.17
A57: 080 | B57: HERNANDEZ SANCHEZ EDWARD JOSE (FML) | C57: 172.18.2.53 | D57: INACTIVO | G57: 0152128260 | H57: SAYAUSI | I57: SI | J57: AV. ORDOÑEZ LASSO FRENTE GASOLINERA PRIMAX | K57: edwjosher@gmail.com | L57: 0981990894 0979409621 0995818946 0981718224 | N57: 45004 | O57: 650M/650M | P57: 10 | Q57: 0 | AB57: =S57+T57-W57-Z57 -> 0 | AC57: SIN FACTURA | AM57: =(AB57+AD57+AE57)-(AH57+AK57) -> 0 | AN57: SIN FACTURA | AX57: =(AM57+AO57+AP57)-(AS57+AV57) -> 0 | AY57: SIN FACTURA | BI57: =(AX57+AZ57+BA57)-(BD57+BG57) -> 0 | BT57: =(BI57+BK57+BL57)-(BO57+BR57) -> 0
A58: 081 | B58: CALLE PERALTA CLARA FILOMENA | C58: 172.18.2.54 | D58: INACTIVO | G58: 0102330420 | H58: SAYAUSI | I58: NO | J58: AV. DEL TEJAR ENTRE CALLE LA MENTA Y HIERBALUISA | K58: geovannyminchala123@gmail.com | L58: 0998534381 0959157268 | N58: 45005 | O58: 650M/650M | P58: 5 | Q58: 0 | AB58: =S58+T58-W58-Z58 -> 0 | AC58: SIN FACTURA | AM58: =(AB58+AD58+AE58)-(AH58+AK58) -> 0 | AN58: SIN FACTURA | AX58: =(AM58+AO58+AP58)-(AS58+AV58) -> 0 | AY58: SIN FACTURA | BI58: =(AX58+AZ58+BA58)-(BD58+BG58) -> 0 | BT58: =(BI58+BK58+BL58)-(BO58+BR58) -> 0
A59: 082 | B59: HUNT BETTY JANE | C59: 172.18.2.55 | D59: INACTIVO | E59: F | G59: LK931490 | H59: SAYAUSI | I59: SI | J59: VIA SAN MIGUEL DE PUTUZHI | K59: amberlee101@protonmail.com | L59: 0978797350 0963154411 | N59: 45015 | O59: 100M/100M | Q59: 0 | AB59: =S59+T59-W59-Z59 -> 0 | AC59: SIN FACTURA | AM59: =(AB59+AD59+AE59)-(AH59+AK59) -> 0 | AN59: SIN FACTURA | AX59: =(AM59+AO59+AP59)-(AS59+AV59) -> 0 | AY59: SIN FACTURA | BI59: =(AX59+AZ59+BA59)-(BD59+BG59) -> 0 | BT59: =(BI59+BK59+BL59)-(BO59+BR59) -> 0
A60: 083 | B60: YUMBO ANDI FABIAN JHONATAN | C60: 172.18.2.56 | D60: ACTIVO | E60: M | G60: 2200433205 | H60: SAYAUSI | I60: SI | J60: CALLE DEL OREGANO Y AV. ORDOÑEZ LASSO | K60: lojat1990@gmail.com | L60: 0939782332 | M60: 83safabiany | N60: 45028 | O60: 650M/650M | P60: 10 | Q60: 0 | S60: 23 | U60: 46031 | V60: 46034 | W60: 23 | X60: Pichincha | Y60: 119425 | AB60: =S60+T60-W60-Z60 -> 0 | AC60: C0375 | AD60: 23 | AF60: 46062 | AG60: 46067 | AH60: 23 | AI60: Pichincha | AJ60: 128536 | AM60: =(AB60+AD60+AE60)-(AH60+AK60) -> 0 | AN60: C0424 | AO60: 23 | AQ60: 46090 | AR60: 20/3/2026 | AS60: 23 | AT60: Pichincha | AX60: =(AM60+AO60+AP60)-(AS60+AV60) -> 0 | AY60: C0469 | AZ60: 23 | BB60: 46121 | BC60: 20/4/2026 | BD60: 23 | BE60: Pichincha | BF60: 142092 | BI60: =(AX60+AZ60+BA60)-(BD60+BG60) -> 0 | BJ60: C0512 | BK60: 23 | BM60: 46151 | BT60: =(BI60+BK60+BL60)-(BO60+BR60) -> 23
A61: 086 | B61: SEVILLANO ULLOA LEIDY MARIA | C61: 172.18.1.28 | D61: ACTIVO | E61: F | G61: 0804132140 | H61: SAYAUSI | I61: SI | J61: SAN MIGUEL LA HERMITA | K61: sevillanoleidymaria@gmail.com | L61: 0999379038 0997033774 0985587882 | M61: 086sayaleidys | N61: 45089 | O61: 650M/650M | P61: 14 | Q61: 0 | S61: 23 | T61: 0 | U61: 46031 | V61: 46174 | W61: 23 | X61: Pichincha | AB61: =S61+T61-W61-Z61 -> 0 | AC61: C0376 | AD61: 23 | AE61: 0 | AF61: 46062 | AG61: 46058 | AH61: 23 | AI61: Pichincha | AJ61: 215996 | AM61: =(AB61+AD61+AE61)-(AH61+AK61) -> 0 | AN61: C0425 | AO61: 23 | AP61: 0 | AQ61: 46090 | AR61: 9/3/2026 | AS61: 23 | AT61: Pichincha | AX61: =(AM61+AO61+AP61)-(AS61+AV61) -> 0 | AY61: C0470 | AZ61: 23 | BA61: 0 | BB61: 46121 | BC61: 2/4/2026 | BD61: 23 | BE61: Pichincha | BI61: =(AX61+AZ61+BA61)-(BD61+BG61) -> 0 | BJ61: C0513 | BK61: 23 | BL61: 0 | BM61: 46151 | BT61: =(BI61+BK61+BL61)-(BO61+BR61) -> 23
A62: 087 | B62: SEGARRA VALAREZO PRISCILA ELIZABETH | C62: 172.18.2.29 | D62: INACTIVO | E62: F | G62: 0704288737 | H62: SAYAUSI | I62: SI | J62: AV. ORDOÑEZ LASSO FRENTE A LA BOMBA PRIMAX | K62: priscilasegarra6@gmail.com | L62: 0988347319 | N62: 45090 | O62: 100M/100M | P62: GRATIS | Q62: 0 | AB62: =S62+T62-W62-Z62 -> 0 | AC62: SIN FACTURA | AM62: =(AB62+AD62+AE62)-(AH62+AK62) -> 0 | AN62: SIN FACTURA | AX62: =(AM62+AO62+AP62)-(AS62+AV62) -> 0 | AY62: SIN FACTURA | BI62: =(AX62+AZ62+BA62)-(BD62+BG62) -> 0 | BT62: =(BI62+BK62+BL62)-(BO62+BR62) -> 0
A63: 088 | B63: PINTADO SANGURIMA VIVIANA ESTEFANIA | C63: 172.18.1.30 | D63: ACTIVO | E63: F | G63: 0107197253 | H63: SAYAUSI | I63: NO | J63: LA HERMITA SAN MIGUEL | K63: stevensangurima05@hotmail.com | L63: 0985738258 0979433402 | M63: 88sayavivianap | N63: 45698 | O63: 650M/650M | P63: 7 | Q63: 23 | S63: =23+15+22+18 -> 78 | U63: 46051 | V63: 46025 | W63: =37+23+18 -> 78 | X63: JEP | AB63: =S63+T63-W63-Z63 -> 0 | AC63: SIN FACTURA | AD63: =23+18 -> 41 | AF63: 46082 | AG63: 46081 | AH63: 41 | AI63: JEP | AM63: =(AB63+AD63+AE63)-(AH63+AK63) -> 0 | AN63: SIN FACTURA | AO63: 23 | AQ63: 46113 | AR63: 31/3/2026 | AS63: 23 | AT63: JEP | AX63: =(AM63+AO63+AP63)-(AS63+AV63) -> 0 | AY63: SIN FACTURA | AZ63: 23 | BB63: 46143 | BC63: 30/4/2026 | BD63: 23 | BE63: JEP | BI63: =(AX63+AZ63+BA63)-(BD63+BG63) -> 0 | BK63: 23 | BM63: 46174 | BT63: =(BI63+BK63+BL63)-(BO63+BR63) -> 23
A64: 090 | B64: AJILA ORELLANA CARLOS HIGINIO | C64: 172.18.2.59 | D64: ACTIVO | E64: M | F64: 12 | G64: 0703488247 | H64: SAYAUSI | I64: SI | J64: AV. ORDOÑEZ LASSO FRENTE A LA BOMBA PRIMAX | K64: ajilacarlos158@gmail.com | L64: 0991880500 0989485278 | N64: 45179 | O64: 100M/100M | P64: GRATIS | Q64: 0 | S64: 11.5 | U64: 46041 | V64: 21/1/2026 | W64: 11.5 | X64: Pichincha | AB64: =S64+T64-W64-Z64 -> 0 | AC64: SIN FACTURA | AD64: 11.5 | AF64: 46072 | AG64: 46067 | AH64: 11.5 | AI64: Pichincha | AJ64: 128540 | AM64: =(AB64+AD64+AE64)-(AH64+AK64) -> 0 | AN64: SIN FACTURA | AO64: 11.5 | AQ64: 46100 | AR64: 24/3/2026 | AS64: 11.5 | AT64: Pichincha | AU64: 138506 | AX64: =(AM64+AO64+AP64)-(AS64+AV64) -> 0 | AY64: SIN FACTURA | AZ64: 11.5 | BB64: 46131 | BC64: 28/4/2026 | BD64: 11.5 | BE64: Pichincha | BF64: 143117 | BI64: =(AX64+AZ64+BA64)-(BD64+BG64) -> 0 | BK64: 11.5 | BM64: 46161 | BT64: =(BI64+BK64+BL64)-(BO64+BR64) -> 11.5
A65: 091 | B65: MORALES TENEGAÑAY JORGE ENRIQUE (SAN MIGUEL) | C65: 172.18.2.61 | D65: ACTIVO | E65: M | F65: SN | G65: 0107113441 | H65: SAYAUSI | I65: SI | J65: CAMINO SAN MIGUEL DE PUTUSHI | K65: jorge.enrique14@hotmail.com | L65: 0939114040 0983137827 | N65: 45209 | O65: 100M/100M | P65: 45 | Q65: 0 | S65: 17.25 | U65: 46031 | V65: 46038 | W65: 17.25 | X65: Pichincha | Y65: 120484 | AB65: =S65+T65-W65-Z65 -> 0 | AC65: SIN FACTURA | AD65: 17.25 | AF65: 46062 | AG65: 46072 | AH65: 17.25 | AI65: Pichincha | AJ65: 129778 | AM65: =(AB65+AD65+AE65)-(AH65+AK65) -> 0 | AN65: SIN FACTURA | AO65: 17.25 | AQ65: 46090 | AR65: 27/3/2026 | AS65: 17.25 | AT65: Pichincha | AX65: =(AM65+AO65+AP65)-(AS65+AV65) -> 0 | AY65: SIN FACTURA | AZ65: 17.25 | BB65: 46121 | BC65: 20/4/2026 | BD65: 17.25 | BE65: Pichincha | BI65: =(AX65+AZ65+BA65)-(BD65+BG65) -> 0 | BK65: 17.25 | BM65: 46151 | BT65: =(BI65+BK65+BL65)-(BO65+BR65) -> 17.25
A66: 092 | B66: OCHOA HURTADO HORTENCIA GUILLERMINA | C66: 172.18.2.62 | D66: ACTIVO | E66: F | F66: 20 | G66: 0103562120 | H66: SAYAUSI | I66: NO | J66: CALLE DE LA MENTA Y LOS MATORRALES | K66: betty0210@live.com | L66: 0983451887 0981228718 | N66: 45349 | O66: 100M/100M | P66: GRATIS | Q66: -34.5 | S66: 17.25 | AB66: =Q66+S66+T66-W66-Z66 -> -17.25 | AC66: SIN FACTURA | AD66: 17.25 | AM66: =(AB66+AD66+AE66)-(AH66+AK66) -> 0 | AN66: SIN FACTURA | AO66: 20.54 | AX66: =(AM66+AO66+AP66)-(AS66+AV66) -> 20.54 | AY66: SIN FACTURA | AZ66: 20.54 | BI66: =(AX66+AZ66+BA66)-(BD66+BG66) -> 41.08 | BK66: 20.54 | BT66: =(BI66+BK66+BL66)-(BO66+BR66) -> 61.62
A67: 093 | B67: ZEAS PRADO LUIS MARIO | C67: 172.18.4.4 | D67: ACTIVO | E67: M | F67: 24 | G67: 0102302643 | H67: SAYAUSI | I67: SI | J67: AV. ORDOÑEZ LASSO (BARRIO SANTA MARÍA) | K67: Zeasbraulio29@gmail.com | L67: 0939294084 | N67: 45418 | O67: 100M/100M | P67: 45 | Q67: 0 | S67: 17.25 | U67: 46031 | V67: 46029 | W67: 17.25 | X67: Pichincha | AB67: =S67+T67-W67-Z67 -> 0 | AC67: C0356 | AD67: 17.25 | AF67: 46062 | AG67: 46059 | AH67: 17.25 | AI67: Pichincha | AJ67: 125423 | AM67: =(AB67+AD67+AE67)-(AH67+AK67) -> 0 | AN67: C0388 | AO67: 17.25 | AQ67: 46090 | AR67: 7/3/2026 | AS67: 17.27 | AT67: Pichincha | AX67: =(AM67+AO67+AP67)-(AS67+AV67) -> -0.02 | AY67: C0438 | AZ67: 17.25 | BB67: 46121 | BC67: 11/4/2026 | BD67: 17.25 | BE67: Pichincha | BF67: 141512 | BI67: =(AX67+AZ67+BA67)-(BD67+BG67) -> -0.02 | BJ67: C02737 | BK67: 17.25 | BM67: 46151 | BT67: =(BI67+BK67+BL67)-(BO67+BR67) -> 17.23
A68: 094 | B68: SOLANO QUEZADA RAUL FERNANDO | C68: 172.18.2.64 | D68: ACTIVO | E68: M | F68: 24 | G68: 1727301028 | H68: SAYAUSI | I68: SI | J68: ELIZABETH VELASQUEZ Y CAMINO A SAN MIGUEL DE PUTUSHI | K68: raulsolano455@gmail.com | L68: 0960234479 | M68: 94sayarauls | N68: 45425 | O68: 650M/650M | P68: 45 | Q68: -0.2 | S68: 23 | T68: 0 | U68: 46031 | V68: 46027 | W68: 23 | X68: Pichincha | AB68: =S68+T68-W68-Z68 -> 0 | AC68: C0377 | AD68: 23 | AE68: 0 | AF68: 46062 | AG68: 46055 | AH68: 23 | AI68: Pichincha | AM68: =(AB68+AD68+AE68)-(AH68+AK68) -> 0 | AN68: C0426 | AO68: 23 | AP68: 0 | AQ68: 46090 | AR68: 3/3/2026 | AS68: 23 | AT68: Pichincha | AX68: =(AM68+AO68+AP68)-(AS68+AV68) -> 0 | AY68: C0471 | AZ68: 23 | BA68: 0 | BB68: 46121 | BC68: 6/4/2026 | BD68: 23 | BE68: Pichincha | BI68: =(AX68+AZ68+BA68)-(BD68+BG68) -> 0 | BJ68: C0514 | BK68: 23 | BL68: 0 | BM68: 46151 | BN68: 4/5/2026 | BO68: 23 | BP68: Pichincha | BT68: =(BI68+BK68+BL68)-(BO68+BR68) -> 0
A69: 095 | B69: ALVARRACIN GUTAMA JONATHAN RAFAEL | C69: 172.18.2.65 | D69: INACTIVO | E69: M | F69: 24 | G69: 0106757537 | H69: SAYAUSI | I69: SI | J69: CALLE AV. EL TEJAR Y DE LA ORTIGA | K69: jhonagutama3@gmail.com | L69: 0968301253 +593 99 337 7095 | M69: 95sayamarlona | N69: 45483 | O69: 600M/600M | P69: GRATIS | Q69: 130.54 | U69: 46031 | AB69: =S69+T69-W69-Z69 -> 0 | AC69: SIN FACTURA | AF69: 46062 | AM69: =(AB69+AD69+AE69)-(AH69+AK69) -> 0 | AN69: SIN FACTURA | AQ69: 46090 | AX69: =(AM69+AO69+AP69)-(AS69+AV69) -> 0 | AY69: SIN FACTURA | BB69: 46121 | BI69: =(AX69+AZ69+BA69)-(BD69+BG69) -> 0 | BM69: 46151 | BT69: =(BI69+BK69+BL69)-(BO69+BR69) -> 0
A70: 096 | B70: LIBRE ED ERICK | D70: INACTIVO | Q70: 0 | AB70: =S70+T70-W70-Z70 -> 0 | AC70: SIN FACTURA | AM70: =(AB70+AD70+AE70)-(AH70+AK70) -> 0 | AN70: SIN FACTURA | AX70: =(AM70+AO70+AP70)-(AS70+AV70) -> 0 | AY70: SIN FACTURA | BI70: =(AX70+AZ70+BA70)-(BD70+BG70) -> 0 | BT70: =(BI70+BK70+BL70)-(BO70+BR70) -> 0
A71: 097 | B71: ESPINOZA QUEVEDO BARBARA | C71: 172.18.2.67 | D71: INACTIVO | G71: 2100551122 | H71: SAYAUSI | I71: SI | J71: CALLE AV. EL TEJAR Y DE LA ORTIGA | K71: barbaraespinoza90@gmail.com | L71: 0958839333 | N71: 45486 | O71: 600M/600M | P71: GRATIS | Q71: 0 | AB71: =S71+T71-W71-Z71 -> 0 | AC71: SIN FACTURA | AM71: =(AB71+AD71+AE71)-(AH71+AK71) -> 0 | AN71: SIN FACTURA | AX71: =(AM71+AO71+AP71)-(AS71+AV71) -> 0 | AY71: SIN FACTURA | BI71: =(AX71+AZ71+BA71)-(BD71+BG71) -> 0 | BT71: =(BI71+BK71+BL71)-(BO71+BR71) -> 0
A72: 098 | B72: LOJA GUAILLAS ERICK FABRICIO (EDIFICIO) (WILMER) | C72: 172.18.3.16 | D72: ACTIVO | E72: M | F72: 12 | G72: 0105785976 | H72: SAYAUSI | I72: SI | J72: CALLE AV. EL TEJAR Y DE LA ORTIGA | K72: erickloja.notificaciones@gmail.com | L72: 0962709482 0984843198 | M72: 098sayaerickl | N72: 45505 | O72: 800M/800M | P72: GRATIS | Q72: 8.05 | S72: 8.05 | T72: 0 | U72: 46031 | V72: 22/1/2026 | W72: 8.05 | X72: Pichincha | AB72: =S72+T72-W72-Z72 -> 0 | AC72: SIN FACTURA | AD72: 8.05 | AE72: 0 | AF72: 46062 | AG72: 46076 | AH72: 8.05 | AI72: Pichincha | AM72: =(AB72+AD72+AE72)-(AH72+AK72) -> 0 | AN72: SIN FACTURA | AO72: 8.05 | AP72: 0 | AQ72: 46090 | AR72: 25/3/2026 | AS72: 8.05 | AT72: JEP | AX72: =(AM72+AO72+AP72)-(AS72+AV72) -> 0 | AY72: SIN FACTURA | AZ72: 8.05 | BA72: 0 | BB72: 46121 | BC72: 24/4/2026 | BD72: 8.05 | BE72: JEP | BI72: =(AX72+AZ72+BA72)-(BD72+BG72) -> 0 | BK72: 8.05 | BL72: 0 | BM72: 46151 | BT72: =(BI72+BK72+BL72)-(BO72+BR72) -> 8.05
A73: 099 | B73: VELEZ MALDONADO JOHANA MARITZA | C73: 172.18.3.20 | D73: ACTIVO | E73: M | F73: 24 | G73: 0107184632 | H73: SAYAUSI | I73: SI | J73: CALLE AV. EL TEJAR Y DE LA ORTIGA | K73: jvelezmaldonado8@gmail.com | L73: 0968907019 0994610909 | N73: 45756 | O73: 650M/650M | P73: GRATIS | Q73: 0 | S73: 11.5 | U73: 46031 | V73: 26/1/2026 | W73: 11.5 | X73: JEP | AB73: =S73+T73-W73-Z73 -> 0 | AC73: SIN FACTURA | AD73: 11.5 | AF73: 46062 | AG73: 46071 | AH73: 11.5 | AI73: JEP | AM73: =(AB73+AD73+AE73)-(AH73+AK73) -> 0 | AN73: SIN FACTURA | AO73: =11.5+15 -> 26.5 | AQ73: 46090 | AR73: 25/3/2026 | AS73: =11.5+15 -> 26.5 | AT73: JEP | AX73: =(AM73+AO73+AP73)-(AS73+AV73) -> 0 | AY73: SIN FACTURA | AZ73: =11.5+15 -> 26.5 | BB73: 46121 | BC73: 22/4/2026 | BD73: 26.5 | BE73: JEP | BI73: =(AX73+AZ73+BA73)-(BD73+BG73) -> 0 | BK73: =11.5+15 -> 26.5 | BM73: 46151 | BT73: =(BI73+BK73+BL73)-(BO73+BR73) -> 26.5
A74: 100 | B74: TACURI PULLA JUAN PABLO | C74: 172.18.3.2 | D74: ACTIVO | E74: M | G74: 0106181191 | H74: SAYAUSI | I74: SI | J74: CALLE AV. EL TEJAR Y DE LA ORTIGA | K74: jpablo-tacuri@hotmail.com | L74: 0960086627 | M74: 100sayajuant | N74: 45497 | Q74: -1.84 | S74: 20.54 | T74: 2 | U74: 46031 | V74: 46024 | W74: 20.54 | X74: JEP | Z74: 1.96 | AA74: JEP | AB74: =S74+T74-W74-Z74 -> 0.04 | AC74: C0347 | AD74: 20.54 | AE74: 2 | AF74: 46062 | AG74: 46055 | AH74: 22.5 | AI74: JEP | AM74: =(AB74+AD74+AE74)-(AH74+AK74) -> 0.08 | AN74: C0390 | AO74: 20.54 | AP74: 2 | AQ74: 46090 | AR74: 1/3/2026 | AS74: 20.5 | AT74: JEP | AV74: 2 | AW74: JEP | AX74: =(AM74+AO74+AP74)-(AS74+AV74) -> 0.12 | AY74: C0440 | AZ74: 20.54 | BA74: 2 | BB74: 46121 | BC74: 1/4/2026 | BD74: 22.5 | BE74: JEP | BI74: =(AX74+AZ74+BA74)-(BD74+BG74) -> 0.16 | BJ74: C02739 | BK74: 20.54 | BL74: 2 | BM74: 46151 | BN74: 1/5/2026 | BO74: 20.5 | BP74: JEP | BR74: 2 | BS74: JEP | BT74: =(BI74+BK74+BL74)-(BO74+BR74) -> 0.2
A75: 101 | B75: SANCHEZ OROZCO VERONICA ALEXANDRA (HERMANO) | C75: 172.18.3.3 | D75: ACTIVO | E75: F | F75: 12 | G75: 0601840119 | H75: SAYAUSI | I75: SI | J75: AV. DEL TEJAR Y CALLE LA MENTA | K75: sanchezalexandra@live.com | L75: 0989830701 | M75: 102sayaveronicas | N75: 45505 | O75: 600M/600M | P75: GRATIS | Q75: 0 | S75: 20.54 | U75: 46031 | V75: 46032 | W75: 20 | X75: JEP | AB75: =S75+T75-W75-Z75 -> 0.54 | AC75: SIN FACTURA | AD75: 20.54 | AF75: 46062 | AG75: 46062 | AH75: 21.08 | AI75: JEP | AM75: =(AB75+AD75+AE75)-(AH75+AK75) -> 0 | AN75: SIN FACTURA | AO75: 20.54 | AQ75: 46090 | AR75: 11/3/2026 | AS75: 20.5 | AT75: JEP | AX75: =(AM75+AO75+AP75)-(AS75+AV75) -> 0.04 | AY75: SIN FACTURA | AZ75: 20.54 | BB75: 46121 | BC75: 8/4/2026 | BD75: 20 | BE75: JEP | BI75: =(AX75+AZ75+BA75)-(BD75+BG75) -> 0.58 | BK75: 20.54 | BM75: 46151 | BT75: =(BI75+BK75+BL75)-(BO75+BR75) -> 21.12
A76: 102 | B76: SANCHEZ OROZCO VERONICA ALEXANDRA | C76: 172.18.3.4 | D76: ACTIVO | E76: F | F76: 24 | G76: 0601840119 | H76: SAYAUSI | I76: SI | J76: AV.DEL TEJAR Y CALLE LA MENTA | K76: sanchezalexandra@live.com | L76: 0989830701 | M76: 102sayaveronicas | N76: 45505 | O76: 600M/600M | P76: GRATIS | Q76: 0.4 | S76: 20.54 | T76: 0 | U76: 46031 | V76: 46032 | W76: 20 | X76: JEP | AB76: =S76+T76-W76-Z76 -> 0.54 | AC76: SIN FACTURA | AD76: 20.54 | AE76: 0 | AF76: 46062 | AG76: 46062 | AH76: 21.08 | AI76: JEP | AM76: =(AB76+AD76+AE76)-(AH76+AK76) -> 0 | AN76: SIN FACTURA | AO76: 20.54 | AP76: 0 | AQ76: 46090 | AR76: 11/3/2026 | AS76: 20.5 | AT76: JEP | AX76: =(AM76+AO76+AP76)-(AS76+AV76) -> 0.04 | AY76: SIN FACTURA | AZ76: 20.54 | BA76: 0 | BB76: 46121 | BC76: 8/4/2026 | BD76: 20 | BE76: JEP | BI76: =(AX76+AZ76+BA76)-(BD76+BG76) -> 0.58 | BK76: 20.54 | BL76: 0 | BM76: 46151 | BT76: =(BI76+BK76+BL76)-(BO76+BR76) -> 21.12
A77: 103 | B77: CARCHI CABRERA ERIKA JOHANNA | C77: 172.18.3.5 | D77: ACTIVO | E77: F | F77: 24 | G77: 0106853328 | H77: SAYAUSI | I77: SI | J77: AV.DEL TEJAR Y CALLE LA MENTA | K77: erikacarchicabrera@gmail.com | L77: 0988860160 | M77: 103sayaerikac | N77: 45505 | O77: 600M/600M | P77: GRATIS | Q77: 0 | S77: 20.54 | T77: 0 | U77: 46031 | V77: 46029 | W77: 20.54 | X77: Pichincha | AB77: =S77+T77-W77-Z77 -> 0 | AC77: C0348 | AD77: 20.54 | AE77: 0 | AF77: 46062 | AG77: 46058 | AH77: 20.54 | AI77: Pichincha | AM77: =(AB77+AD77+AE77)-(AH77+AK77) -> 0 | AN77: C0391 | AO77: 20.54 | AP77: 0 | AQ77: 46090 | AR77: 4/3/2026 | AS77: 20.54 | AT77: Pichincha | AX77: =(AM77+AO77+AP77)-(AS77+AV77) -> 0 | AY77: C0441 | AZ77: 20.54 | BA77: 0 | BB77: 46121 | BC77: 1/4/2026 | BD77: 20.54 | BE77: Pichincha | BI77: =(AX77+AZ77+BA77)-(BD77+BG77) -> 0 | BJ77: C02740 | BK77: 20.54 | BL77: 0 | BM77: 46151 | BN77: 4/5/2026 | BO77: 20.54 | BP77: Pichincha | BT77: =(BI77+BK77+BL77)-(BO77+BR77) -> 0
A78: 104 | B78: AZOCAR GUERRA DARYANA CAROLINA | C78: 172.18.2.86 | D78: ACTIVO | E78: F | F78: 24 | G78: V26.720.952 | H78: SAYAUSI | I78: SI | J78: SUBIDA A SAN MIGUEL | K78: azocardari@gmail.com | L78: 0963854218 | M78: 104sayadaryanaa | N78: 45505 | O78: 600M/600M | P78: GRATIS | Q78: 0 | S78: 20.54 | T78: 0 | U78: 46037 | V78: 46038 | W78: 20.54 | X78: Pichincha | AB78: =S78+T78-W78-Z78 -> 0 | AC78: SIN FACTURA | AD78: 20.54 | AE78: 0 | AF78: 46068 | AG78: 46070 | AH78: 22.55 | AI78: Pichincha | AJ78: 128818 | AM78: =(AB78+AD78+AE78)-(AH78+AK78) -> -2.01 | AN78: SIN FACTURA | AO78: 20.54 | AP78: 0 | AQ78: 46096 | AR78: 16/3/2026 | AS78: 18.55 | AT78: Pichincha | AX78: =(AM78+AO78+AP78)-(AS78+AV78) -> -0.02 | AY78: SIN FACTURA | AZ78: 20.54 | BA78: 0 | BB78: 46127 | BC78: 23/4/2026 | BD78: 20.52 | BE78: Pichincha | BI78: =(AX78+AZ78+BA78)-(BD78+BG78) -> 0 | BK78: 20.54 | BL78: 0 | BM78: 46157 | BT78: =(BI78+BK78+BL78)-(BO78+BR78) -> 20.54
A79: 105 | B79: BUESTAN GUTIERREZ PABLO FABIAN | C79: 172.18.3.7 | D79: INACTIVO | E79: M | F79: SIN | H79: SAYAUSI | I79: SI | J79: AV.DEL TEJAR Y CALLE LA MENTA | M79: 105sayapablob | N79: 45505 | O79: 600M/600M | P79: GRATIS | Q79: 0 | AB79: =S79+T79-W79-Z79 -> 0 | AC79: SIN FACTURA | AM79: =(AB79+AD79+AE79)-(AH79+AK79) -> 0 | AN79: SIN FACTURA | AX79: =(AM79+AO79+AP79)-(AS79+AV79) -> 0 | AY79: SIN FACTURA | BI79: =(AX79+AZ79+BA79)-(BD79+BG79) -> 0 | BT79: =(BI79+BK79+BL79)-(BO79+BR79) -> 0
A80: 106 | B80: TENECORA ORELLANA RUBENIA MARGOTH | C80: 172.18.3.8 | D80: ACTIVO | E80: F | F80: 12 | G80: 0104119821 | H80: SAYAUSI | I80: SI | J80: AV.DEL TEJAR Y CALLE LA MENTA | K80: rubenia_tenecora27@hotmail.com | L80: 0998625573 | M80: 106sayarubeniam | N80: 45505 | O80: 600M/600M | P80: GRATIS | Q80: -3.92 | S80: 20.54 | T80: 0 | U80: 46031 | V80: 46049 | W80: 20.54 | X80: Pichincha | AB80: =S80+T80-W80-Z80 -> 0 | AC80: SIN FACTURA | AD80: 20.54 | AE80: 0 | AF80: 46062 | AG80: 46076 | AH80: 20.54 | AI80: Pichincha | AM80: =(AB80+AD80+AE80)-(AH80+AK80) -> 0 | AN80: SIN FACTURA | AO80: 20.54 | AP80: 0 | AQ80: 46090 | AR80: 6/4/2026 | AS80: 20.54 | AT80: Pichincha | AX80: =(AM80+AO80+AP80)-(AS80+AV80) -> 0 | AY80: SIN FACTURA | AZ80: 20.54 | BA80: 0 | BB80: 46121 | BC80: 28/4/2026 | BD80: 20.54 | BE80: Pichincha | BI80: =(AX80+AZ80+BA80)-(BD80+BG80) -> 0 | BK80: 20.54 | BL80: 0 | BM80: 46151 | BT80: =(BI80+BK80+BL80)-(BO80+BR80) -> 20.54
A81: 107 | B81: GUAILLAS CARANQUI CARLOS RAMIRO | C81: 172.18.3.9 | D81: ACTIVO | E81: F | F81: 12 | G81: 0103762134 | H81: SAYAUSI | I81: SI | J81: AV.DEL TEJAR Y CALLE LA MENTA | K81: liderazgoyestudio@gmail.com | L81: 0963273939 | N81: 45981 | O81: 600M/600M | P81: GRATIS | Q81: 0 | S81: 20.54 | T81: 0 | U81: 46031 | V81: 46044 | W81: 20.54 | X81: Pichincha | AB81: =S81+T81-W81-Z81 -> 0 | AC81: C0358 | AD81: 20.54 | AE81: 0 | AF81: 46062 | AG81: 46066 | AH81: 20.54 | AI81: Pichincha | AM81: =(AB81+AD81+AE81)-(AH81+AK81) -> 0 | AN81: C0392 | AO81: 20.54 | AP81: 0 | AQ81: 46090 | AR81: 21/3/2026 | AS81: 20.54 | AT81: Pichincha | AX81: =(AM81+AO81+AP81)-(AS81+AV81) -> 0 | AY81: C0442 | AZ81: 20.54 | BA81: 0 | BB81: 46121 | BC81: 24/4/2026 | BD81: 20.54 | BE81: Pichincha | BI81: =(AX81+AZ81+BA81)-(BD81+BG81) -> 0 | BJ81: C02741 | BK81: 20.54 | BL81: 0 | BM81: 46151 | BT81: =(BI81+BK81+BL81)-(BO81+BR81) -> 20.54
A82: 108 | B82: SIGUENCIA DELGADO LUIS ANGEL | C82: 172.18.1.43 | D82: ACTIVO | E82: SI | F82: 24 | G82: 0928998673 | H82: SAYAUSI | I82: SI | J82: SUBIDA A SAN MIGUEL | K82: luchoflow1990@gmail.com | L82: 0999853460 0989892052 | M82: 108sayaluiss | N82: 46059 | O82: 600M/600M | P82: GRATIS | Q82: 0 | S82: 20.54 | T82: 0 | U82: 46031 | V82: 46043 | W82: 20.54 | X82: Pichincha | AB82: =S82+T82-W82-Z82 -> 0 | AC82: SIN FACTURA | AD82: 20.54 | AE82: 0 | AF82: 46062 | AG82: 46065 | AH82: 20.54 | AI82: Pichincha | AM82: =(AB82+AD82+AE82)-(AH82+AK82) -> 0 | AN82: SIN FACTURA | AO82: 20.54 | AP82: 0 | AQ82: 46090 | AR82: 16/3/2026 | AS82: 20.54 | AT82: Pichincha | AX82: =(AM82+AO82+AP82)-(AS82+AV82) -> 0 | AY82: SIN FACTURA | AZ82: 20.54 | BA82: 0 | BB82: 46121 | BC82: 17/04/2026 | BD82: 20.54 | BE82: Pichincha | BI82: =(AX82+AZ82+BA82)-(BD82+BG82) -> 0 | BK82: 20.54 | BL82: 0 | BM82: 46151 | BT82: =(BI82+BK82+BL82)-(BO82+BR82) -> 20.54
A83: 109 | B83: MINCHALO RIERA WILSON CIRILO | C83: 172.18.1.31 | D83: ACTIVO | E83: M | F83: 24 | G83: 0104154216 | H83: SAYAUSI | I83: NO | J83: SAN MIGUEL | K83: wilsonminchalo76@gmail.com | L83: 0997593462 | M83: 109sayawilsonm | N83: 45506 | O83: 650M/650M | P83: GRATIS | Q83: 0 | S83: 23 | U83: 46031 | V83: 46034 | W83: 23 | X83: Pichincha | Y83: 119427 | AB83: =S83+T83-W83-Z83 -> 0 | AC83: C0378 | AD83: 23 | AF83: 46062 | AG83: 46081 | AH83: 23 | AI83: Pichincha | AJ83: 133878 | AM83: =(AB83+AD83+AE83)-(AH83+AK83) -> 0 | AN83: C0427 | AO83: 23 | AQ83: 46090 | AR83: 26/3/2026 | AS83: 23 | AT83: Pichincha | AX83: =(AM83+AO83+AP83)-(AS83+AV83) -> 0 | AY83: C0472 | AZ83: 23 | BB83: 46121 | BC83: 30/4/2026 | BD83: 23 | BE83: Pichincha | BI83: =(AX83+AZ83+BA83)-(BD83+BG83) -> 0 | BJ83: C0515 | BK83: 23 | BM83: 46151 | BT83: =(BI83+BK83+BL83)-(BO83+BR83) -> 23
A84: 110 | B84: QUINDE CAICEDO NICOLE | C84: 172.18.3.11 | D84: ACTIVO | E84: F | F84: 24 | G84: 0941072506001 | H84: SAYAUSI | I84: SI | J84: AV. TEJAR Y CALLE DE LA MENTA | K84: caicedonicole720@gmail.com | L84: 0981417874 | M84: 110sayamiriamm | N84: 45509 | O84: 600M/600M | P84: GRATIS | Q84: 0.02 | S84: 20.54 | U84: 46038 | V84: 21/1/2026 | W84: 20.54 | X84: Pichincha | AB84: =S84+T84-W84-Z84 -> 0 | AC84: C0359 | AD84: 20.54 | AF84: 46069 | AG84: 46071 | AH84: 20.54 | AI84: Pichincha | AM84: =(AB84+AD84+AE84)-(AH84+AK84) -> 0 | AN84: C0393 | AO84: 20.54 | AQ84: 46097 | AR84: 16/3/2026 | AS84: 20.54 | AT84: Pichincha | AX84: =(AM84+AO84+AP84)-(AS84+AV84) -> 0 | AY84: C0443 | AZ84: 20.54 | BB84: 46128 | BC84: 16/4/2026 | BD84: 20.54 | BE84: Pichincha | BI84: =(AX84+AZ84+BA84)-(BD84+BG84) -> 0 | BJ84: C02742 | BK84: 20.54 | BM84: 46158 | BT84: =(BI84+BK84+BL84)-(BO84+BR84) -> 20.54
A85: 111 | B85: ENRIQUEZ ENRIQUEZ MONICA DEL ROSARIO | C85: 172.18.2.71 | D85: ACTIVO | E85: F | F85: SIN | G85: 0105696017 | H85: SAYAUSI | I85: SI | J85: CALLE AV. EL TEJAR Y DE LA ORTIGA | K85: monyenr26@gmail.com | L85: 0968021224 | M85: 96sayamonicae | N85: 45517 | O85: 600M/600M | P85: GRATIS | Q85: 0 | S85: 20.54 | T85: 0 | U85: 46031 | V85: 46038 | W85: 20.54 | X85: Pichincha | Y85: 120486 | AB85: =S85+T85-W85-Z85 -> 0 | AC85: C0349 | AD85: 20.54 | AE85: 0 | AF85: 46062 | AG85: 46072 | AH85: 20.54 | AI85: Pichincha | AJ85: 129780 | AM85: =(AB85+AD85+AE85)-(AH85+AK85) -> 0 | AN85: C0394 | AO85: 20.54 | AP85: 0 | AQ85: 46090 | AR85: 21/3/2026 | AS85: 20.54 | AT85: Pichincha | AX85: =(AM85+AO85+AP85)-(AS85+AV85) -> 0 | AY85: C0444 | AZ85: 20.54 | BA85: 0 | BB85: 46121 | BC85: 16/4/2026 | BD85: 20.54 | BE85: Pichincha | BI85: =(AX85+AZ85+BA85)-(BD85+BG85) -> 0 | BJ85: C02743 | BK85: 20.54 | BL85: 0 | BM85: 46151 | BT85: =(BI85+BK85+BL85)-(BO85+BR85) -> 20.54
A86: 112 | B86: QUIÑONEZ QUIÑONEZ MARIA DIANA | C86: 172.18.1.32 | D86: ACTIVO | E86: F | F86: SIN | G86: 0918912486 | H86: SAYAUSI | I86: SI | J86: SECTOR LA HERMITA | K86: dianaquinonez624@gmail.com | L86: 0988363530 0994465266 | M86: 112sayamariaq | N86: 45533 | O86: 650M/650M | P86: 25 | Q86: 0 | S86: 23 | T86: 0 | U86: 46031 | V86: 45680 | W86: 23 | X86: Pichincha | AB86: =S86+T86-W86-Z86 -> 0 | AC86: C0379 | AD86: 23 | AE86: 0 | AF86: 46062 | AG86: 46076 | AH86: 23 | AI86: Pichincha | AM86: =(AB86+AD86+AE86)-(AH86+AK86) -> 0 | AN86: C0428 | AO86: 23 | AP86: 0 | AQ86: 46090 | AR86: 23/3/2026 | AS86: 23 | AT86: Pichincha | AX86: =(AM86+AO86+AP86)-(AS86+AV86) -> 0 | AY86: C0473 | AZ86: 23 | BA86: 0 | BB86: 46121 | BC86: 22/4/2026 | BD86: 23 | BE86: Pichincha | BF86: 322193 | BI86: =(AX86+AZ86+BA86)-(BD86+BG86) -> 0 | BJ86: C0516 | BK86: 23 | BL86: 2 | BM86: 46151 | BT86: =(BI86+BK86+BL86)-(BO86+BR86) -> 25
A87: 113 | B87: CARRILLO DOMINGUEZ JHOANA ELIZABETH | C87: 172.18.1.33 | D87: INACTIVO | E87: F | F87: 24 | G87: 0105877864 | H87: SAYAUSI | I87: SI | J87: SUBIDA A LA HERMITA | K87: carrillo.jhoana@yahoo.com | L87: 0980444195 | M87: 113sayajhoanac | N87: 45534 | O87: .800M/800M | P87: GRATIS | Q87: 0 | AB87: =S87+T87-W87-Z87 -> 0 | AC87: SIN FACTURA | AM87: =(AB87+AD87+AE87)-(AH87+AK87) -> 0 | AN87: SIN FACTURA | AX87: =(AM87+AO87+AP87)-(AS87+AV87) -> 0 | AY87: SIN FACTURA | BI87: =(AX87+AZ87+BA87)-(BD87+BG87) -> 0 | BT87: =(BI87+BK87+BL87)-(BO87+BR87) -> 0
A88: 114 | B88: MUÑOZ ALVAREZ LILIAN MARLENE | C88: 172.18.1.35 | D88: INACTIVO | E88: F | F88: SIN | G88: 0104769963 | H88: SAYAUSI | J88: SUBIDA A LA HERMITA | K88: lilianmunoz414@gmail.com | L88: 0983149695 | N88: 45544 | O88: 100M/100M | P88: GRATIS | Q88: 0 | AB88: =S88+T88-W88-Z88 -> 0 | AC88: SIN FACTURA | AM88: =(AB88+AD88+AE88)-(AH88+AK88) -> 0 | AN88: SIN FACTURA | AX88: =(AM88+AO88+AP88)-(AS88+AV88) -> 0 | AY88: SIN FACTURA | BI88: =(AX88+AZ88+BA88)-(BD88+BG88) -> 0 | BT88: =(BI88+BK88+BL88)-(BO88+BR88) -> 0
A89: 115 | B89: CRISANTO MOSQUERA DIOGO KLEVER | C89: 172.18.2.72 | D89: INACTIVO | E89: M | F89: SIN | H89: SAYAUSI | L89: 998135858 | M89: 115sayadiogoc | N89: 45549 | P89: 45 | Q89: 90.54 | S89: 10 | U89: 46031 | AB89: 0 | AC89: SIN FACTURA | AF89: 46062 | AM89: =(AB89+AD89+AE89)-(AH89+AK89) -> 0 | AN89: SIN FACTURA | AQ89: 46090 | AX89: =(AM89+AO89+AP89)-(AS89+AV89) -> 0 | AY89: SIN FACTURA | BB89: 46121 | BI89: =(AX89+AZ89+BA89)-(BD89+BG89) -> 0 | BM89: 46151 | BT89: =(BI89+BK89+BL89)-(BO89+BR89) -> 0
A90: 116 | B90: ILLESCAS PATINO EVELYN DANIELA (ED SRA KARLA) | C90: 172.18.3.12 | D90: INACTIVO | E90: F | F90: 24 | G90: 0107065880 | H90: SAYAUSI | I90: SI | J90: AV.DEL TEJAR Y CALLE LA MENTA | K90: evelyn19.illescas@gmail.com | L90: 0999855857 | M90: 116sayaevelyni | N90: 45549 | O90: 600M/600M | P90: GRATIS | Q90: 0 | S90: 20.54 | U90: 46031 | AB90: =S90+T90-W90-Z90 -> 20.54 | AC90: SIN FACTURA | AD90: 10 | AF90: 46062 | AM90: =(AB90+AD90+AE90)-(AH90+AK90) -> 30.54 | AN90: SIN FACTURA | AO90: 10 | AQ90: 46090 | AR90: 3/3/2026 | AS90: 40.54 | AT90: Pichincha | AX90: =(AM90+AO90+AP90)-(AS90+AV90) -> 0 | AY90: SIN FACTURA | BB90: 46121 | BI90: =(AX90+AZ90+BA90)-(BD90+BG90) -> 0 | BM90: 46151 | BT90: =(BI90+BK90+BL90)-(BO90+BR90) -> 0
A91: 117 | B91: ZAMBRANO GUAILLAS WILMER ANDRES | C91: 172.18.3.17 | D91: ACTIVO | E91: M | F91: 24 | G91: 0106693153 | H91: SAYAUSI | I91: SI | J91: AV.DEL TEJAR Y CALLE LA ORTIGA | K91: wazg97@gmail.com | L91: 0962709482 | M91: 117sayawilmerz | N91: 45573 | O91: 650M/650M | P91: GRATIS | Q91: 0 | S91: 23 | U91: 46031 | V91: 22/1/2026 | W91: 23 | X91: Pichincha | AB91: =S91+T91-W91-Z91 -> 0 | AC91: C02406 | AD91: 23 | AF91: 46062 | AG91: 46076 | AH91: 23 | AI91: Pichincha | AM91: =(AB91+AD91+AE91)-(AH91+AK91) -> 0 | AN91: C0429 | AO91: =23+15 -> 38 | AQ91: 46090 | AR91: 25/3/2026 | AS91: =23+15 -> 38 | AT91: JEP | AX91: =(AM91+AO91+AP91)-(AS91+AV91) -> 0 | AY91: C0474 | AZ91: 23 | BB91: 46121 | BC91: 24/04/2026 | BD91: 23 | BE91: JEP | BI91: =(AX91+AZ91+BA91)-(BD91+BG91) -> 0 | BJ91: C0517 | BK91: 23 | BM91: 46151 | BT91: =(BI91+BK91+BL91)-(BO91+BR91) -> 23
A92: 118 | B92: ZUMBA SANCHEZ JOHANNA VERONICA | C92: 172.18.1.36 | D92: ACTIVO | E92: F | F92: 12 | G92: 0104587464 | H92: SAYAUSI | I92: SI | J92: SUBIDA A SAN MIGUEL | K92: zujove070899@gmail.com | L92: 0969063324 0959467166 | M92: 118sayajohannaz | N92: 45363 | O92: 600M/600M | P92: GRATIS | Q92: -0.46 | S92: 20.54 | T92: 0 | U92: 46031 | V92: 22/1/2026 | W92: 20.54 | X92: JEP | AB92: =S92+T92-W92-Z92 -> 0 | AC92: SIN FACTURA | AD92: 20.54 | AE92: 0 | AF92: 46062 | AG92: 46074 | AH92: 20.54 | AI92: JEP | AM92: =(AB92+AD92+AE92)-(AH92+AK92) -> 0 | AN92: SIN FACTURA | AO92: 20.54 | AP92: 0 | AQ92: 46090 | AR92: 25/3/2026 | AS92: 20.54 | AT92: JEP | AX92: =(AM92+AO92+AP92)-(AS92+AV92) -> 0 | AY92: SIN FACTURA | AZ92: 20.54 | BA92: 0 | BB92: 46121 | BC92: 14/4/2026 | BD92: 20.54 | BE92: JEP | BI92: =(AX92+AZ92+BA92)-(BD92+BG92) -> 0 | BK92: 20.54 | BL92: 0 | BM92: 46151 | BT92: =(BI92+BK92+BL92)-(BO92+BR92) -> 20.54
A93: 119 | B93: SICHA LOJA EVELYN DAYANNA (ESTEBAN GUTAMA) | C93: 172.18.3.13 | D93: ACTIVO | E93: F | F93: 12 | G93: 0106666142 | H93: SAYAUSI | I93: NO | J93: AV. TEJAR Y DE LA ORTIGA | K93: evelyndayanna01@gmail.com | L93: 0987829567 0967001605 | N93: 45579 | O93: 600M/600M | P93: GRATIS | Q93: -2.68 | S93: 0 | U93: 46046 | AB93: =S93+T93-W93-Z93 -> 0 | AC93: SIN FACTURA | AD93: 20.54 | AF93: 46077 | AG93: 46081 | AH93: 20.54 | AI93: Pichincha | AM93: =(AB93+AD93+AE93)-(AH93+AK93) -> 0 | AN93: SIN FACTURA | AO93: 20.54 | AQ93: 46105 | AR93: 25/3/2026 | AS93: 20.5 | AT93: Pichincha | AX93: =(AM93+AO93+AP93)-(AS93+AV93) -> 0.04 | AY93: SIN FACTURA | AZ93: 20.54 | BB93: 46136 | BC93: 20/4/2026 | BD93: 21 | BE93: JEP | BI93: =(AX93+AZ93+BA93)-(BD93+BG93) -> -0.42 | BK93: 20.54 | BM93: 46166 | BT93: =(BI93+BK93+BL93)-(BO93+BR93) -> 20.12
A94: 120 | B94: GOMEZ SANGURIMA ELIANA JACQUELINE | C94: 172.18.1.37 | D94: ACTIVO | E94: F | F94: 24 | G94: 0105364087 | H94: SAYAUSI | I94: NO | J94: SECTOR LA HERMITA | K94: du.l.cejaky@hotmail.com | L94: 0989109410 0939351271 0989109410 | M94: 120sayaelianag | N94: 45582 | O94: 650M/650M | P94: GRATIS | Q94: 0 | S94: 23 | T94: 0 | U94: 46032 | V94: 46034 | W94: 23 | X94: Pichincha | AB94: =S94+T94-W94-Z94 -> 0 | AC94: C0380 | AD94: 23 | AE94: 0 | AF94: 46063 | AG94: 46071 | AH94: 23 | AI94: Pichincha | AM94: =(AB94+AD94+AE94)-(AH94+AK94) -> 0 | AN94: C0430 | AO94: 23 | AP94: 0 | AQ94: 46091 | AR94: 4/3/2026 | AS94: 23 | AT94: JEP | AX94: =(AM94+AO94+AP94)-(AS94+AV94) -> 0 | AY94: C0475 | AZ94: 23 | BA94: 0 | BB94: 46122 | BC94: 17/4/2026 | BD94: 23 | BE94: Pichincha | BI94: =(AX94+AZ94+BA94)-(BD94+BG94) -> 0 | BJ94: C0518 | BK94: 23 | BL94: 0 | BM94: 46152 | BT94: =(BI94+BK94+BL94)-(BO94+BR94) -> 23
A95: 121 | B95: GUTAMA CHUNIR RUT FAVIOLA | C95: 172.18.2.74 | D95: ACTIVO | E95: F | F95: 24 | G95: 0105050892 | H95: SAYAUSI | I95: SI | J95: SANTA MARIA | K95: guutamaruth6@gmail.com | L95: 0991343433 0998338650 | M95: 121sayaruthg | N95: 45582 | O95: 650M/650M | P95: GRATIS | Q95: 0 | S95: 23 | T95: 0 | U95: 46032 | V95: 46029 | W95: 23 | X95: Pichincha | Y95: 117684 | AB95: =S95+T95-W95-Z95 -> 0 | AC95: C0381 | AD95: =23 -> 23 | AE95: 0 | AF95: 46063 | AG95: 46072 | AH95: 23 | AI95: Pichincha | AJ95: 129782 | AM95: =(AB95+AD95+AE95)-(AH95+AK95) -> 0 | AN95: C0431 | AO95: =23 -> 23 | AP95: 0 | AQ95: 46091 | AR95: 7/3/2026 | AS95: 23 | AT95: Pichincha | AX95: =(AM95+AO95+AP95)-(AS95+AV95) -> 0 | AY95: C0476 | AZ95: =23 -> 23 | BA95: 0 | BB95: 46122 | BC95: 11/4/2026 | BD95: 23 | BE95: Pichincha | BF95: 141514 | BI95: =(AX95+AZ95+BA95)-(BD95+BG95) -> 0 | BJ95: C0519 | BK95: =23 -> 23 | BL95: 0 | BM95: 46152 | BT95: =(BI95+BK95+BL95)-(BO95+BR95) -> 23
A96: 122 | B96: GALARZA CHALCO HOMERO ANIBAL | C96: 172.18.2.75 | D96: ACTIVO | E96: M | F96: 24 | G96: 0104789029 | H96: SAYAUSI | I96: NO | J96: CALLE SAN MIGUEL Y CALLE LAS BREVAS | K96: anibal.galarza1310@gmail.com | L96: 0987400084 | M96: 122sayahomerog | N96: 45596 | O96: 650M/650M | P96: GRATIS | Q96: 0.5 | S96: 23 | T96: 0 | U96: 46032 | V96: 46037 | W96: 22.5 | X96: JEP | AB96: =Q96+S96+T96-W96-Z96 -> 1 | AC96: SIN FACTURA | AD96: 23 | AE96: 0 | AF96: 46063 | AG96: 46077 | AH96: 25 | AI96: JEP | AM96: =(AB96+AD96+AE96)-(AH96+AK96) -> -1 | AN96: SIN FACTURA | AO96: 23 | AP96: 0 | AQ96: 46091 | AR96: 25/3/2026 | AS96: 23 | AT96: JEP | AX96: =(AM96+AO96+AP96)-(AS96+AV96) -> -1 | AY96: SIN FACTURA | AZ96: 23 | BA96: 0 | BB96: 46122 | BC96: 28/4/2026 | BD96: 23 | BE96: JEP | BI96: =(AX96+AZ96+BA96)-(BD96+BG96) -> -1 | BK96: 23 | BL96: 0 | BM96: 46152 | BT96: =(BI96+BK96+BL96)-(BO96+BR96) -> 22
A97: 123 | B97: CORONEL JIMENEZ JESSICA ANDREINA | C97: 172.18.2.76 | D97: ACTIVO | E97: F | F97: 24 | G97: 0106348139 | H97: SAYAUSI | I97: NO | J97: LAS GROSELLAS SAN MIGUEL | K97: jessy22coronel@gmail.com | L97: 0984305729 | M97: 123sajessicac | N97: 45602 | O97: 600M/600M | P97: GRATIS | Q97: -6.08 | S97: 20.54 | T97: 0 | U97: 46032 | V97: 46048 | W97: 25 | X97: JEP | AB97: =Q97+S97+T97-W97-Z97 -> -10.54 | AC97: SIN FACTURA | AD97: =20.54+45 -> 65.54 | AE97: 0 | AF97: 46063 | AG97: 46078 | AH97: 70 | AI97: JEP | AM97: =(AB97+AD97+AE97)-(AH97+AK97) -> -15 | AN97: SIN FACTURA | AO97: 20.54 | AP97: 0 | AQ97: 46091 | AR97: 12/3/2026 | AS97: 20 | AT97: JEP | AX97: =(AM97+AO97+AP97)-(AS97+AV97) -> -14.46 | AY97: SIN FACTURA | AZ97: 20.54 | BA97: 0 | BB97: 46122 | BC97: 20/4/2026 | BD97: 22 | BE97: JEP | BI97: =(AX97+AZ97+BA97)-(BD97+BG97) -> -15.92 | BK97: 20.54 | BL97: 0 | BM97: 46152 | BT97: =(BI97+BK97+BL97)-(BO97+BR97) -> 4.62
A98: 124 | B98: TENEPAGUAY LEON ALEXANDRA PATRICIA | C98: 172.18.1.38 | D98: ACTIVO | E98: F | F98: 24 | G98: 0105778336 | H98: SAYAUSI | I98: NO | J98: SAN MIGUEL | K98: tenenpaguayalexandra@gmail.com | L98: 0998396524 0982322878 | M98: 124sayaalexandrat | N98: 45608 | O98: 100M/100M | P98: GRATIS | Q98: -3 | S98: 17.25 | T98: 2 | U98: 46032 | V98: 46034 | W98: 20 | X98: JEP | AB98: =S98+T98-W98-Z98 -> -0.75 | AC98: SIN FACTURA | AD98: 17.25 | AE98: 2 | AF98: 46063 | AG98: 46062 | AH98: 20 | AI98: JEP | AM98: =(AB98+AD98+AE98)-(AH98+AK98) -> -1.5 | AN98: SIN FACTURA | AO98: 17.25 | AP98: 2 | AQ98: 46091 | AR98: 13/3/2026 | AS98: 20 | AT98: JEP | AX98: =(AM98+AO98+AP98)-(AS98+AV98) -> -2.25 | AY98: SIN FACTURA | AZ98: 17.25 | BA98: 2 | BB98: 46122 | BC98: 15/4/2026 | BD98: 20 | BE98: JEP | BI98: =(AX98+AZ98+BA98)-(BD98+BG98) -> -3 | BK98: 17.25 | BL98: 2 | BM98: 46152 | BT98: =(BI98+BK98+BL98)-(BO98+BR98) -> 16.25
A99: 125 | B99: CARDENAS VALLADARES VICENTE RODRIGO | C99: 172.18.3.14 | D99: ACTIVO | E99: F | F99: 24 | G99: 0105392559 | H99: SAYAUSI | I99: SI | J99: AV. ORDOÑEZ LASSO Y CALLE DEL TEJAR | K99: cardenasvicente012@gmail.com | L99: 0984473370 0993766373 | N99: 45962 | O99: 600M/600M | P99: GRATIS | Q99: 0 | S99: 20.54 | U99: 46032 | V99: 46049 | W99: 20 | X99: JEP | AB99: =S99+T99-W99-Z99 -> 0.54 | AC99: C0344 | AD99: 20.54 | AF99: 46063 | AG99: 46077 | AH99: 21.08 | AI99: Pichincha | AM99: =(AB99+AD99+AE99)-(AH99+AK99) -> 0 | AN99: C0395 | AO99: =20.54+17.5 -> 38.04 | AQ99: 46091 | AS99: 38.04 | AT99: Pichincha | AX99: =(AM99+AO99+AP99)-(AS99+AV99) -> 0 | AY99: C0446 | AZ99: =20.54+17.5 -> 38.04 | BB99: 46122 | BC99: 22/4/2026 | BD99: 38 | BE99: Pichincha | BI99: =(AX99+AZ99+BA99)-(BD99+BG99) -> 0.04 | BK99: 20.54 | BM99: 46152 | BT99: =(BI99+BK99+BL99)-(BO99+BR99) -> 20.58
A100: 126 | B100: CABRERA BURI KARLA FABIOLA | C100: 172.18.5.3 | D100: ACTIVO | E100: F | F100: 24 | G100: 0705912640 | H100: SAYAUSI | I100: NO | J100: BUENOS AIRES | K100: cabreraburik@gmail.com | L100: 0984604015 0997228600 | N100: 45610 | O100: 650M/650M | P100: GRATIS | Q100: 0 | S100: 0 | U100: 45300 | AB100: =S100+T100-W100-Z100 -> 0 | AC100: SIN FACTURA | AD100: 0 | AF100: 45331 | AM100: =(AB100+AD100+AE100)-(AH100+AK100) -> 0 | AN100: SIN FACTURA | AO100: 0 | AQ100: 45360 | AX100: =(AM100+AO100+AP100)-(AS100+AV100) -> 0 | AY100: SIN FACTURA | AZ100: 0 | BB100: 45391 | BI100: =(AX100+AZ100+BA100)-(BD100+BG100) -> 0 | BK100: 0 | BM100: 45421 | BT100: =(BI100+BK100+BL100)-(BO100+BR100) -> 0
...

Sheet PLATAFORMA
A1: COD | B1: NOMBRE CLIENTE | C1: CONTACTO | D1: PROVEEDOR | E1: USUARIO | F1: CONTRASEÑA | G1: CUENTAS | H1: MAC SMART ONE | I1: OBSERVACIONES | J1: ESTADO | K1: VALOR | L1: ACTIVO | M1: ENERO | N1: FACTURA | O1: FECHA A PAGAR | P1: FECHA DE PAGO | Q1: PAGO | R1: BANCO | S1: COD | T1: SALDO | U1: FEBRERO | V1: FACTURA | W1: FECHA A PAGAR | X1: FECHA DE PAGO | Y1: PAGO | Z1: BANCO | AA1: COD | AB1: SALDO | AC1: MARZO | AD1: FACTURA | AE1: FECHA A PAGAR | AF1: FECHA DE PAGO | AG1: PAGO | AH1: BANCO | AI1: COD | AJ1: SALDO | AK1: ABRIL | AL1: FACTURA | AM1: FECHA A PAGAR | AN1: FECHA DE PAGO | AO1: PAGO | AP1: BANCO | AQ1: COD | AR1: SALDO | AS1: MAYO | AT1: FACTURA | AU1: FECHA A PAGAR | AV1: FECHA DE PAGO | AW1: PAGO | AX1: BANCO | AY1: COD | AZ1: SALDO
A2: 1C | B2: EVELYN GISSELLE SOLANO HERRERA | C2: 0979348416 | D2: OPSATEL | E2: Ausayasolano | F2: TV2023.@ | G2: 2 | I2: CUENTA EN TV Y PC | J2: INFINITO | K2: GRATIS | L2: SI | M2: 0 | Q2: 0 | T2: =M2-Q2 -> 0 | U2: 0 | AB2: =U2-Y2 -> 0
A3: 2C | B3: LUIS EDISON ALQUINGA | C3: 0979368744 | D3: OPSATEL | E3: Auluisal | F3: TV2023.@ | G3: 1 | I3: CUENTA EN QUITO | J3: INFINITO | K3: GRATIS | L3: SI | M3: 0 | Q3: 0 | T3: =M3-Q3 -> 0 | U3: 0 | AB3: =U3-Y3 -> 0
A4: 3C | B4: MESIAS GOMEZ JORGE HUMBERTO | C4: 074199465 0989392536 | D4: OPSATEL | E4: Aujorgem | F4: TV2023.@ | G4: 1 | I4: RENOVACIÓN IKS - 15/08/2024 | J4: FIJO | K4: 6 | L4: SI | M4: 6 | P4: 46038 | Q4: 6 | R4: Pichincha | T4: =M4-Q4 -> 0 | U4: 6 | X4: 46071 | Y4: 6 | Z4: Pichincha | AB4: =U4-Y4 -> 0 | AC4: 6 | AE4: 46091 | AF4: 46084 | AG4: 6 | AH4: Pichincha | AK4: 6 | AM4: 46132 | AN4: 46132 | AO4: 6 | AP4: Pichincha
A5: 4C | B5: AVILA CUESTA DAVID GUILLERMO | C5: 0992732555 0983291669 | D5: OPSATEL | E5: Aucueguillermoa | F5: TV2024.@ | G5: 2 | I5: CUENTA IKS DOS TV | J5: FIJO | K5: 16 | L5: SI | M5: 16 | P5: 46027 | Q5: 16 | R5: Pichincha | T5: =M5-Q5 -> 0 | U5: 16 | X5: 46056 | Y5: 16 | Z5: Pichincha | AB5: =U5-Y5 -> 0
A6: 5C | B6: TANIA MARCELA CALLE MESIAS | C6: 0992787096 | D6: OPSATEL | E6: Autaniac | F6: TV2023.@ | G6: 1 | J6: FIJO | K6: 6 | L6: SI | M6: 16 | P6: 46028 | Q6: 16 | R6: Pichincha | T6: =M6-Q6 -> 0 | U6: 6 | AB6: =U6-Y6 -> 6
A7: 6C | B7: DIEGO FERNANDO LIMA JUMA | C7: 0998043204 | D7: OPSATEL | E7: Audiegof | F7: TV2023.@ | G7: 3 | J7: FIJO | K7: 10 | L7: SI | M7: 10 | P7: 46174 | Q7: 10 | R7: Pichincha | T7: =M7-Q7 -> 0 | U7: 10 | X7: 46055 | Y7: 10 | Z7: Pichincha | AB7: =U7-Y7 -> 0 | AC7: 10 | AE7: 46091 | AF7: 46083 | AG7: 10 | AH7: Pichincha | AK7: 10 | AM7: 46122 | AN7: 46113 | AO7: 10 | AP7: Pichincha | AS7: 10 | AU7: 46152 | AV7: 46146 | AW7: 10 | AX7: Pichincha | AZ7: =10-AW7 -> 0
B8: LUCIA CALLE RUC | C8: 99 172 6293 | D8: OPSATEL | G8: 12 | J8: FIJO | K8: 26.91 | L8: SI | M8: 26.91 | N8: C02398 | P8: 21/1/2026 | Q8: 26.91 | R8: JEP | T8: =M8-Q8 -> 0 | U8: 26.91 | V8: C02503 | X8: 46077 | Y8: 26.91 | Z8: JEP | AB8: =U8-Y8 -> 0 | AC8: 31.395 | AD8: C02623 | AE8: 46091 | AF8: 46091 | AG8: 26.91 | AH8: JEP | AK8: 31.4 | AM8: 46122 | AN8: 46132 | AO8: 31.4 | AP8: Pichincha
A9: 7C | B9: PENTHOUSE S.A | C9: 0997742952 0984894015 | D9: OPSATEL | E9: Aubalucia | F9: TV2023.@ | G9: 10 | I9: HOTEL PENTHOUSE | J9: FIJO | K9: 37.95 | L9: SI | M9: 37.95 | N9: C02399 | P9: 46045 | Q9: 37.95 | R9: Pichincha | T9: =M9-Q9 -> 0 | U9: 37.95 | V9: C02502 | X9: 46073 | Y9: 37.95 | Z9: Pichincha | AB9: =U9-Y9 -> 0 | AC9: 37.95 | AD9: C02624
A10: 8C | B10: JAYA GUALPA GERMANIA JANETH | C10: =593997191340 -> 593997191340 | D10: OPSATEL | E10: Ausajuanc | F10: TV2024.@ | G10: 1 | J10: FIJO | K10: 4 | L10: SI | M10: 7 | T10: =M10-Q10 -> 7 | U10: 4 | X10: 46055 | Y10: 20 | Z10: JEP | AB10: =T10+U10-Y10 -> -9 | AE10: 46122 | AG10: 4 | AM10: 46122 | AO10: 4
A11: 12C | B11: ANA CATALINA MESIAS GUAMAN | C11: 0987538447 | D11: OPSATEL | E11: Aucamesias | F11: TV2023.@ | G11: 1 | J11: FIJO | K11: 6 | L11: SI | M11: 6 | P11: 46038 | Q11: 6 | R11: Pichincha | T11: =M11-Q11 -> 0 | U11: 6 | X11: 46071 | Y11: 6 | Z11: Pichincha | AB11: =U11-Y11 -> 0 | AC11: 6 | AE11: 46091 | AF11: 46084 | AG11: 6 | AH11: Pichincha | AK11: 6 | AM11: 46132 | AN11: 46132 | AO11: 6 | AP11: Pichincha
A12: 14C | B12: PABLO FERNANDO SAGBAY CARCHI | C12: 0962826267 | D12: OPSATEL | E12: Aucuepablos | F12: TV2023.@ | G12: 1 | J12: FIJO | K12: 4 | L12: SI | M12: 4 | P12: 46204 | Q12: 4 | R12: JEP | T12: =M12-Q12 -> 0 | U12: 4 | X12: 46063 | Y12: 4 | Z12: JEP | AB12: =U12-Y12 -> 0 | AC12: 4 | AE12: 46091 | AF12: 46083 | AG12: 4 | AH12: JEP | AK12: 4 | AM12: 46122 | AN12: 46116 | AO12: 4 | AP12: JEP | AS12: 4 | AU12: 46152 | AV12: 46147 | AW12: 4 | AX12: JEP | AZ12: 0
A13: 15C | B13: CARLOS QUILLE UGUÑA | C13: 0968381275 | D13: OPSATEL | E13: Aucuecarlosq | F13: TV2023.@ | G13: 3 | J13: FIJO | K13: 18 | L13: SI | T13: =M13-Q13 -> 0 | AB13: =U13-Y13 -> 0 | AC13: 6 | AE13: 46091 | AF13: 46093 | AG13: 6 | AH13: Pichincha
A14: 16C | B14: JUAN KLEBER CABRERA TERREROS | C14: 0996003124 | D14: OPSATEL | E14: Aucuemerced | F14: TV2023.@ | G14: 1 | I14: LA MERCED | J14: IRREGULAR | K14: 4 | L14: SI | T14: =M14-Q14 -> 0 | AB14: =U14-Y14 -> 0
A15: 21C | B15: JUAN DIEGO AREVALO MARQUEZ | C15: 0984753950 | D15: OPSATEL | E15: Aucuejuan | F15: TV2023.@ | G15: 2 | I15: CLIENTE IRREGULAR | J15: SEMIFIJO | K15: 6 | L15: NO | T15: =M15-Q15 -> 0 | AB15: =U15-Y15 -> 0
A16: 22C | B16: JOSE LUIS QUEZADA | C16: 0990805284 | D16: OPSATEL | E16: Aubajosel | F16: TV2023.@ | G16: 1 | I16: CLIENTE IRREGULAR | J16: IRREGULAR | K16: 4 | L16: NO | T16: =M16-Q16 -> 0 | AB16: =U16-Y16 -> 0
A17: 28C | B17: GEOVANNA NARCISA AYALA CARDENAS | C17: 0962291007 | D17: OPSATEL | E17: Auiogeovannaa | F17: TV2024.@ | G17: 2 | I17: RECOMENDADO LUIS ALQUINGA | J17: FIJO | K17: 6 | L17: SI | T17: =M17-Q17 -> 0 | AB17: =U17-Y17 -> 0
A18: 29C | B18: MARTHA LUZMILA PACHO NAULA | C18: 0988197965 | D18: OPSATEL | E18: Aucuemarthap | F18: TV2024.@ | G18: 1 | J18: FIJO | K18: 4 | L18: SI | M18: -8 | Q18: 4 | T18: -4 | U18: 4 | Y18: 4 | AB18: =U18-Y18 -> 0 | AC18: 4 | AG18: 20 | AH18: JEP | AJ18: =AC18-AG18 -> -16
A19: 31C | B19: RENE MAURICIO PATIÑO CARACUNDO | C19: 0995801983 | D19: OPSATEL | E19: Aucuerenep | F19: TV2024.@ | G19: 1 | I19: RECOMENDACION CLIENTE 24C | J19: FIJO | K19: 4 | L19: SI | M19: 6 | P19: 46204 | Q19: 6 | R19: Pichincha | T19: =M19-Q19 -> 0 | U19: 6 | X19: 46064 | Y19: =6+5 -> 11 | Z19: Pichincha | AB19: =U19-Y19 -> -5 | AC19: 6 | AE19: 46091 | AF19: 46091 | AG19: 6 | AH19: Pichincha | AJ19: =AC19-AG19 -> 0 | AK19: 6 | AM19: 46122 | AN19: 46128 | AO19: 6 | AP19: Pichincha
B20: PABLO GUAMAN | D20: LUIS ALQUINGA | E20: Auiopablog | F20: TV2024.@ | G20: 1 | I20: PAGO POR UN AÑO | J20: EXTERNO | K20: 51 | T20: =M20-Q20 -> 0 | AB20: =U20-Y20 -> 0 | AJ20: =AC20-AG20 -> 0
A21: 33C | B21: LISSETH SEVILLANO | C21: 0969939630 | D21: OPSATEL | E21: Auextlisseths | F21: TV2024.@ | G21: 1 | I21: HERMANA LADY SEVILLANO | J21: FIJO | K21: 4 | L21: SI | M21: 4 | P21: 46053 | Q21: 4 | R21: Pichincha | T21: =M21-Q21 -> 0 | U21: 4 | AB21: =U21-Y21 -> 4 | AC21: 4 | AE21: 46091 | AF21: 46094 | AG21: 4 | AH21: Pichincha | AJ21: =AC21-AG21 -> 0
A22: 36C | B22: KARINA GUAMAN | C22: 0968471788 | D22: OPSATEL | E22: Aucuekarinag | F22: TV2024.@ | G22: 1 | J22: SEMIFIJO | K22: 4 | L22: SI | M22: 4 | O22: 46046 | T22: =M22-Q22 -> 4 | U22: 4 | AB22: =U22-Y22 -> 4
A23: 37C | B23: ORDOÑEZ ABAD CARLOS RENE | C23: 0990105069 | D23: OPSATEL | E23: Aureneo | F23: TV2023.@ | G23: 1 | J23: FIJO | K23: 6 | L23: SI | M23: 6 | P23: 26/1/2026 | Q23: 6 | R23: Pichincha | T23: =M23-Q23 -> 0 | U23: 6 | AB23: =U23-Y23 -> 6
A24: 40C | B24: LEONARDO MANUEL YUNGA CHIMBO | C24: 968422984 | D24: OPSATEL | E24: Aucueleonardoy | F24: TV2024.@ | G24: 1 | J24: SEMIFIJO | K24: 4 | L24: SI | T24: =M24-Q24 -> 0 | AB24: =U24-Y24 -> 0
A25: 38C | B25: ADRIANA MAGDALENA NAREA CASTRO | C25: 960587655 | D25: OPSATEL | E25: 109baadrianan | J25: FIJO | K25: 4 | L25: SI | M25: 6 | P25: 46030 | Q25: 6 | R25: Efectivo | T25: =M25-Q25 -> 0 | U25: 6 | AB25: =U25-Y25 -> 6
A26: 17C | B26: ROBERTO ZAMBRANO QUEVEDO | C26: 096 389 4460 | D26: OPSATEL | E26: Auiorobertoz | F26: TV2023.@ | G26: 2 | K26: 6 | L26: SI | M26: =6+4 -> 10 | P26: 46174 | Q26: 10 | R26: Pichincha | T26: =M26-Q26 -> 0 | U26: 6 | X26: 46081 | Y26: 6 | Z26: Pichincha | AB26: =U26-Y26 -> 0
A27: 39C | B27: LIKENET | C27: 0959680752 0958979912 | D27: OPSATEL | G27: CORPORATIVO | J27: FIJO | K27: 498 | L27: SI | M27: 498 | P27: 26/1/2026 | Q27: 498 | R27: Pichincha | T27: =M27-Q27 -> 0 | U27: 498 | X27: 46077 | Y27: 498 | Z27: Pichincha | AB27: =U27-Y27 -> 0 | AC27: 377 | AE27: 46091 | AF27: 46090 | AG27: 377 | AH27: Pichincha
B28: SABANDO LIDER | D28: LUIS ALQUINGA | E28: Auioliders | F28: TV2024.@ | G28: 1 | J28: FIJO | K28: 4 | L28: SI | T28: =M28-Q28 -> 0 | AB28: =U28-Y28 -> 0
B29: GUSTAVO | D29: PATRICIO | E29: Augigustavop | F29: TV2024.@ | G29: 1 | J29: SEMIFIJO | T29: =M29-Q29 -> 0 | U29: 4 | AB29: =U29-Y29 -> 4
B30: CHISTIAN P | D30: PATRICIO | E30: Aucuechristianp | F30: TV2024.@ | G30: 1 | J30: FIJO | T30: =M30-Q30 -> 0 | AB30: =U30-Y30 -> 0
A31: 42C PE | B31: CARLOS ESTEBAN GUAMAN DURAN (VECINO OPSATEL) | D31: OPSATEL | E31: Aucueestebang | F31: TV2025.@ | G31: 1 | J31: FIJO | M31: 4 | P31: 46041 | Q31: 4 | R31: Efectivo | T31: =M31-Q31 -> 0 | U31: 4 | X31: 46078 | Y31: 4 | Z31: Efectivo | AB31: =U31-Y31 -> 0 | AC31: =4+5 -> 9 | AG31: 5 | AH31: Efectivo
B32: CHRISTIAN YUPANGUI | D32: OPSATEL | E32: Aucuechristiany | F32: TV2025.@ | G32: 1 | J32: FIJO | T32: =M32-Q32 -> 0 | AB32: =U32-Y32 -> 0
B33: LIMA JUMA LUIS MIGUEL | D33: OPSATEL | E33: Aucueluisl | F33: TV2025.@ | G33: 1 | J33: FIJO | K33: 6 | T33: =M33-Q33 -> 0 | U33: 6 | X33: 46081 | Y33: 6 | Z33: Pichincha | AB33: =U33-Y33 -> 0 | AC33: 6 | AE33: 46091 | AF33: 46113 | AG33: 12 | AH33: Pichincha | AK33: 6 | AM33: 46122 | AN33: 46113 | AR33: 0
D34: ALQUINGA | E34: Auiosantiagob | F34: TV2024.@ | T34: =M34-Q34 -> 0 | AB34: =U34-Y34 -> 0
A35: 27C | B35: GUSTAVO PALTIN LICORERIA | D35: PATRICIO VIZHCO | E35: Augigustavop | F35: TV2024.@ | G35: 1 | T35: =M35-Q35 -> 0 | AB35: =U35-Y35 -> 0
B36: DON IVAN CASA | E36: Aucueivano | F36: TV2024.@ | T36: =M36-Q36 -> 0 | AB36: =U36-Y36 -> 0
A37: 46C | B37: CHAVEZ ALMEIDA TITO DAVID | C37: 0999388706 | D37: OPSATEL | E37: 46cchavezt | F37: TV2025.@ | G37: 1 | J37: NUEVO | T37: =M37-Q37 -> 0 | AB37: =U37-Y37 -> 0
A38: 47C | B38: PESANTEZ GAVILANES DARWIN ISRAEL | C38: 0991046372 | D38: OPSATEL | E38: Aucuepesantezd | F38: TV2025.@ | G38: 2 | I38: RECOMENDADO DON RODOLFO | J38: NUEVO | M38: 4 | P38: 46037 | Q38: 4 | R38: Pichincha | T38: =M38-Q38 -> 0 | U38: 4 | X38: 46037 | Y38: 4 | Z38: Pichincha | AB38: =U38-Y38 -> 0 | AC38: 4 | AE38: 46091 | AF38: 46099 | AG38: 4 | AH38: Pichincha | AJ38: =AC38-AG38 -> 0 | AK38: 4 | AM38: 46122 | AN38: 46122 | AO38: 4 | AP38: Pichincha
A39: 49C | B39: ZARUMA QUITUIZACA ELVIS GEOVANNY | D39: OPSATEL | E39: 49czarumae | F39: TV2025.@ | G39: 1 | M39: 100 | P39: 46041 | Q39: 100 | R39: Pichincha | T39: =M39-Q39 -> 0 | U39: 100 | X39: 46041 | AB39: =U39-Y39 -> 100 | AE39: 46094 | AF39: 46094 | AG39: 100 | AH39: Pichincha
A40: 50C | B40: BARROS PIEDAD | C40: 999235418 | D40: PATRICIO VIZHCO | E40: 50cbarrosp | F40: TV2025.@ | G40: 1 | J40: NUEVO | T40: =M40-Q40 -> 0 | AB40: =U40-Y40 -> 0
B41: JACHERO CISNEROS JUAN ALBERTO | M41: 4 | P41: 46043 | Q41: 8 | R41: JEP | T41: =M41-Q41 -> -4 | U41: 4 | X41: 46043 | AB41: 0 | AC41: 4 | AE41: 46091 | AF41: 46088 | AG41: 8 | AH41: JEP | AJ41: =AC41-AG41 -> -4
A42: 52C | B42: ZUIN MELGAR ESTEBAN PAUL (TECNICO) | D42: OPSATEL | E42: 52czuinp | F42: TV2025.@ | G42: 2 | I42: CUENTA PARA PAUL TECNICO | T42: =M42-Q42 -> 0 | AB42: =U42-Y42 -> 0
A43: 53C | B43: ARPI ARPI LINO VINICIO | C43: 0986541656 | D43: OPSATEL | E43: 53carpil | F43: TV2025.@ | G43: 1 | T43: =M43-Q43 -> 0 | AB43: =U43-Y43 -> 0 | AC43: 4 | AE43: 46120 | AF43: 46120 | AG43: 4 | AH43: Pichincha | AK43: 4 | AM43: 46122 | AN43: 46120 | AO43: 4 | AP43: Pichincha
A44: 54C | B44: FANNY MINCHALO | E44: 54cminchalof | T44: =M44-Q44 -> 0 | AB44: =U44-Y44 -> 0
A45: 55C | B45: DANIEL SUAREZ | T45: =M45-Q45 -> 0 | AB45: =U45-Y45 -> 0
A46: 56C | B46: BRYAN ANDRES PAUTE LOJA | T46: =M46-Q46 -> 0 | AB46: =U46-Y46 -> 0
A47: 56C | B47: JOSE ASCUNTAR GUERRERO | C47: 0959680752 | D47: OPSATEL | G47: 35 | J47: ACTIVO | K47: 100 | T47: =M47-Q47 -> 0 | U47: 300 | X47: 46056 | Y47: =100+100+100 -> 300 | Z47: Pichincha | AB47: =U47-Y47 -> 0 | AC47: 200 | AE47: 46091 | AF47: 46089 | AG47: 200 | AH47: Pichincha
A48: 57C | B48: MARIO VASQUEZ | E48: 57cvasquezm | G48: 1 | I48: Ganador sudamericano | T48: =M48-Q48 -> 0 | AB48: =U48-Y48 -> 0
A49: 58C | B49: BRYAN CABRERA | E49: 58ccabrerab | F49: TV2026.@ | G49: 1 | I49: DSPORTS X OPSATV | T49: =M49-Q49 -> 0 | AB49: =U49-Y49 -> 0
A50: 59C | B50: ALVARADO FELIX | E50: 59calvaradof | F50: TV2026.@ | G50: 1 | T50: =M50-Q50 -> 0 | U50: 4 | X50: 46073 | Y50: 4 | Z50: JEP | AB50: =U50-Y50 -> 0
A51: 60C | B51: REMIGIO TORAL | J51: ACTIVO | K51: 6 | L51: SI | T51: =M51-Q51 -> 0 | AB51: 6 | AE51: 46091 | AF51: 46085 | AG51: 6 | AH51: Efectivo | AK51: 6 | AM51: 46122 | AN51: 46122 | AO51: 6 | AP51: Efectivo | AS51: 6 | AU51: 46148 | AV51: 46148 | AW51: 6 | AX51: Efectivo
A52: 61C | B52: MARCELO SIGUA | D52: PATRICIO VIZCHO | E52: 61csiguam | F52: TV2026.@ | G52: 1 | J52: ACTIVO | AK52: 44.8 | AM52: 46124 | AN52: 46124 | AO52: 44.8 | AP52: Pichincha

Sheet BALANCE_FEBRERO_2026
D1: INGRESOS | AI1: PROYECTO CORPORACION
C2: INGRESO BAÑOS | G2: INGRESO SAYAUSI | I2: SR. NORMA | N2: Gastos OPSATEL | S2: ANALISIS | T2: DE CUENTAS | U2: OPSATEL | V2: Lab dBLog | Z2: GASTOS PLATAFORMA | AH2: OPSATEL dBLog
A3: COD-CLI | B3: FECHA DE PAGO | C3: Tipo Efectivo/Transferencia | D3: VALOR | E3: COD-CLI | F3: FECHA DE PAGO | G3: Tipo Efectivo/Transferencia | H3: Fecha Colaborador | I3: N° Comp Depósito | J3: VALOR | M3: item | N3: Descripción | O3: fecha | P3: Tipo Efectivo/Transferencia | Q3: valor | T3: SOBRANTE ANTERIOR MES | U3: OPSATEL | V3: Lab dBLog | W3: Pichincha | Z3: item | AA3: Descripcion | AC3: Fecha | AD3: Tipo Efectivo/Transferencia | AE3: valor | AH3: item | AI3: Descripcion | AK3: Fecha | AL3: Tipo Efectivo/Transferencia | AM3: valor
A4: =BAÑOS!A248 -> 264 | B4: =BAÑOS!AH248 -> 0 | C4: =BAÑOS!AI248 -> 0 | D4: =BAÑOS!AH248 -> 0 | E4: =SAYAUSI!A156 -> 182 | F4: =SAYAUSI!AG156 -> 0 | G4: =SAYAUSI!AI156 -> 0 | J4: =SAYAUSI!AH156 -> 0 | L4: VARIOS | M4: 1 | N4: CAMARA OFICINA | O4: 46055 | P4: Efectivo | Q4: 38 | T4: CAJA CHICA | Y4: GASTOS VARIOS | Z4: 1 | AA4: CLARO PLAN CELU TEC ADMIN | AB4: COTITULARES | AC4: 45389 | AD4: Pichincha | AE4: 37.55 | AH4: 1 | AI4: COLCHON 2025 | AK4: 46027 | AL4: Pichincha | AM4: 1805.35
A5: =BAÑOS!A249 -> 265 | B5: =BAÑOS!AH249 -> 0 | C5: =BAÑOS!AI249 -> 0 | D5: =BAÑOS!AH249 -> 0 | E5: =SAYAUSI!A157 -> 183 | F5: =SAYAUSI!AG157 -> 0 | G5: =SAYAUSI!AI157 -> 0 | J5: =SAYAUSI!AH157 -> 0 | M5: 2 | N5: EMOV TARJ JOHN | O5: 46066 | P5: Efectivo | Q5: =14.37 -> 14.37 | T5: PICHINCHA | W5: PLUS | Z5: 2 | AH5: 2 | AI5: OPSATEL AYUDA TO INVERSIONISTA | AK5: 46204 | AL5: Pichincha | AM5: 400
A6: =BAÑOS!A250 -> 266 | B6: =BAÑOS!AH250 -> 11 | C6: =BAÑOS!AI250 -> Efectivo | D6: =BAÑOS!AH250 -> 11 | E6: =SAYAUSI!A158 -> 184 | F6: =SAYAUSI!AG158 -> 46071 | G6: =SAYAUSI!AI158 -> Efectivo | J6: =SAYAUSI!AH158 -> 8.5 | M6: 3 | N6: AMAZON PRIME TARJ JOHN | O6: 46064 | P6: Efectivo | Q6: =14.99+2.25 -> 17.24 | T6: JEP | W6: Proyectos | Z6: 3 | AA6: PLATAFORMA EXT | AB6: PERSONAL | AC6: 46078 | AD6: Pichincha | AE6: =250+1+0.26+13.33 -> 264.59 | AH6: 1 | AI6: SUDAMERICANO | AK6: 46045 | AL6: Pichincha | AM6: 683
A7: =BAÑOS!A252 -> 268 | B7: =BAÑOS!AH252 -> 4 | C7: =BAÑOS!AI252 -> Efectivo | D7: =BAÑOS!AH252 -> 4 | E7: =SAYAUSI!A159 -> 185 | F7: =SAYAUSI!AG159 -> 46073 | G7: =SAYAUSI!AI159 -> Efectivo | J7: =SAYAUSI!AH159 -> 3.42 | M7: 4 | N7: TARJETA JOHN CONTROL FIRESTICK | O7: 46068 | P7: Efectivo | Q7: =135.1+1.7+0.26 -> 137.06 | T7: SUBTOTAL | Z7: 4 | AA7: DiGITAL OCEAN OPSATEL | AB7: PERSONAL | AC7: 46078 | AD7: Pichincha | AE7: 14.74 | AH7: 2 | AI7: OPSATEL RESERVA ENERO | AK7: 46053 | AL7: Pichincha | AM7: 562.96
A8: =BAÑOS!A253 -> 269 | B8: =BAÑOS!AH253 -> 13.7 | C8: =BAÑOS!AI253 -> Efectivo | D8: =BAÑOS!AH253 -> 13.7 | E8: =SAYAUSI!A160 -> 186 | F8: =SAYAUSI!AG160 -> 0 | G8: =SAYAUSI!AI160 -> 0 | J8: =SAYAUSI!AH160 -> 0 | M8: 5 | N8: CONTRATOS | O8: 46065 | P8: Efectivo | Q8: 9.6 | T8: RESERVA | Z8: 5 | AA8: GOOGLE ONE DRIVE | AB8: PERSONAL | AC8: 46078 | AD8: Pichincha | AE8: =1.99+0.3 -> 2.29 | AH8: 3 | AI8: OPSATEL AYUDA TO INVERSIONISTA | AK8: 46062 | AL8: Pichincha | AM8: 300
A9: =BAÑOS!A254 -> 270 | B9: =BAÑOS!AH253 -> 13.7 | C9: =BAÑOS!AI254 -> 0 | D9: =BAÑOS!AH253 -> 13.7 | E9: =SAYAUSI!A161 -> 187 | F9: =SAYAUSI!AG161 -> 0 | G9: =SAYAUSI!AI161 -> 0 | J9: =SAYAUSI!AH161 -> 0 | M9: 6 | N9: RECARGA TEC | O9: 46072 | P9: Pichincha | Q9: 10 | T9: TOTAL | Z9: 6 | AA9: ZAPING SPORTS | AB9: PERSONAL | AC9: 46078 | AD9: Pichincha | AE9: 17.99 | AH9: 4 | AI9: OPSATEL FEBRERO | AK9: 46081 | AL9: Pichincha | AM9: =Q111 -> 632.55
A10: =BAÑOS!A255 -> 271 | B10: =BAÑOS!AH254 -> 0 | D10: =BAÑOS!AH254 -> 0 | M10: 3 | N10: GECKO | O10: 46063 | P10: Pichincha | Q10: 60 | T10: OPSATEL | V10: Lab dBLog | Z10: 7 | AA10: SMARTONE SR. AYALA | AB10: PERSONAL | AC10: 46078 | AD10: Pichincha | AE10: =3.11+3.11+3.12 -> 9.34 | AH10: 5
A11: =BAÑOS!A256 -> 272 | M11: 4 | N11: CELULAR RECARGA PATRICIO | O11: 46076 | P11: Efectivo | Q11: 1 | S11: Caja CHICA | T11: =D19+D22+J19+J22+H38+U4-Q128 -> 0 | U11: 0 | W11: 0 | Z11: 8 | AA11: VPS | AB11: PERSONAL | AC11: 46078 | AD11: Pichincha | AE11: =41.2+1.14 -> 42.34 | AH11: 6
A12: =BAÑOS!A257 -> 273 | M12: 5 | N12: ACEITE | O12: 46076 | P12: Efectivo | Q12: 8 | S12: PICHINCHA | T12: =D20+D23+J20+J23+H39+U5-Q129 -> 0 | U12: 0 | V12: =AB46 -> 5.6843419e-14 | W12: 0 | Z12: 9 | AA12: ANTRHOPIC | AB12: PERSONAL | AC12: 46078 | AD12: Pichincha | AE12: =5.75+5.75+6.9+6.9+0.9 -> 26.2 | AH12: 7
A13: =BAÑOS!A258 -> 274 | M13: 6 | N13: VARIOS FERRETERIA | O13: 46076 | P13: Efectivo | Q13: 335.64 | S13: JEP | T13: =D21+D24+J21+J24+H40+U6+AE48-Q130 -> 17.25 | U13: 0 | Z13: 10 | AA13: LUZ PLATAFORMA | AB13: PERSONAL | AC13: 46080 | AD13: Pichincha | AE13: 32.36 | AH13: 8
M14: 7 | N14: INSTALACION CLIENTES WILLIAN ZHAGUI | O14: 46076 | P14: Pichincha | Q14: 53 | U14: 0 | AL14: Pichincha | AM14: =SUMIF(AL4:AL13,"Pichincha",AM4:AM13) -> 4383.86
M15: 8 | N15: ARREGLO CAMIONETA | O15: 46079 | P15: Pichincha | Q15: 50 | AG15: GASTOS GENERAL
M16: 9 | N16: ARREGLO VENTANA CAMIONETA | O16: 46079 | P16: Pichincha | Q16: 43.4
M17: 10 | N17: PROTECTOR CELULAR | O17: 46079 | P17: Efectivo | Q17: 5 | S17: TOTAL | T17: =SUM(T11:T13)+V12+V11 -> 17.25 | U17: =SUM(U11:U13)+W12+W11 -> 0 | Z17: 14 | AH17: item | AI17: Descripcion | AK17: Fecha | AL17: Tipo Efectivo/Transferencia | AM17: valor
E18: =SAYAUSI!A75 -> 101 | F18: 46063 | G18: JEP | J18: 3.34 | M18: 11 | N18: COPIAS MATRICULA CAMIONETA | O18: 46079 | P18: Efectivo | Q18: 1.5 | S18: CUENTA AUXILIAR | Z18: 15 | AG18: TECNICO | AH18: 1 | AI18: Pago Enero (Inv N8) | AK18: 46204 | AL18: Pichincha | AM18: 790.41
C19: Efectivo | D19: =SUMIF(BAÑOS!AI2:AI247,C19,BAÑOS!AH2:AH247)+SUMIF(C4:C18,C19,D4:D18) -> 2901.97 | F19: MOVIMIENTOS INTERNOS INGRESOS | I19: Efectivo | J19: =SUMIF(SAYAUSI!AI2:AI152,I19,SAYAUSI!AH2:AH152)+SUMIF(G4:G18,I19,J4:J18) -> 32.04 | M19: 12 | N19: IMPRESIONES | O19: 46079 | P19: Pichincha | Q19: 6.58 | S19: SALDO DISPONIBLE | T19: =T17+V17 -> 17.25 | AD19: Efectivo | AE19: =SUMIF($AD$4:$AD$18,"Efectivo",$AE$4:AE18) -> 0 | AH19: 2 | AI19: Pago Febrero (Inv N9) | AK19: 46062 | AL19: Pichincha | AM19: 790.41
C20: Pichincha | D20: =SUMIF(BAÑOS!AI2:AI247,C20,BAÑOS!AH2:AH247)+SUMIF(C4:C18,C20,D4:D18) -> 839.7 | E20: DE | F20: FECHA DE PAGO | G20: Tipo Efectivo/Transferencia | H20: VALOR | I20: Pichincha | J20: =SUMIF(SAYAUSI!AI2:AI152,I20,SAYAUSI!AH2:AH152)+SUMIF(G4:G18,I20,J4:J18) -> 1495.22 | M20: 13 | N20: camioneta MECANICA | O20: 46081 | P20: Pichincha | Q20: 100.41 | T20: RESERVA PICHINCHA CLIENTES | AD20: Pichincha | AE20: =SUMIF($AD$4:$AD$18,"Pichincha",$AE$4:AE19) -> 447.4 | AH20: 3
C21: JEP | D21: =SUMIF(BAÑOS!AI2:AI247,C21,BAÑOS!AH2:AH247)+SUMIF(C4:C18,C21,D4:D18) -> 706.76 | E21: =P107 -> JEP | F21: =O107 -> 46066 | G21: =N107 -> Pichincha | H21: =Q107-0.41 -> 337.57 | I21: JEP | J21: =SUMIF(SAYAUSI!AI2:AI152,I21,SAYAUSI!AH2:AH152)+SUMIF(G4:G18,I21,J4:J18) -> 1015.76 | M21: 14 | N21: CAMIONETA VENTANA | O21: 46082 | P21: Pichincha | Q21: 12.5 | T21: RESERVA EFECTIVO CLIENTES | AD21: JEP | AE21: =SUMIF($AD$4:$AD$18,"JEP",$AE$4:AE20) -> 0 | AH21: 4
C22: Extra Efectivo | D22: =SUMIF(BAÑOS!AI2:AI247,C22,BAÑOS!AH2:AH247)+SUMIF(C4:C18,C22,D4:D18) -> 0 | E22: =P108 -> Efectivo | F22: =O108 -> 46066 | G22: =N108 -> Pichincha | H22: =Q108-0.41 -> 539.67 | I22: Extra Efectivo | J22: =SUMIF(SAYAUSI!AI2:AI152,I22,SAYAUSI!AH2:AH152)+SUMIF(G4:G18,I22,J4:J18) -> 0 | M22: 1 | AH22: 5
C23: Extra Pichincha | D23: =SUMIF(BAÑOS!AI2:AI247,C23,BAÑOS!AH2:AH247)+SUMIF(C4:C18,C23,D4:D18) -> 0 | E23: =AA25 -> Pichincha | F23: =AB25 -> 46066 | G23: =AD25 -> Pichincha | H23: =AE25 -> 70.45 | I23: Extra Pichincha | J23: =SUMIF(SAYAUSI!AI2:AI152,I23,SAYAUSI!AH2:AH152)+SUMIF(G4:G18,I23,J4:J18) -> 0 | M23: 2 | T23: RECAUDAR | U23: CLIENTES | V23: RECAUDADO | W23: CARTERA X VENCER | AA23: MOVIMIENTOS INTERNOS | AH23: 6
C24: Extra JEP | D24: =SUMIF(BAÑOS!AI2:AI247,C24,BAÑOS!AH2:AH247)+SUMIF(C4:C18,C24,D4:D18) -> 0 | E24: Pichincha | F24: 46078 | G24: Pichincha | H24: =AE26 -> 184.95 | I24: Extra JEP | J24: =SUMIF(SAYAUSI!AI2:AI152,I24,SAYAUSI!AH2:AH152)+SUMIF(G4:G18,I24,J4:J18) -> 0 | M24: 3 | S24: BAÑOS TOTAL | T24: =SUM(BAÑOS!IY2:IY207)+SUM(BAÑOS!JA2:JA207)+SUM(BAÑOS!JB2:JB207) -> 0 | U24: =COUNTIF(BAÑOS!JA2:JA207,"<>") -> 0 | V24: =SUM(BAÑOS!HQ2:HQ185)+SUM(BAÑOS!HS2:HS185) -> 0 | W24: =SUMIF(BAÑOS!HR2:HR185,"",BAÑOS!HU6:HU185) -> 0 | Z24: item | AA24: BANK | AC24: Fecha | AD24: BANK | AE24: valor | AH24: 7
C25: Reserva Pichincha | D25: =SUMIF(BAÑOS!AI2:AI247,C25,BAÑOS!AH2:AH247)+SUMIF(C4:C18,C25,D4:D18) -> 0 | E25: Pichincha | F25: 46078 | G25: Pichincha | H25: =AE27 -> 216.15 | I25: Reserva Pichincha | J25: =SUMIF(SAYAUSI!AI2:AI152,I25,SAYAUSI!AH2:AH152)+SUMIF(G4:G18,I25,J4:J18) -> 0 | L25: SUDA | M25: 1 | S25: SAYAUSI TOTAL | T25: =SUM(SAYAUSI!JR2:JR115)+SUM(SAYAUSI!JT2:JT115)+SUM(SAYAUSI!JU2:JU115) -> 0 | U25: =COUNTIF(SAYAUSI!JT2:JT115,"<>") -> 0 | V25: =SUM(SAYAUSI!ID2:ID109)+SUM(SAYAUSI!IG2:IG109) -> 0 | W25: =SUMIF(SAYAUSI!ID2:ID109,"",SAYAUSI!II2:II109) -> 0 | Y25: TRANSF EGRESOS | Z25: 1 | AA25: Pichincha | AB25: 46066 | AC25: 46066 | AD25: Pichincha | AE25: 70.45 | AH25: 8
C26: Reserva Efectivo | D26: =SUMIF(BAÑOS!AI2:AI247,C26,BAÑOS!AH2:AH247)+SUMIF(C4:C18,C26,D4:D18) -> 0 | E26: Efectivo | F26: 46080 | G26: Pichincha | H26: =Q109-0.41 -> 1708.11 | I26: Reserva Efectivo | J26: =SUMIF(SAYAUSI!AI2:AI152,I26,SAYAUSI!AH2:AH152)+SUMIF(G4:G18,I26,J4:J18) -> 0 | M26: 2 | S26: PREPAGO | T26: =SUM(D4:D18)+SUM(J4:J18) -> 57.66 | Z26: 2 | AA26: Pichincha | AB26: 46078 | AC26: 46078 | AD26: Pichincha | AE26: 184.95 | AH26: 9
C27: TOTAL | D27: =SUM(D19:D26) -> 4448.43 | E27: JEP | F27: 46080 | G27: Pichincha | H27: =Q110-0.41 -> 904.71 | I27: TOTAL | J27: =SUM(J19:J26) -> 2543.02 | M27: 3 | S27: dBLog PLUS | T27: =SUM(PLATAFORMA!BK2:BK38) -> 0 | Z27: 3 | AA27: Pichincha | AB27: 46078 | AC27: 46078 | AD27: Pichincha | AE27: 216.15 | AH27: 10
L28: HELP PROYECTO | M28: 1 | Z28: 4 | AH28: 11
M29: 2 | Z29: 5 | AH29: 12
M30: 3 | S30: TOTAL | T30: =SUM(T24:T29) -> 57.66 | U30: =SUM(U24:U25) -> 0 | Z30: 6 | AH30: 13 | AI30: Arrendamiento Postes | AK30: 46036 | AL30: Pichincha | AM30: 1015.45
L31: INVERSION CLIENTES NUEVOS | M31: 1 | S31: GASTOS | T31: =SUM(Q4:Q100)+SUM(AE4:AE18) -> 7023.03 | Z31: 7 | AH31: 14 | AI31: Retencion preyecto ETAPA | AK31: 46049 | AL31: Pichincha | AM31: =437.61+0.5 -> 438.11
M32: 2 | Z32: 8 | AH32: 15
M33: 1 | S33: A FAVOR OPSATEL | T33: =T30-T31 -> -6965.37 | Z33: 9 | AH33: 16
M34: 2 | Y34: TRANSF INGRESOS | Z34: 1 | AH34: 1
M35: 3 | Z35: 2 | AH35: 2
M36: 4 | T36: LIMA | U36: LLERENA | V36: SOLANO | W36: ZUIN | Z36: 3 | AH36: 3
M37: 5 | S37: ADELANTO1 | T37: 10 | Z37: 4 | AH37: 4
G38: Efectivo | H38: =SUMIF(G21:G37,"Efectivo",H21:H37) -> 0 | M38: 6 | S38: OPSATEL | T38: 350 | U38: 360 | V38: 360 | Z38: 5 | AH38: 5
G39: Trans Pichincha | H39: =SUMIF(G21:G37,"Pichincha",H21:H37) -> 3961.61 | M39: 7 | S39: ENTREGADO | Z39: 6 | AH39: 6
G40: Trans JEP | H40: =SUMIF(G21:G37,"JEP",H21:H37) -> 0 | L40: PRESTAMOS | M40: 1 | S40: ADELANTO 1 | AD40: Efectivo EGRESOS | AE40: =SUMIF($AD$25:$AD$33,"Efectivo",$AE$25:$AE$33) -> 0 | AH40: 1
G41: Total Efectivo | H41: =D19+H38+J19 -> 2934.01 | M41: 2 | S41: ADELANTO 2 | AD41: Pichincha EGRESOS | AE41: =SUMIF($AD$25:$AD$33,"Pichincha",$AE$25:$AE$33) -> 471.55 | AH41: 2
G42: Total Trans Pichincha | H42: =D20+H39+J20 -> 6296.53 | M42: 3 | S42: ADELANTO | T42: 5.25 | U42: 18.5 | V42: 17.25 | AD42: JEP EGRESOS | AE42: =SUMIF($AD$25:$AD$33,"JEP",$AE$25:$AE$33) -> 0 | AH42: 3
G43: Total Trans JEP | H43: =D21+H40+J21 -> 1722.52 | M43: 4 | S43: ADELANTO 2 | T43: 2 | AD43: Efetivo INGRESOS | AE43: =SUMIF($AD$34:$AD$39,"Efectivo",$AE$34:$AE$39) -> 0 | AH43: 4
